Workbook
Name File_Name: OFFSET(#REF!,0,0,1,1)
Name File_Name: OFFSET(#REF!,0,0,1,1)
Name File_Name: OFFSET(#REF!,0,0,1,1)
Name File_Name: OFFSET(#REF!,0,0,1,1)
Name File_Name: OFFSET(#REF!,0,0,1,1)
Name File_Name: OFFSET(#REF!,0,0,1,1)
Name File_Name: OFFSET(#REF!,0,0,1,1)
Name File_Name: OFFSET(#REF!,0,0,1,1)
Name File_Name: OFFSET(#REF!,0,0,1,1)
Name File_Name: OFFSET(#REF!,0,0,1,1)
Name File_Name: OFFSET(#REF!,0,0,1,1)
Name File_Name: OFFSET(#REF!,0,0,1,1)
Name File_Name: OFFSET(#REF!,0,0,1,1)
Name File_Name: OFFSET(#REF!,0,0,1,1)
Name File_Name: OFFSET(#REF!,0,0,1,1)
Name File_Name: OFFSET(#REF!,0,0,1,1)
Name File_Name: OFFSET(#REF!,0,0,1,1)
Name File_Name: OFFSET(#REF!,0,0,1,1)
Name File_Name: OFFSET(#REF!,0,0,1,1)
Name File_Name: OFFSET(#REF!,0,0,1,1)
Name File_Name: OFFSET(#REF!,0,0,1,1)
Name File_Name: OFFSET(#REF!,0,0,1,1)
Name File_Name: OFFSET(#REF!,0,0,1,1)
Name File_Name: OFFSET(#REF!,0,0,1,1)
Name File_Name: OFFSET(#REF!,0,0,1,1)
Name File_Name: OFFSET(#REF!,0,0,1,1)
Name File_Name: OFFSET(#REF!,0,0,1,1)
Name File_Name: OFFSET(#REF!,0,0,1,1)
Name File_Name: OFFSET(#REF!,0,0,1,1)
Name pepe1: OFFSET(#REF!,0,0,1,1)
Name pepe1: OFFSET(#REF!,0,0,1,1)
Name pepe1: OFFSET(#REF!,0,0,1,1)
Name pepe1: OFFSET(#REF!,0,0,1,1)
Name pepe1: OFFSET(#REF!,0,0,1,1)
Name pepe1: OFFSET(#REF!,0,0,1,1)
Name pepe1: OFFSET(#REF!,0,0,1,1)
Name pepe1: OFFSET(#REF!,0,0,1,1)
Name pepe1: OFFSET(#REF!,0,0,1,1)
Name pepe1: OFFSET(#REF!,0,0,1,1)
Name pepe1: OFFSET(#REF!,0,0,1,1)
Name pepe1: OFFSET(#REF!,0,0,1,1)
Name pepe1: OFFSET(#REF!,0,0,1,1)
Name pepe1: OFFSET(#REF!,0,0,1,1)
Name pepe1: OFFSET(#REF!,0,0,1,1)
Name pepe1: OFFSET(#REF!,0,0,1,1)
Name pepe1: OFFSET(#REF!,0,0,1,1)
Name pepe1: OFFSET(#REF!,0,0,1,1)
Name pepe1: OFFSET(#REF!,0,0,1,1)
Name pepe1: OFFSET(#REF!,0,0,1,1)
Name pepe1: OFFSET(#REF!,0,0,1,1)
Name pepe1: OFFSET(#REF!,0,0,1,1)
Name pepe1: OFFSET(#REF!,0,0,1,1)
Name pepe1: OFFSET(#REF!,0,0,1,1)
Name pepe1: OFFSET(#REF!,0,0,1,1)
Name pepe1: OFFSET(#REF!,0,0,1,1)
Name pepe1: OFFSET(#REF!,0,0,1,1)
Name pepe1: OFFSET(#REF!,0,0,1,1)
Name pepe1: OFFSET(#REF!,0,0,1,1)
Name run: OFFSET(#REF!,0,0,1,1)
Name run: OFFSET(#REF!,0,0,1,1)

Sheet 2026R
C2: MENSUAL | S2: ACUMULADO
A5: ESTADO DE RESULTADOS | C5: P2K | D5: PSP | E5: PRG | F5: PC | G5: PLA | H5: PSI | I5: PPA | J5: PPB | K5: CBA | L5: TORR | M5: HOT | N5: PV | O5: DEPTOS | P5: PLP | Q5: PE | S5: P2K | T5: PSP | U5: PRG | V5: PC | W5: PLA | X5: PSI | Y5: PPA | Z5: PPB | AA5: CBA | AB5: TORR | AC5: HOT | AD5: PV | AE5: DEPTOS | AF5: PLP | AG5: PE | AI5: TOTAL | AJ5: TOTAL
A6: 2026R | AI6: MENSUAL | AJ6: ACUMULADO
A8: INGRESOS BRUTOS
A10: Ingresos por Operación de Plazas: | C10: =+SUM(C11:C19) -> 16261771 | D10: =+SUM(D11:D19) -> 9457039.9 | E10: =+SUM(E11:E19) -> 10802671 | F10: =+SUM(F11:F19) -> 857264.25 | G10: =+SUM(G11:G19) -> 0 | H10: =+SUM(H11:H19) -> 5395703.8 | I10: =+SUM(I11:I19) -> 993670.92 | J10: =+SUM(J11:J19) -> 0 | ... Q10: =+SUM(Q11:Q19) -> 2222465.7 | S10: =+SUM(S11:S19) -> 94962221 | T10: =+SUM(T11:T19) -> 55997212 | U10: =+SUM(U11:U19) -> 65848762 | V10: =+SUM(V11:V19) -> 5198522.2 | W10: =+SUM(W11:W19) -> 0 | X10: =+SUM(X11:X19) -> 34333619 | Y10: =+SUM(Y11:Y19) -> 6014245.2 | Z10: =+SUM(Z11:Z19) -> 0 | ... AG10: =+SUM(AG11:AG19) -> 14235942 | AI10: =+SUM(AI11:AI19) -> 84164402 | AJ10: =+SUM(AJ11:AJ19) -> 4.7715293e+08
A11: Renta Mínima | C11: 10624960 | D11: 6502731.3 | E11: 8191397.2 | F11: 735279.23 | G11: 0 | H11: 4223243.9 | I11: 872047.28 | J11: 0 | K11: 7610603.7 | L11: 7256017.1 | M11: 166822.77 | N11: 9643025.2 | O11: 0 | P11: 1978265.4 | Q11: 1610604.8 | S11: 63008168 | T11: 39249345 | U11: 50265100 | V11: 4411601.7 | W11: 0 | X11: 26867364 | Y11: 5237999.2 | Z11: 0 | AA11: 42563517 | AB11: 43222989 | AC11: 994996.91 | AD11: 36263034 | AE11: 0 | AF11: 11791932 | AG11: 9658099 | AI11: =+SUM(C11:Q11) -> 59414998 | AJ11: =+SUM(S11:AG11) -> 3.3353415e+08
A12: Renta Variable | C12: 1096856.1 | D12: 354412.68 | E12: 154073.93 | F12: 30687.47 | G12: 0 | H12: 29414.38 | I12: 21969.12 | J12: 0 | K12: 3084110.3 | L12: 386300.98 | M12: 65333.84 | N12: 472988.09 | O12: 0 | P12: 56468.4 | Q12: 352526.19 | S12: 5936802 | T12: 2149334.7 | U12: 1601322.1 | V12: 237997.13 | W12: 0 | X12: 457853.33 | Y12: 184504.06 | Z12: 0 | AA12: 19593344 | AB12: 2316884 | AC12: 242195.82 | AD12: 2679393 | AE12: 0 | AF12: 342695.48 | AG12: 2955235.6 | AI12: =+SUM(C12:Q12) -> 6105141.4 | AJ12: =+SUM(S12:AG12) -> 38697561
A13: Cuota de Mantenimiento | C13: 1391476.5 | D13: 916164.79 | E13: 1104314.2 | F13: 88845.35 | G13: 0 | H13: 560791.49 | I13: 99654.52 | J13: 0 | K13: 1271254.2 | L13: 965185.71 | M13: 16682.28 | N13: 757344.31 | O13: 0 | P13: 299851.17 | Q13: 259334.7 | S13: 8458764.7 | T13: 5547740 | U13: 6800608.1 | V13: 534210.17 | W13: 0 | X13: 3723919.4 | Y13: 591742.03 | Z13: 0 | AA13: 7346878.5 | AB13: 5727815.6 | AC13: 99499.71 | AD13: 4491185.6 | AE13: 0 | AF13: 1779469.7 | AG13: 1622607.2 | AI13: =+SUM(C13:Q13) -> 7730899.1 | AJ13: =+SUM(S13:AG13) -> 46724441
A14: Publicidad | C14: 4990.32 | D14: 0 | E14: 13081.09 | F14: 2452.2 | G14: 0 | H14: 2899.78 | I14: 0 | J14: 0 | K14: 0 | L14: 0 | M14: 0 | N14: 0 | O14: 0 | P14: 523.19 | Q14: 0 | S14: 30319.17 | T14: 0 | U14: 78486.54 | V14: 14713.2 | W14: 0 | X14: 17398.68 | Y14: 0 | Z14: 0 | AA14: 0 | AB14: 0 | AC14: 0 | AD14: 0 | AE14: 0 | AF14: 3139.14 | AG14: 0 | AI14: =+SUM(C14:Q14) -> 23946.58 | AJ14: =+SUM(S14:AG14) -> 144056.73
A15: Estacionamiento | C15: 3046278.6 | D15: 1664810.2 | E15: 1297657.4 | F15: 0 | G15: 0 | H15: 573992.25 | I15: 0 | J15: 0 | K15: 2212106.1 | L15: 117739 | M15: 0 | N15: 1120573.3 | O15: 0 | P15: 0 | Q15: 0 | S15: 17133305 | T15: 8927194.6 | U15: 6964036 | V15: 0 | W15: 0 | X15: 2994929.3 | Y15: 0 | Z15: 0 | AA15: 11301441 | AB15: 706434 | AC15: 0 | AD15: 5922929.2 | AE15: 0 | AF15: 0 | AG15: 0 | AI15: =+SUM(C15:Q15) -> 10033157 | AJ15: =+SUM(S15:AG15) -> 53950270
A16: Cuotas Condominales | C16: 0 | D16: 0 | E16: 0 | F16: 0 | G16: 0 | H16: 0 | I16: 0 | J16: 0 | K16: 0 | L16: 0 | M16: 0 | N16: 44486.45 | O16: 112937 | P16: 133435.63 | Q16: 0 | S16: 0 | T16: 0 | U16: 0 | V16: 0 | W16: 0 | X16: 0 | Y16: 0 | Z16: 0 | AA16: 0 | AB16: 0 | AC16: 0 | AD16: 228384.81 | AE16: 456329 | AF16: 821048.09 | AG16: 0 | AI16: =+SUM(C16:Q16) -> 290859.08 | AJ16: =+SUM(S16:AG16) -> 1505761.9
A17: Guantes | C17: 58850.37 | D17: 18920.88 | E17: 16063.05 | F17: 0 | G17: 0 | H17: 5361.95 | I17: 0 | J17: 0 | K17: 210267.31 | L17: 0 | M17: 0 | N17: 19324.07 | O17: 0 | P17: 1967.82 | Q17: 0 | S17: 356502.43 | T17: 123597.55 | U17: 87040.4 | V17: 0 | W17: 0 | X17: 32171.7 | Y17: 0 | Z17: 0 | AA17: 1210903.1 | AB17: 0 | AC17: 0 | AD17: 120820.79 | AE17: 0 | AF17: 10649.58 | AG17: 0 | AI17: =+SUM(C17:Q17) -> 330755.45 | AJ17: =+SUM(S17:AG17) -> 1941685.5
A18: Penalizaciones | C18: 38359.08 | D18: 0 | E18: 26084.57 | F18: 0 | G18: 0 | H18: 0 | I18: 0 | J18: 0 | K18: 0 | L18: 0 | M18: 0 | N18: 0 | O18: 0 | P18: 43934.24 | Q18: 0 | S18: 38359.08 | T18: 0 | U18: 52169.14 | V18: 0 | W18: 0 | X18: 172414 | Y18: 0 | Z18: 0 | AA18: 0 | AB18: 0 | AC18: 0 | AD18: 0 | AE18: 0 | AF18: 43934.24 | AG18: 0 | AI18: =+SUM(C18:Q18) -> 108377.89 | AJ18: =+SUM(S18:AG18) -> 306876.46
A19: Otros Ingresos Operativos de Plazas | C19: 0 | D19: 0 | E19: 0 | F19: 0 | G19: 0 | H19: 0 | I19: 0 | J19: 0 | K19: 126268 | L19: 0 | M19: 0 | N19: 0 | O19: 0 | P19: 0 | Q19: 0 | S19: 0 | T19: 0 | U19: 0 | V19: 0 | W19: 0 | X19: 67568.96 | Y19: 0 | Z19: 0 | AA19: 280560.31 | AB19: 0 | AC19: 0 | AD19: 0 | AE19: 0 | AF19: 0 | AG19: 0 | AI19: =+SUM(C19:Q19) -> 126268 | AJ19: =+SUM(S19:AG19) -> 348129.27
A20: Ingresos por Servicios: | C20: =+SUM(C21:C29) -> 0 | D20: =+SUM(D21:D29) -> 0 | E20: =+SUM(E21:E29) -> 0 | F20: =+SUM(F21:F29) -> 0 | G20: =+SUM(G21:G29) -> 0 | H20: =+SUM(H21:H29) -> 0 | I20: =+SUM(I21:I29) -> 0 | J20: =+SUM(J21:J29) -> 0 | ... Q20: =+SUM(Q21:Q29) -> 0 | S20: =+SUM(S21:S29) -> 0 | T20: =+SUM(T21:T29) -> 0 | U20: =+SUM(U21:U29) -> 0 | V20: =+SUM(V21:V29) -> 0 | W20: =+SUM(W21:W29) -> 0 | X20: =+SUM(X21:X29) -> 0 | Y20: =+SUM(Y21:Y29) -> 0 | Z20: =+SUM(Z21:Z29) -> 0 | ... AG20: =+SUM(AG21:AG29) -> 0 | AI20: =+SUM(AI21:AI29) -> 0 | AJ20: =+SUM(AJ21:AJ29) -> 0
A21: Administración de Nómina | C21: 0 | D21: 0 | E21: 0 | F21: 0 | G21: 0 | H21: 0 | I21: 0 | J21: 0 | K21: 0 | L21: 0 | M21: 0 | N21: 0 | O21: 0 | P21: 0 | Q21: 0 | S21: 0 | T21: 0 | U21: 0 | V21: 0 | W21: 0 | X21: 0 | Y21: 0 | Z21: 0 | AA21: 0 | AB21: 0 | AC21: 0 | AD21: 0 | AE21: 0 | AF21: 0 | AG21: 0 | AI21: =+SUM(R21:AF21) -> 0 | AJ21: =+SUM(S21:AG21) -> 0
A22: Apertura/Cierre de Contratos | C22: 0 | D22: 0 | E22: 0 | F22: 0 | G22: 0 | H22: 0 | I22: 0 | J22: 0 | K22: 0 | L22: 0 | M22: 0 | N22: 0 | O22: 0 | P22: 0 | Q22: 0 | S22: 0 | T22: 0 | U22: 0 | V22: 0 | W22: 0 | X22: 0 | Y22: 0 | Z22: 0 | AA22: 0 | AB22: 0 | AC22: 0 | AD22: 0 | AE22: 0 | AF22: 0 | AG22: 0 | AI22: =+SUM(R22:AF22) -> 0 | AJ22: =+SUM(S22:AG22) -> 0
A23: Renovación de Contratos | C23: 0 | D23: 0 | E23: 0 | F23: 0 | G23: 0 | H23: 0 | I23: 0 | J23: 0 | K23: 0 | L23: 0 | M23: 0 | N23: 0 | O23: 0 | P23: 0 | Q23: 0 | S23: 0 | T23: 0 | U23: 0 | V23: 0 | W23: 0 | X23: 0 | Y23: 0 | Z23: 0 | AA23: 0 | AB23: 0 | AC23: 0 | AD23: 0 | AE23: 0 | AF23: 0 | AG23: 0 | AI23: =+SUM(R23:AF23) -> 0 | AJ23: =+SUM(S23:AG23) -> 0
A24: Administración de Obra | C24: 0 | D24: 0 | E24: 0 | F24: 0 | G24: 0 | H24: 0 | I24: 0 | J24: 0 | K24: 0 | L24: 0 | M24: 0 | N24: 0 | O24: 0 | P24: 0 | Q24: 0 | S24: 0 | T24: 0 | U24: 0 | V24: 0 | W24: 0 | X24: 0 | Y24: 0 | Z24: 0 | AA24: 0 | AB24: 0 | AC24: 0 | AD24: 0 | AE24: 0 | AF24: 0 | AG24: 0 | AI24: =+SUM(R24:AF24) -> 0 | AJ24: =+SUM(S24:AG24) -> 0
A25: Administración de Plaza | C25: 0 | D25: 0 | E25: 0 | F25: 0 | G25: 0 | H25: 0 | I25: 0 | J25: 0 | K25: 0 | L25: 0 | M25: 0 | N25: 0 | O25: 0 | P25: 0 | Q25: 0 | S25: 0 | T25: 0 | U25: 0 | V25: 0 | W25: 0 | X25: 0 | Y25: 0 | Z25: 0 | AA25: 0 | AB25: 0 | AC25: 0 | AD25: 0 | AE25: 0 | AF25: 0 | AG25: 0 | AI25: =+SUM(R25:AF25) -> 0 | AJ25: =+SUM(S25:AG25) -> 0
A26: Consultoría | C26: 0 | D26: 0 | E26: 0 | F26: 0 | G26: 0 | H26: 0 | I26: 0 | J26: 0 | K26: 0 | L26: 0 | M26: 0 | N26: 0 | O26: 0 | P26: 0 | Q26: 0 | S26: 0 | T26: 0 | U26: 0 | V26: 0 | W26: 0 | X26: 0 | Y26: 0 | Z26: 0 | AA26: 0 | AB26: 0 | AC26: 0 | AD26: 0 | AE26: 0 | AF26: 0 | AG26: 0 | AI26: =+SUM(R26:AF26) -> 0 | AJ26: =+SUM(S26:AG26) -> 0
A27: Renta de Terrenos | C27: 0 | D27: 0 | E27: 0 | F27: 0 | G27: 0 | H27: 0 | I27: 0 | J27: 0 | K27: 0 | L27: 0 | M27: 0 | N27: 0 | O27: 0 | P27: 0 | Q27: 0 | S27: 0 | T27: 0 | U27: 0 | V27: 0 | W27: 0 | X27: 0 | Y27: 0 | Z27: 0 | AA27: 0 | AB27: 0 | AC27: 0 | AD27: 0 | AE27: 0 | AF27: 0 | AG27: 0 | AI27: =+SUM(R27:AF27) -> 0 | AJ27: =+SUM(S27:AG27) -> 0
A28: Operación de Hotel | C28: 0 | D28: 0 | E28: 0 | F28: 0 | G28: 0 | H28: 0 | I28: 0 | J28: 0 | K28: 0 | L28: 0 | M28: 0 | N28: 0 | O28: 0 | P28: 0 | Q28: 0 | S28: 0 | T28: 0 | U28: 0 | V28: 0 | W28: 0 | X28: 0 | Y28: 0 | Z28: 0 | AA28: 0 | AB28: 0 | AC28: 0 | AD28: 0 | AE28: 0 | AF28: 0 | AG28: 0 | AI28: =+SUM(R28:AF28) -> 0 | AJ28: =+SUM(S28:AG28) -> 0
A29: Otros Servicios | C29: 0 | D29: 0 | E29: 0 | F29: 0 | G29: 0 | H29: 0 | I29: 0 | J29: 0 | K29: 0 | L29: 0 | M29: 0 | N29: 0 | O29: 0 | P29: 0 | Q29: 0 | S29: 0 | T29: 0 | U29: 0 | V29: 0 | W29: 0 | X29: 0 | Y29: 0 | Z29: 0 | AA29: 0 | AB29: 0 | AC29: 0 | AD29: 0 | AE29: 0 | AF29: 0 | AG29: 0 | AI29: =+SUM(R29:AF29) -> 0 | AJ29: =+SUM(S29:AG29) -> 0
A31: Total Ingresos Brutos | C31: =+C10+C20 -> 16261771 | D31: =+D10+D20 -> 9457039.9 | E31: =+E10+E20 -> 10802671 | F31: =+F10+F20 -> 857264.25 | G31: =+G10+G20 -> 0 | H31: =+H10+H20 -> 5395703.8 | I31: =+I10+I20 -> 993670.92 | J31: =+J10+J20 -> 0 | ... Q31: =+Q10+Q20 -> 2222465.7 | S31: =+S10+S20 -> 94962221 | T31: =+T10+T20 -> 55997212 | U31: =+U10+U20 -> 65848762 | V31: =+V10+V20 -> 5198522.2 | W31: =+W10+W20 -> 0 | X31: =+X10+X20 -> 34333619 | Y31: =+Y10+Y20 -> 6014245.2 | Z31: =+Z10+Z20 -> 0 | ... AG31: =+AG10+AG20 -> 14235942 | AI31: =+AI10+AI20 -> 84164402 | AJ31: =+AJ10+AJ20 -> 4.7715293e+08
A33: BONIFICACIONES SOBRE INGRESOS
A35: Ingresos por Operación de Plazas: | C35: =+SUM(C36:C44) -> 0 | D35: =+SUM(D36:D44) -> 8627.5 | E35: =+SUM(E36:E44) -> 36267.56 | F35: =+SUM(F36:F44) -> 0 | G35: =+SUM(G36:G44) -> 0 | H35: =+SUM(H36:H44) -> 142551.72 | I35: =+SUM(I36:I44) -> 0 | J35: =+SUM(J36:J44) -> 0 | ... Q35: =+SUM(Q36:Q44) -> 0 | S35: =+SUM(S36:S44) -> 203155.79 | T35: =+SUM(T36:T44) -> 70832.42 | U35: =+SUM(U36:U44) -> 179325.4 | V35: =+SUM(V36:V44) -> 9378.96 | W35: =+SUM(W36:W44) -> 0 | X35: =+SUM(X36:X44) -> 1294687.7 | Y35: =+SUM(Y36:Y44) -> 0 | Z35: =+SUM(Z36:Z44) -> 0 | ... AG35: =+SUM(AG36:AG44) -> 0 | AI35: =+SUM(AI36:AI44) -> 658832.06 | AJ35: =+SUM(AJ36:AJ44) -> 4250676.8
A36: Renta Mínima | C36: 0 | D36: 8627.5 | E36: 30222.97 | F36: 0 | G36: 0 | H36: 142551.72 | I36: 0 | J36: 0 | K36: 187032.51 | L36: 103013.9 | M36: 0 | N36: 167380.79 | O36: 0 | P36: 0 | Q36: 0 | S36: 202866.92 | T36: 66490.97 | U36: 119466.37 | V36: 0 | W36: 0 | X36: 1290478.6 | Y36: 0 | Z36: 0 | AA36: 777417.77 | AB36: 103013.9 | AC36: 0 | AD36: 1559634 | AE36: 0 | AF36: 4466.79 | AG36: 0 | AI36: =+SUM(C36:Q36) -> 638829.39 | AJ36: =+SUM(S36:AG36) -> 4123835.3
A37: Renta Variable | C37: 0 | D37: 0 | E37: 0 | F37: 0 | G37: 0 | H37: 0 | I37: 0 | J37: 0 | K37: 0 | L37: 0 | M37: 0 | N37: 0 | O37: 0 | P37: 0 | Q37: 0 | S37: 0 | T37: 0 | U37: 0 | V37: 0 | W37: 0 | X37: 0 | Y37: 0 | Z37: 0 | AA37: 0 | AB37: 0 | AC37: 11092.38 | AD37: 0 | AE37: 0 | AF37: 0 | AG37: 0 | AI37: =+SUM(C37:Q37) -> 0 | AJ37: =+SUM(S37:AG37) -> 11092.38
A38: Cuota de Mantenimiento | C38: 0 | D38: 0 | E38: 6044.59 | F38: 0 | G38: 0 | H38: 0 | I38: 0 | J38: 0 | K38: 1596.41 | L38: 12361.67 | M38: 0 | N38: 0 | O38: 0 | P38: 0 | Q38: 0 | S38: 288.87 | T38: 4341.45 | U38: 21170.43 | V38: 0 | W38: 0 | X38: 4209.09 | Y38: 0 | Z38: 0 | AA38: 10154.8 | AB38: 26781.67 | AC38: 0 | AD38: 735.23 | AE38: 0 | AF38: 0 | AG38: 0 | AI38: =+SUM(C38:Q38) -> 20002.67 | AJ38: =+SUM(S38:AG38) -> 67681.54
A39: Publicidad | C39: 0 | D39: 0 | E39: 0 | F39: 0 | G39: 0 | H39: 0 | I39: 0 | J39: 0 | K39: 0 | L39: 0 | M39: 0 | N39: 0 | O39: 0 | P39: 0 | Q39: 0 | S39: 0 | T39: 0 | U39: 0 | V39: 0 | W39: 0 | X39: 0 | Y39: 0 | Z39: 0 | AA39: 0 | AB39: 0 | AC39: 0 | AD39: 0 | AE39: 0 | AF39: 0 | AG39: 0 | AI39: =+SUM(C39:Q39) -> 0 | AJ39: =+SUM(S39:AG39) -> 0
A40: Estacionamiento | C40: 0 | D40: 0 | E40: 0 | F40: 0 | G40: 0 | H40: 0 | I40: 0 | J40: 0 | K40: 0 | L40: 0 | M40: 0 | N40: 0 | O40: 0 | P40: 0 | Q40: 0 | S40: 0 | T40: 0 | U40: 0 | V40: 0 | W40: 0 | X40: 0 | Y40: 0 | Z40: 0 | AA40: 0 | AB40: 0 | AC40: 0 | AD40: 0 | AE40: 0 | AF40: 0 | AG40: 0 | AI40: =+SUM(C40:Q40) -> 0 | AJ40: =+SUM(S40:AG40) -> 0
A41: Cuotas Condominales | C41: 0 | D41: 0 | E41: 0 | F41: 0 | G41: 0 | H41: 0 | I41: 0 | J41: 0 | K41: 0 | L41: 0 | M41: 0 | N41: 0 | O41: 0 | P41: 0 | Q41: 0 | S41: 0 | T41: 0 | U41: 0 | V41: 0 | W41: 0 | X41: 0 | Y41: 0 | Z41: 0 | AA41: 0 | AB41: 0 | AC41: 0 | AD41: 0 | AE41: 0 | AF41: 0 | AG41: 0 | AI41: =+SUM(C41:Q41) -> 0 | AJ41: =+SUM(S41:AG41) -> 0
A42: Guantes | C42: 0 | D42: 0 | E42: 0 | F42: 0 | G42: 0 | H42: 0 | I42: 0 | J42: 0 | K42: 0 | L42: 0 | M42: 0 | N42: 0 | O42: 0 | P42: 0 | Q42: 0 | S42: 0 | T42: 0 | U42: 0 | V42: 0 | W42: 0 | X42: 0 | Y42: 0 | Z42: 0 | AA42: 0 | AB42: 0 | AC42: 0 | AD42: 0 | AE42: 0 | AF42: 0 | AG42: 0 | AI42: =+SUM(C42:Q42) -> 0 | AJ42: =+SUM(S42:AG42) -> 0
A43: Penalizaciones | C43: 0 | D43: 0 | E43: 0 | F43: 0 | G43: 0 | H43: 0 | I43: 0 | J43: 0 | K43: 0 | L43: 0 | M43: 0 | N43: 0 | O43: 0 | P43: 0 | Q43: 0 | S43: 0 | T43: 0 | U43: 38688.6 | V43: 9378.96 | W43: 0 | X43: 0 | Y43: 0 | Z43: 0 | AA43: 0 | AB43: 0 | AC43: 0 | AD43: 0 | AE43: 0 | AF43: 0 | AG43: 0 | AI43: =+SUM(C43:Q43) -> 0 | AJ43: =+SUM(S43:AG43) -> 48067.56
A44: Otros Ingresos Operativos de Plazas | C44: 0 | D44: 0 | E44: 0 | F44: 0 | G44: 0 | H44: 0 | I44: 0 | J44: 0 | K44: 0 | L44: 0 | M44: 0 | N44: 0 | O44: 0 | P44: 0 | Q44: 0 | S44: 0 | T44: 0 | U44: 0 | V44: 0 | W44: 0 | X44: 0 | Y44: 0 | Z44: 0 | AA44: 0 | AB44: 0 | AC44: 0 | AD44: 0 | AE44: 0 | AF44: 0 | AG44: 0 | AI44: =+SUM(C44:Q44) -> 0 | AJ44: =+SUM(S44:AG44) -> 0
A45: Ingresos por Servicios: | C45: =+SUM(C46:C54) -> 0 | D45: =+SUM(D46:D54) -> 0 | E45: =+SUM(E46:E54) -> 0 | F45: =+SUM(F46:F54) -> 0 | G45: =+SUM(G46:G54) -> 0 | H45: =+SUM(H46:H54) -> 0 | I45: =+SUM(I46:I54) -> 0 | J45: =+SUM(J46:J54) -> 0 | ... Q45: =+SUM(Q46:Q54) -> 0 | S45: =+SUM(S46:S54) -> 0 | T45: =+SUM(T46:T54) -> 0 | U45: =+SUM(U46:U54) -> 0 | V45: =+SUM(V46:V54) -> 0 | W45: =+SUM(W46:W54) -> 0 | X45: =+SUM(X46:X54) -> 0 | Y45: =+SUM(Y46:Y54) -> 0 | Z45: =+SUM(Z46:Z54) -> 0 | ... AG45: =+SUM(AG46:AG54) -> 0 | AI45: =+SUM(AI46:AI54) -> 0 | AJ45: =+SUM(AJ46:AJ54) -> 0
A46: Administración de Nómina | C46: 0 | D46: 0 | E46: 0 | F46: 0 | G46: 0 | H46: 0 | I46: 0 | J46: 0 | K46: 0 | L46: 0 | M46: 0 | N46: 0 | O46: 0 | P46: 0 | Q46: 0 | S46: 0 | T46: 0 | U46: 0 | V46: 0 | W46: 0 | X46: 0 | Y46: 0 | Z46: 0 | AA46: 0 | AB46: 0 | AC46: 0 | AD46: 0 | AE46: 0 | AF46: 0 | AG46: 0 | AI46: =+SUM(R46:AF46) -> 0 | AJ46: =+SUM(S46:AG46) -> 0
A47: Apertura/Cierre de Contratos | C47: 0 | D47: 0 | E47: 0 | F47: 0 | G47: 0 | H47: 0 | I47: 0 | J47: 0 | K47: 0 | L47: 0 | M47: 0 | N47: 0 | O47: 0 | P47: 0 | Q47: 0 | S47: 0 | T47: 0 | U47: 0 | V47: 0 | W47: 0 | X47: 0 | Y47: 0 | Z47: 0 | AA47: 0 | AB47: 0 | AC47: 0 | AD47: 0 | AE47: 0 | AF47: 0 | AG47: 0 | AI47: =+SUM(R47:AF47) -> 0 | AJ47: =+SUM(S47:AG47) -> 0
A48: Renovación de Contratos | C48: 0 | D48: 0 | E48: 0 | F48: 0 | G48: 0 | H48: 0 | I48: 0 | J48: 0 | K48: 0 | L48: 0 | M48: 0 | N48: 0 | O48: 0 | P48: 0 | Q48: 0 | S48: 0 | T48: 0 | U48: 0 | V48: 0 | W48: 0 | X48: 0 | Y48: 0 | Z48: 0 | AA48: 0 | AB48: 0 | AC48: 0 | AD48: 0 | AE48: 0 | AF48: 0 | AG48: 0 | AI48: =+SUM(R48:AF48) -> 0 | AJ48: =+SUM(S48:AG48) -> 0
A49: Administración de Obra | C49: 0 | D49: 0 | E49: 0 | F49: 0 | G49: 0 | H49: 0 | I49: 0 | J49: 0 | K49: 0 | L49: 0 | M49: 0 | N49: 0 | O49: 0 | P49: 0 | Q49: 0 | S49: 0 | T49: 0 | U49: 0 | V49: 0 | W49: 0 | X49: 0 | Y49: 0 | Z49: 0 | AA49: 0 | AB49: 0 | AC49: 0 | AD49: 0 | AE49: 0 | AF49: 0 | AG49: 0 | AI49: =+SUM(R49:AF49) -> 0 | AJ49: =+SUM(S49:AG49) -> 0
A50: Administración de Plaza | C50: 0 | D50: 0 | E50: 0 | F50: 0 | G50: 0 | H50: 0 | I50: 0 | J50: 0 | K50: 0 | L50: 0 | M50: 0 | N50: 0 | O50: 0 | P50: 0 | Q50: 0 | S50: 0 | T50: 0 | U50: 0 | V50: 0 | W50: 0 | X50: 0 | Y50: 0 | Z50: 0 | AA50: 0 | AB50: 0 | AC50: 0 | AD50: 0 | AE50: 0 | AF50: 0 | AG50: 0 | AI50: =+SUM(R50:AF50) -> 0 | AJ50: =+SUM(S50:AG50) -> 0
A51: Consultoría | C51: 0 | D51: 0 | E51: 0 | F51: 0 | G51: 0 | H51: 0 | I51: 0 | J51: 0 | K51: 0 | L51: 0 | M51: 0 | N51: 0 | O51: 0 | P51: 0 | Q51: 0 | S51: 0 | T51: 0 | U51: 0 | V51: 0 | W51: 0 | X51: 0 | Y51: 0 | Z51: 0 | AA51: 0 | AB51: 0 | AC51: 0 | AD51: 0 | AE51: 0 | AF51: 0 | AG51: 0 | AI51: =+SUM(R51:AF51) -> 0 | AJ51: =+SUM(S51:AG51) -> 0
A52: Renta de Terrenos | C52: 0 | D52: 0 | E52: 0 | F52: 0 | G52: 0 | H52: 0 | I52: 0 | J52: 0 | K52: 0 | L52: 0 | M52: 0 | N52: 0 | O52: 0 | P52: 0 | Q52: 0 | S52: 0 | T52: 0 | U52: 0 | V52: 0 | W52: 0 | X52: 0 | Y52: 0 | Z52: 0 | AA52: 0 | AB52: 0 | AC52: 0 | AD52: 0 | AE52: 0 | AF52: 0 | AG52: 0 | AI52: =+SUM(R52:AF52) -> 0 | AJ52: =+SUM(S52:AG52) -> 0
A53: Operación de Hotel | C53: 0 | D53: 0 | E53: 0 | F53: 0 | G53: 0 | H53: 0 | I53: 0 | J53: 0 | K53: 0 | L53: 0 | M53: 0 | N53: 0 | O53: 0 | P53: 0 | Q53: 0 | S53: 0 | T53: 0 | U53: 0 | V53: 0 | W53: 0 | X53: 0 | Y53: 0 | Z53: 0 | AA53: 0 | AB53: 0 | AC53: 0 | AD53: 0 | AE53: 0 | AF53: 0 | AG53: 0 | AI53: =+SUM(R53:AF53) -> 0 | AJ53: =+SUM(S53:AG53) -> 0
A54: Otros Servicios | C54: 0 | D54: 0 | E54: 0 | F54: 0 | G54: 0 | H54: 0 | I54: 0 | J54: 0 | K54: 0 | L54: 0 | M54: 0 | N54: 0 | O54: 0 | P54: 0 | Q54: 0 | S54: 0 | T54: 0 | U54: 0 | V54: 0 | W54: 0 | X54: 0 | Y54: 0 | Z54: 0 | AA54: 0 | AB54: 0 | AC54: 0 | AD54: 0 | AE54: 0 | AF54: 0 | AG54: 0 | AI54: =+SUM(R54:AF54) -> 0 | AJ54: =+SUM(S54:AG54) -> 0
A56: Total Bonificaciones sobre Ingresos | C56: =+C35+C45 -> 0 | D56: =+D35+D45 -> 8627.5 | E56: =+E35+E45 -> 36267.56 | F56: =+F35+F45 -> 0 | G56: =+G35+G45 -> 0 | H56: =+H35+H45 -> 142551.72 | I56: =+I35+I45 -> 0 | J56: =+J35+J45 -> 0 | ... Q56: =+Q35+Q45 -> 0 | S56: =+S35+S45 -> 203155.79 | T56: =+T35+T45 -> 70832.42 | U56: =+U35+U45 -> 179325.4 | V56: =+V35+V45 -> 9378.96 | W56: =+W35+W45 -> 0 | X56: =+X35+X45 -> 1294687.7 | Y56: =+Y35+Y45 -> 0 | Z56: =+Z35+Z45 -> 0 | ... AG56: =+AG35+AG45 -> 0 | AI56: =+AI35+AI45 -> 658832.06 | AJ56: =+AJ35+AJ45 -> 4250676.8
A58: DEVOLUCIONES SOBRE INGRESOS
A60: Ingresos por Operación de Plazas: | C60: =+SUM(C61:C69) -> 7259.24 | D60: =+SUM(D61:D69) -> 0 | E60: =+SUM(E61:E69) -> 0 | F60: =+SUM(F61:F69) -> 0 | G60: =+SUM(G61:G69) -> 0 | H60: =+SUM(H61:H69) -> 0 | I60: =+SUM(I61:I69) -> 0 | J60: =+SUM(J61:J69) -> 0 | ... Q60: =+SUM(Q61:Q69) -> 0 | S60: =+SUM(S61:S69) -> 44727.81 | T60: =+SUM(T61:T69) -> 0 | U60: =+SUM(U61:U69) -> 319463.56 | V60: =+SUM(V61:V69) -> 0 | W60: =+SUM(W61:W69) -> 0 | X60: =+SUM(X61:X69) -> 357497.08 | Y60: =+SUM(Y61:Y69) -> 0 | Z60: =+SUM(Z61:Z69) -> 0 | ... AG60: =+SUM(AG61:AG69) -> 0 | AI60: =+SUM(AI61:AI69) -> 8239.36 | AJ60: =+SUM(AJ61:AJ69) -> 1240187.1
A61: Renta Mínima | C61: 7259.24 | D61: 0 | E61: 0 | F61: 0 | G61: 0 | H61: 0 | I61: 0 | J61: 0 | K61: 0 | L61: 0 | M61: 0 | N61: 816.77 | O61: 0 | P61: 0 | Q61: 0 | S61: 38379.98 | T61: 0 | U61: 277248.48 | V61: 0 | W61: 0 | X61: 303367.56 | Y61: 0 | Z61: 0 | AA61: 105000 | AB61: 271834.05 | AC61: 0 | AD61: 117200.41 | AE61: 0 | AF61: 0 | AG61: 0 | AI61: =+SUM(C61:Q61) -> 8076.01 | AJ61: =+SUM(S61:AG61) -> 1113030.5
A62: Renta Variable | C62: 0 | D62: 0 | E62: 0 | F62: 0 | G62: 0 | H62: 0 | I62: 0 | J62: 0 | K62: 0 | L62: 0 | M62: 0 | N62: 0 | O62: 0 | P62: 0 | Q62: 0 | S62: 0 | T62: 0 | U62: 0 | V62: 0 | W62: 0 | X62: 0 | Y62: 0 | Z62: 0 | AA62: 0 | AB62: 0 | AC62: 0 | AD62: 0 | AE62: 0 | AF62: 0 | AG62: 0 | AI62: =+SUM(C62:Q62) -> 0 | AJ62: =+SUM(S62:AG62) -> 0
A63: Cuota de Mantenimiento | C63: 0 | D63: 0 | E63: 0 | F63: 0 | G63: 0 | H63: 0 | I63: 0 | J63: 0 | K63: 0 | L63: 0 | M63: 0 | N63: 163.35 | O63: 0 | P63: 0 | Q63: 0 | S63: 6347.83 | T63: 0 | U63: 42215.08 | V63: 0 | W63: 0 | X63: 54129.52 | Y63: 0 | Z63: 0 | AA63: 0 | AB63: 0 | AC63: 0 | AD63: 23440.07 | AE63: 0 | AF63: 1024.14 | AG63: 0 | AI63: =+SUM(C63:Q63) -> 163.35 | AJ63: =+SUM(S63:AG63) -> 127156.64
A64: Publicidad | C64: 0 | D64: 0 | E64: 0 | F64: 0 | G64: 0 | H64: 0 | I64: 0 | J64: 0 | K64: 0 | L64: 0 | M64: 0 | N64: 0 | O64: 0 | P64: 0 | Q64: 0 | S64: 0 | T64: 0 | U64: 0 | V64: 0 | W64: 0 | X64: 0 | Y64: 0 | Z64: 0 | AA64: 0 | AB64: 0 | AC64: 0 | AD64: 0 | AE64: 0 | AF64: 0 | AG64: 0 | AI64: =+SUM(C64:Q64) -> 0 | AJ64: =+SUM(S64:AG64) -> 0
A65: Estacionamiento | C65: 0 | D65: 0 | E65: 0 | F65: 0 | G65: 0 | H65: 0 | I65: 0 | J65: 0 | K65: 0 | L65: 0 | M65: 0 | N65: 0 | O65: 0 | P65: 0 | Q65: 0 | S65: 0 | T65: 0 | U65: 0 | V65: 0 | W65: 0 | X65: 0 | Y65: 0 | Z65: 0 | AA65: 0 | AB65: 0 | AC65: 0 | AD65: 0 | AE65: 0 | AF65: 0 | AG65: 0 | AI65: =+SUM(C65:Q65) -> 0 | AJ65: =+SUM(S65:AG65) -> 0
A66: Cuotas Condominales | C66: 0 | D66: 0 | E66: 0 | F66: 0 | G66: 0 | H66: 0 | I66: 0 | J66: 0 | K66: 0 | L66: 0 | M66: 0 | N66: 0 | O66: 0 | P66: 0 | Q66: 0 | S66: 0 | T66: 0 | U66: 0 | V66: 0 | W66: 0 | X66: 0 | Y66: 0 | Z66: 0 | AA66: 0 | AB66: 0 | AC66: 0 | AD66: 0 | AE66: 0 | AF66: 0 | AG66: 0 | AI66: =+SUM(C66:Q66) -> 0 | AJ66: =+SUM(S66:AG66) -> 0
A67: Guantes | C67: 0 | D67: 0 | E67: 0 | F67: 0 | G67: 0 | H67: 0 | I67: 0 | J67: 0 | K67: 0 | L67: 0 | M67: 0 | N67: 0 | O67: 0 | P67: 0 | Q67: 0 | S67: 0 | T67: 0 | U67: 0 | V67: 0 | W67: 0 | X67: 0 | Y67: 0 | Z67: 0 | AA67: 0 | AB67: 0 | AC67: 0 | AD67: 0 | AE67: 0 | AF67: 0 | AG67: 0 | AI67: =+SUM(C67:Q67) -> 0 | AJ67: =+SUM(S67:AG67) -> 0
A68: Penalizaciones | C68: 0 | D68: 0 | E68: 0 | F68: 0 | G68: 0 | H68: 0 | I68: 0 | J68: 0 | K68: 0 | L68: 0 | M68: 0 | N68: 0 | O68: 0 | P68: 0 | Q68: 0 | S68: 0 | T68: 0 | U68: 0 | V68: 0 | W68: 0 | X68: 0 | Y68: 0 | Z68: 0 | AA68: 0 | AB68: 0 | AC68: 0 | AD68: 0 | AE68: 0 | AF68: 0 | AG68: 0 | AI68: =+SUM(C68:Q68) -> 0 | AJ68: =+SUM(S68:AG68) -> 0
A69: Otros Ingresos Operativos de Plazas | C69: 0 | D69: 0 | E69: 0 | F69: 0 | G69: 0 | H69: 0 | I69: 0 | J69: 0 | K69: 0 | L69: 0 | M69: 0 | N69: 0 | O69: 0 | P69: 0 | Q69: 0 | S69: 0 | T69: 0 | U69: 0 | V69: 0 | W69: 0 | X69: 0 | Y69: 0 | Z69: 0 | AA69: 0 | AB69: 0 | AC69: 0 | AD69: 0 | AE69: 0 | AF69: 0 | AG69: 0 | AI69: =+SUM(C69:Q69) -> 0 | AJ69: =+SUM(S69:AG69) -> 0
A70: Ingresos por Servicios: | C70: =+SUM(C71:C79) -> 0 | D70: =+SUM(D71:D79) -> 0 | E70: =+SUM(E71:E79) -> 0 | F70: =+SUM(F71:F79) -> 0 | G70: =+SUM(G71:G79) -> 0 | H70: =+SUM(H71:H79) -> 0 | I70: =+SUM(I71:I79) -> 0 | J70: =+SUM(J71:J79) -> 0 | ... Q70: =+SUM(Q71:Q79) -> 0 | S70: =+SUM(S71:S79) -> 0 | T70: =+SUM(T71:T79) -> 0 | U70: =+SUM(U71:U79) -> 0 | V70: =+SUM(V71:V79) -> 0 | W70: =+SUM(W71:W79) -> 0 | X70: =+SUM(X71:X79) -> 0 | Y70: =+SUM(Y71:Y79) -> 0 | Z70: =+SUM(Z71:Z79) -> 0 | ... AG70: =+SUM(AG71:AG79) -> 0 | AI70: =+SUM(AI71:AI79) -> 0 | AJ70: =+SUM(AJ71:AJ79) -> 0
A71: Administración de Nómina | C71: 0 | D71: 0 | E71: 0 | F71: 0 | G71: 0 | H71: 0 | I71: 0 | J71: 0 | K71: 0 | L71: 0 | M71: 0 | N71: 0 | O71: 0 | P71: 0 | Q71: 0 | S71: 0 | T71: 0 | U71: 0 | V71: 0 | W71: 0 | X71: 0 | Y71: 0 | Z71: 0 | AA71: 0 | AB71: 0 | AC71: 0 | AD71: 0 | AE71: 0 | AF71: 0 | AG71: 0 | AI71: =+SUM(R71:AF71) -> 0 | AJ71: =+SUM(S71:AG71) -> 0
A72: Apertura/Cierre de Contratos | C72: 0 | D72: 0 | E72: 0 | F72: 0 | G72: 0 | H72: 0 | I72: 0 | J72: 0 | K72: 0 | L72: 0 | M72: 0 | N72: 0 | O72: 0 | P72: 0 | Q72: 0 | S72: 0 | T72: 0 | U72: 0 | V72: 0 | W72: 0 | X72: 0 | Y72: 0 | Z72: 0 | AA72: 0 | AB72: 0 | AC72: 0 | AD72: 0 | AE72: 0 | AF72: 0 | AG72: 0 | AI72: =+SUM(R72:AF72) -> 0 | AJ72: =+SUM(S72:AG72) -> 0
A73: Renovación de Contratos | C73: 0 | D73: 0 | E73: 0 | F73: 0 | G73: 0 | H73: 0 | I73: 0 | J73: 0 | K73: 0 | L73: 0 | M73: 0 | N73: 0 | O73: 0 | P73: 0 | Q73: 0 | S73: 0 | T73: 0 | U73: 0 | V73: 0 | W73: 0 | X73: 0 | Y73: 0 | Z73: 0 | AA73: 0 | AB73: 0 | AC73: 0 | AD73: 0 | AE73: 0 | AF73: 0 | AG73: 0 | AI73: =+SUM(R73:AF73) -> 0 | AJ73: =+SUM(S73:AG73) -> 0
A74: Administración de Obra | C74: 0 | D74: 0 | E74: 0 | F74: 0 | G74: 0 | H74: 0 | I74: 0 | J74: 0 | K74: 0 | L74: 0 | M74: 0 | N74: 0 | O74: 0 | P74: 0 | Q74: 0 | S74: 0 | T74: 0 | U74: 0 | V74: 0 | W74: 0 | X74: 0 | Y74: 0 | Z74: 0 | AA74: 0 | AB74: 0 | AC74: 0 | AD74: 0 | AE74: 0 | AF74: 0 | AG74: 0 | AI74: =+SUM(R74:AF74) -> 0 | AJ74: =+SUM(S74:AG74) -> 0
A75: Administración de Plaza | C75: 0 | D75: 0 | E75: 0 | F75: 0 | G75: 0 | H75: 0 | I75: 0 | J75: 0 | K75: 0 | L75: 0 | M75: 0 | N75: 0 | O75: 0 | P75: 0 | Q75: 0 | S75: 0 | T75: 0 | U75: 0 | V75: 0 | W75: 0 | X75: 0 | Y75: 0 | Z75: 0 | AA75: 0 | AB75: 0 | AC75: 0 | AD75: 0 | AE75: 0 | AF75: 0 | AG75: 0 | AI75: =+SUM(R75:AF75) -> 0 | AJ75: =+SUM(S75:AG75) -> 0
A76: Consultoría | C76: 0 | D76: 0 | E76: 0 | F76: 0 | G76: 0 | H76: 0 | I76: 0 | J76: 0 | K76: 0 | L76: 0 | M76: 0 | N76: 0 | O76: 0 | P76: 0 | Q76: 0 | S76: 0 | T76: 0 | U76: 0 | V76: 0 | W76: 0 | X76: 0 | Y76: 0 | Z76: 0 | AA76: 0 | AB76: 0 | AC76: 0 | AD76: 0 | AE76: 0 | AF76: 0 | AG76: 0 | AI76: =+SUM(R76:AF76) -> 0 | AJ76: =+SUM(S76:AG76) -> 0
A77: Renta de Terrenos | C77: 0 | D77: 0 | E77: 0 | F77: 0 | G77: 0 | H77: 0 | I77: 0 | J77: 0 | K77: 0 | L77: 0 | M77: 0 | N77: 0 | O77: 0 | P77: 0 | Q77: 0 | S77: 0 | T77: 0 | U77: 0 | V77: 0 | W77: 0 | X77: 0 | Y77: 0 | Z77: 0 | AA77: 0 | AB77: 0 | AC77: 0 | AD77: 0 | AE77: 0 | AF77: 0 | AG77: 0 | AI77: =+SUM(R77:AF77) -> 0 | AJ77: =+SUM(S77:AG77) -> 0
A78: Operación de Hotel | C78: 0 | D78: 0 | E78: 0 | F78: 0 | G78: 0 | H78: 0 | I78: 0 | J78: 0 | K78: 0 | L78: 0 | M78: 0 | N78: 0 | O78: 0 | P78: 0 | Q78: 0 | S78: 0 | T78: 0 | U78: 0 | V78: 0 | W78: 0 | X78: 0 | Y78: 0 | Z78: 0 | AA78: 0 | AB78: 0 | AC78: 0 | AD78: 0 | AE78: 0 | AF78: 0 | AG78: 0 | AI78: =+SUM(R78:AF78) -> 0 | AJ78: =+SUM(S78:AG78) -> 0
A79: Otros Servicios | C79: 0 | D79: 0 | E79: 0 | F79: 0 | G79: 0 | H79: 0 | I79: 0 | J79: 0 | K79: 0 | L79: 0 | M79: 0 | N79: 0 | O79: 0 | P79: 0 | Q79: 0 | S79: 0 | T79: 0 | U79: 0 | V79: 0 | W79: 0 | X79: 0 | Y79: 0 | Z79: 0 | AA79: 0 | AB79: 0 | AC79: 0 | AD79: 0 | AE79: 0 | AF79: 0 | AG79: 0 | AI79: =+SUM(R79:AF79) -> 0 | AJ79: =+SUM(S79:AG79) -> 0
A81: Total Devoluciones sobre Ventas | C81: =+C60+C70 -> 7259.24 | D81: =+D60+D70 -> 0 | E81: =+E60+E70 -> 0 | F81: =+F60+F70 -> 0 | G81: =+G60+G70 -> 0 | H81: =+H60+H70 -> 0 | I81: =+I60+I70 -> 0 | J81: =+J60+J70 -> 0 | ... Q81: =+Q60+Q70 -> 0 | S81: =+S60+S70 -> 44727.81 | T81: =+T60+T70 -> 0 | U81: =+U60+U70 -> 319463.56 | V81: =+V60+V70 -> 0 | W81: =+W60+W70 -> 0 | X81: =+X60+X70 -> 357497.08 | Y81: =+Y60+Y70 -> 0 | Z81: =+Z60+Z70 -> 0 | ... AG81: =+AG60+AG70 -> 0 | AI81: =+AI60+AI70 -> 8239.36 | AJ81: =+AJ60+AJ70 -> 1240187.1
A83: INGRESOS NETOS
A85: Ingresos por Operación de Plazas: | C85: =+SUM(C86:C94) -> 16254512 | D85: =+SUM(D86:D94) -> 9448412.4 | E85: =+SUM(E86:E94) -> 10766404 | F85: =+SUM(F86:F94) -> 857264.25 | G85: =+SUM(G86:G94) -> 0 | H85: =+SUM(H86:H94) -> 5253152 | I85: =+SUM(I86:I94) -> 993670.92 | J85: =+SUM(J86:J94) -> 0 | ... Q85: =+SUM(Q86:Q94) -> 2222465.7 | S85: =+SUM(S86:S94) -> 94714338 | T85: =+SUM(T86:T94) -> 55926379 | U85: =+SUM(U86:U94) -> 65349973 | V85: =+SUM(V86:V94) -> 5189143.3 | W85: =+SUM(W86:W94) -> 0 | X85: =+SUM(X86:X94) -> 32681434 | Y85: =+SUM(Y86:Y94) -> 6014245.2 | Z85: =+SUM(Z86:Z94) -> 0 | ... AG85: =+SUM(AG86:AG94) -> 14235942 | AI85: =+SUM(AI86:AI94) -> 83497331 | AJ85: =+SUM(AJ86:AJ94) -> 4.7166206e+08
A86: Renta Mínima | C86: =+C11-C36-C61 -> 10617701 | D86: =+D11-D36-D61 -> 6494103.8 | E86: =+E11-E36-E61 -> 8161174.2 | F86: =+F11-F36-F61 -> 735279.23 | G86: =+G11-G36-G61 -> 0 | H86: =+H11-H36-H61 -> 4080692.2 | I86: =+I11-I36-I61 -> 872047.28 | J86: =+J11-J36-J61 -> 0 | ... Q86: =+Q11-Q36-Q61 -> 1610604.8 | S86: =+S11-S36-S61 -> 62766922 | T86: =+T11-T36-T61 -> 39182854 | U86: =+U11-U36-U61 -> 49868385 | V86: =+V11-V36-V61 -> 4411601.7 | W86: =+W11-W36-W61 -> 0 | X86: =+X11-X36-X61 -> 25273517 | Y86: =+Y11-Y36-Y61 -> 5237999.2 | Z86: =+Z11-Z36-Z61 -> 0 | ... AG86: =+AG11-AG36-AG61 -> 9658099 | AI86: =+AI11-AI36-AI61 -> 58768092 | AJ86: =+AJ11-AJ36-AJ61 -> 3.2829728e+08
A87: Renta Variable | C87: =+C12-C37-C62 -> 1096856.1 | D87: =+D12-D37-D62 -> 354412.68 | E87: =+E12-E37-E62 -> 154073.93 | F87: =+F12-F37-F62 -> 30687.47 | G87: =+G12-G37-G62 -> 0 | H87: =+H12-H37-H62 -> 29414.38 | I87: =+I12-I37-I62 -> 21969.12 | J87: =+J12-J37-J62 -> 0 | ... Q87: =+Q12-Q37-Q62 -> 352526.19 | S87: =+S12-S37-S62 -> 5936802 | T87: =+T12-T37-T62 -> 2149334.7 | U87: =+U12-U37-U62 -> 1601322.1 | V87: =+V12-V37-V62 -> 237997.13 | W87: =+W12-W37-W62 -> 0 | X87: =+X12-X37-X62 -> 457853.33 | Y87: =+Y12-Y37-Y62 -> 184504.06 | Z87: =+Z12-Z37-Z62 -> 0 | ... AG87: =+AG12-AG37-AG62 -> 2955235.6 | AI87: =+AI12-AI37-AI62 -> 6105141.4 | AJ87: =+AJ12-AJ37-AJ62 -> 38686469
A88: Cuota de Mantenimiento | C88: =+C13-C38-C63 -> 1391476.5 | D88: =+D13-D38-D63 -> 916164.79 | E88: =+E13-E38-E63 -> 1098269.6 | F88: =+F13-F38-F63 -> 88845.35 | G88: =+G13-G38-G63 -> 0 | H88: =+H13-H38-H63 -> 560791.49 | I88: =+I13-I38-I63 -> 99654.52 | J88: =+J13-J38-J63 -> 0 | ... Q88: =+Q13-Q38-Q63 -> 259334.7 | S88: =+S13-S38-S63 -> 8452128 | T88: =+T13-T38-T63 -> 5543398.5 | U88: =+U13-U38-U63 -> 6737222.6 | V88: =+V13-V38-V63 -> 534210.17 | W88: =+W13-W38-W63 -> 0 | X88: =+X13-X38-X63 -> 3665580.8 | Y88: =+Y13-Y38-Y63 -> 591742.03 | Z88: =+Z13-Z38-Z63 -> 0 | ... AG88: =+AG13-AG38-AG63 -> 1622607.2 | AI88: =+AI13-AI38-AI63 -> 7710733.1 | AJ88: =+AJ13-AJ38-AJ63 -> 46529603
A89: Publicidad | C89: =+C14-C39-C64 -> 4990.32 | D89: =+D14-D39-D64 -> 0 | E89: =+E14-E39-E64 -> 13081.09 | F89: =+F14-F39-F64 -> 2452.2 | G89: =+G14-G39-G64 -> 0 | H89: =+H14-H39-H64 -> 2899.78 | I89: =+I14-I39-I64 -> 0 | J89: =+J14-J39-J64 -> 0 | ... Q89: =+Q14-Q39-Q64 -> 0 | S89: =+S14-S39-S64 -> 30319.17 | T89: =+T14-T39-T64 -> 0 | U89: =+U14-U39-U64 -> 78486.54 | V89: =+V14-V39-V64 -> 14713.2 | W89: =+W14-W39-W64 -> 0 | X89: =+X14-X39-X64 -> 17398.68 | Y89: =+Y14-Y39-Y64 -> 0 | Z89: =+Z14-Z39-Z64 -> 0 | ... AG89: =+AG14-AG39-AG64 -> 0 | AI89: =+AI14-AI39-AI64 -> 23946.58 | AJ89: =+AJ14-AJ39-AJ64 -> 144056.73
A90: Estacionamiento | C90: =+C15-C40-C65 -> 3046278.6 | D90: =+D15-D40-D65 -> 1664810.2 | E90: =+E15-E40-E65 -> 1297657.4 | F90: =+F15-F40-F65 -> 0 | G90: =+G15-G40-G65 -> 0 | H90: =+H15-H40-H65 -> 573992.25 | I90: =+I15-I40-I65 -> 0 | J90: =+J15-J40-J65 -> 0 | ... Q90: =+Q15-Q40-Q65 -> 0 | S90: =+S15-S40-S65 -> 17133305 | T90: =+T15-T40-T65 -> 8927194.6 | U90: =+U15-U40-U65 -> 6964036 | V90: =+V15-V40-V65 -> 0 | W90: =+W15-W40-W65 -> 0 | X90: =+X15-X40-X65 -> 2994929.3 | Y90: =+Y15-Y40-Y65 -> 0 | Z90: =+Z15-Z40-Z65 -> 0 | ... AG90: =+AG15-AG40-AG65 -> 0 | AI90: =+AI15-AI40-AI65 -> 10033157 | AJ90: =+AJ15-AJ40-AJ65 -> 53950270
A91: Cuotas Condominales | C91: =+C16-C41-C66 -> 0 | D91: =+D16-D41-D66 -> 0 | E91: =+E16-E41-E66 -> 0 | F91: =+F16-F41-F66 -> 0 | G91: =+G16-G41-G66 -> 0 | H91: =+H16-H41-H66 -> 0 | I91: =+I16-I41-I66 -> 0 | J91: =+J16-J41-J66 -> 0 | ... Q91: =+Q16-Q41-Q66 -> 0 | S91: =+S16-S41-S66 -> 0 | T91: =+T16-T41-T66 -> 0 | U91: =+U16-U41-U66 -> 0 | V91: =+V16-V41-V66 -> 0 | W91: =+W16-W41-W66 -> 0 | X91: =+X16-X41-X66 -> 0 | Y91: =+Y16-Y41-Y66 -> 0 | Z91: =+Z16-Z41-Z66 -> 0 | ... AG91: =+AG16-AG41-AG66 -> 0 | AI91: =+AI16-AI41-AI66 -> 290859.08 | AJ91: =+AJ16-AJ41-AJ66 -> 1505761.9
A92: Guantes | C92: =+C17-C42-C67 -> 58850.37 | D92: =+D17-D42-D67 -> 18920.88 | E92: =+E17-E42-E67 -> 16063.05 | F92: =+F17-F42-F67 -> 0 | G92: =+G17-G42-G67 -> 0 | H92: =+H17-H42-H67 -> 5361.95 | I92: =+I17-I42-I67 -> 0 | J92: =+J17-J42-J67 -> 0 | ... Q92: =+Q17-Q42-Q67 -> 0 | S92: =+S17-S42-S67 -> 356502.43 | T92: =+T17-T42-T67 -> 123597.55 | U92: =+U17-U42-U67 -> 87040.4 | V92: =+V17-V42-V67 -> 0 | W92: =+W17-W42-W67 -> 0 | X92: =+X17-X42-X67 -> 32171.7 | Y92: =+Y17-Y42-Y67 -> 0 | Z92: =+Z17-Z42-Z67 -> 0 | ... AG92: =+AG17-AG42-AG67 -> 0 | AI92: =+AI17-AI42-AI67 -> 330755.45 | AJ92: =+AJ17-AJ42-AJ67 -> 1941685.5
A93: Penalizaciones | C93: =+C18-C43-C68 -> 38359.08 | D93: =+D18-D43-D68 -> 0 | E93: =+E18-E43-E68 -> 26084.57 | F93: =+F18-F43-F68 -> 0 | G93: =+G18-G43-G68 -> 0 | H93: =+H18-H43-H68 -> 0 | I93: =+I18-I43-I68 -> 0 | J93: =+J18-J43-J68 -> 0 | ... Q93: =+Q18-Q43-Q68 -> 0 | S93: =+S18-S43-S68 -> 38359.08 | T93: =+T18-T43-T68 -> 0 | U93: =+U18-U43-U68 -> 13480.54 | V93: =+V18-V43-V68 -> -9378.96 | W93: =+W18-W43-W68 -> 0 | X93: =+X18-X43-X68 -> 172414 | Y93: =+Y18-Y43-Y68 -> 0 | Z93: =+Z18-Z43-Z68 -> 0 | ... AG93: =+AG18-AG43-AG68 -> 0 | AI93: =+AI18-AI43-AI68 -> 108377.89 | AJ93: =+AJ18-AJ43-AJ68 -> 258808.9
A94: Otros Ingresos Operativos de Plazas | C94: =+C19-C44-C69 -> 0 | D94: =+D19-D44-D69 -> 0 | E94: =+E19-E44-E69 -> 0 | F94: =+F19-F44-F69 -> 0 | G94: =+G19-G44-G69 -> 0 | H94: =+H19-H44-H69 -> 0 | I94: =+I19-I44-I69 -> 0 | J94: =+J19-J44-J69 -> 0 | ... Q94: =+Q19-Q44-Q69 -> 0 | S94: =+S19-S44-S69 -> 0 | T94: =+T19-T44-T69 -> 0 | U94: =+U19-U44-U69 -> 0 | V94: =+V19-V44-V69 -> 0 | W94: =+W19-W44-W69 -> 0 | X94: =+X19-X44-X69 -> 67568.96 | Y94: =+Y19-Y44-Y69 -> 0 | Z94: =+Z19-Z44-Z69 -> 0 | ... AG94: =+AG19-AG44-AG69 -> 0 | AI94: =+AI19-AI44-AI69 -> 126268 | AJ94: =+AJ19-AJ44-AJ69 -> 348129.27
A95: Ingresos por Servicios: | C95: =+SUM(C96:C104) -> 0 | D95: =+SUM(D96:D104) -> 0 | E95: =+SUM(E96:E104) -> 0 | F95: =+SUM(F96:F104) -> 0 | G95: =+SUM(G96:G104) -> 0 | H95: =+SUM(H96:H104) -> 0 | I95: =+SUM(I96:I104) -> 0 | J95: =+SUM(J96:J104) -> 0 | ... Q95: =+SUM(Q96:Q104) -> 0 | S95: =+SUM(S96:S104) -> 0 | T95: =+SUM(T96:T104) -> 0 | U95: =+SUM(U96:U104) -> 0 | V95: =+SUM(V96:V104) -> 0 | W95: =+SUM(W96:W104) -> 0 | X95: =+SUM(X96:X104) -> 0 | Y95: =+SUM(Y96:Y104) -> 0 | Z95: =+SUM(Z96:Z104) -> 0 | ... AG95: =+SUM(AG96:AG104) -> 0 | AI95: =+SUM(AI96:AI104) -> 0 | AJ95: =+SUM(AJ96:AJ104) -> 0
A96: Administración de Nómina | C96: =+C21-C46-C71 -> 0 | D96: =+D21-D46-D71 -> 0 | E96: =+E21-E46-E71 -> 0 | F96: =+F21-F46-F71 -> 0 | G96: =+G21-G46-G71 -> 0 | H96: =+H21-H46-H71 -> 0 | I96: =+I21-I46-I71 -> 0 | J96: =+J21-J46-J71 -> 0 | ... Q96: =+Q21-Q46-Q71 -> 0 | S96: =+S21-S46-S71 -> 0 | T96: =+T21-T46-T71 -> 0 | U96: =+U21-U46-U71 -> 0 | V96: =+V21-V46-V71 -> 0 | W96: =+W21-W46-W71 -> 0 | X96: =+X21-X46-X71 -> 0 | Y96: =+Y21-Y46-Y71 -> 0 | Z96: =+Z21-Z46-Z71 -> 0 | ... AG96: =+AG21-AG46-AG71 -> 0 | AI96: =+AI21-AI46-AI71 -> 0 | AJ96: =+AJ21-AJ46-AJ71 -> 0
A97: Apertura/Cierre de Contratos | C97: =+C22-C47-C72 -> 0 | D97: =+D22-D47-D72 -> 0 | E97: =+E22-E47-E72 -> 0 | F97: =+F22-F47-F72 -> 0 | G97: =+G22-G47-G72 -> 0 | H97: =+H22-H47-H72 -> 0 | I97: =+I22-I47-I72 -> 0 | J97: =+J22-J47-J72 -> 0 | ... Q97: =+Q22-Q47-Q72 -> 0 | S97: =+S22-S47-S72 -> 0 | T97: =+T22-T47-T72 -> 0 | U97: =+U22-U47-U72 -> 0 | V97: =+V22-V47-V72 -> 0 | W97: =+W22-W47-W72 -> 0 | X97: =+X22-X47-X72 -> 0 | Y97: =+Y22-Y47-Y72 -> 0 | Z97: =+Z22-Z47-Z72 -> 0 | ... AG97: =+AG22-AG47-AG72 -> 0 | AI97: =+AI22-AI47-AI72 -> 0 | AJ97: =+AJ22-AJ47-AJ72 -> 0
A98: Renovación de Contratos | C98: =+C23-C48-C73 -> 0 | D98: =+D23-D48-D73 -> 0 | E98: =+E23-E48-E73 -> 0 | F98: =+F23-F48-F73 -> 0 | G98: =+G23-G48-G73 -> 0 | H98: =+H23-H48-H73 -> 0 | I98: =+I23-I48-I73 -> 0 | J98: =+J23-J48-J73 -> 0 | ... Q98: =+Q23-Q48-Q73 -> 0 | S98: =+S23-S48-S73 -> 0 | T98: =+T23-T48-T73 -> 0 | U98: =+U23-U48-U73 -> 0 | V98: =+V23-V48-V73 -> 0 | W98: =+W23-W48-W73 -> 0 | X98: =+X23-X48-X73 -> 0 | Y98: =+Y23-Y48-Y73 -> 0 | Z98: =+Z23-Z48-Z73 -> 0 | ... AG98: =+AG23-AG48-AG73 -> 0 | AI98: =+AI23-AI48-AI73 -> 0 | AJ98: =+AJ23-AJ48-AJ73 -> 0
A99: Administración de Obra | C99: =+C24-C49-C74 -> 0 | D99: =+D24-D49-D74 -> 0 | E99: =+E24-E49-E74 -> 0 | F99: =+F24-F49-F74 -> 0 | G99: =+G24-G49-G74 -> 0 | H99: =+H24-H49-H74 -> 0 | I99: =+I24-I49-I74 -> 0 | J99: =+J24-J49-J74 -> 0 | ... Q99: =+Q24-Q49-Q74 -> 0 | S99: =+S24-S49-S74 -> 0 | T99: =+T24-T49-T74 -> 0 | U99: =+U24-U49-U74 -> 0 | V99: =+V24-V49-V74 -> 0 | W99: =+W24-W49-W74 -> 0 | X99: =+X24-X49-X74 -> 0 | Y99: =+Y24-Y49-Y74 -> 0 | Z99: =+Z24-Z49-Z74 -> 0 | ... AG99: =+AG24-AG49-AG74 -> 0 | AI99: =+AI24-AI49-AI74 -> 0 | AJ99: =+AJ24-AJ49-AJ74 -> 0
A100: Administración de Plaza | C100: =+C25-C50-C75 -> 0 | D100: =+D25-D50-D75 -> 0 | E100: =+E25-E50-E75 -> 0 | F100: =+F25-F50-F75 -> 0 | G100: =+G25-G50-G75 -> 0 | H100: =+H25-H50-H75 -> 0 | I100: =+I25-I50-I75 -> 0 | J100: =+J25-J50-J75 -> 0 | ... Q100: =+Q25-Q50-Q75 -> 0 | S100: =+S25-S50-S75 -> 0 | T100: =+T25-T50-T75 -> 0 | U100: =+U25-U50-U75 -> 0 | V100: =+V25-V50-V75 -> 0 | W100: =+W25-W50-W75 -> 0 | X100: =+X25-X50-X75 -> 0 | Y100: =+Y25-Y50-Y75 -> 0 | Z100: =+Z25-Z50-Z75 -> 0 | ... AG100: =+AG25-AG50-AG75 -> 0 | AI100: =+AI25-AI50-AI75 -> 0 | AJ100: =+AJ25-AJ50-AJ75 -> 0
A101: Consultoría | C101: =+C26-C51-C76 -> 0 | D101: =+D26-D51-D76 -> 0 | E101: =+E26-E51-E76 -> 0 | F101: =+F26-F51-F76 -> 0 | G101: =+G26-G51-G76 -> 0 | H101: =+H26-H51-H76 -> 0 | I101: =+I26-I51-I76 -> 0 | J101: =+J26-J51-J76 -> 0 | ... Q101: =+Q26-Q51-Q76 -> 0 | S101: =+S26-S51-S76 -> 0 | T101: =+T26-T51-T76 -> 0 | U101: =+U26-U51-U76 -> 0 | V101: =+V26-V51-V76 -> 0 | W101: =+W26-W51-W76 -> 0 | X101: =+X26-X51-X76 -> 0 | Y101: =+Y26-Y51-Y76 -> 0 | Z101: =+Z26-Z51-Z76 -> 0 | ... AG101: =+AG26-AG51-AG76 -> 0 | AI101: =+AI26-AI51-AI76 -> 0 | AJ101: =+AJ26-AJ51-AJ76 -> 0
A102: Renta de Terrenos | C102: =+C27-C52-C77 -> 0 | D102: =+D27-D52-D77 -> 0 | E102: =+E27-E52-E77 -> 0 | F102: =+F27-F52-F77 -> 0 | G102: =+G27-G52-G77 -> 0 | H102: =+H27-H52-H77 -> 0 | I102: =+I27-I52-I77 -> 0 | J102: =+J27-J52-J77 -> 0 | ... Q102: =+Q27-Q52-Q77 -> 0 | S102: =+S27-S52-S77 -> 0 | T102: =+T27-T52-T77 -> 0 | U102: =+U27-U52-U77 -> 0 | V102: =+V27-V52-V77 -> 0 | W102: =+W27-W52-W77 -> 0 | X102: =+X27-X52-X77 -> 0 | Y102: =+Y27-Y52-Y77 -> 0 | Z102: =+Z27-Z52-Z77 -> 0 | ... AG102: =+AG27-AG52-AG77 -> 0 | AI102: =+AI27-AI52-AI77 -> 0 | AJ102: =+AJ27-AJ52-AJ77 -> 0
A103: Operación de Hotel | C103: =+C28-C53-C78 -> 0 | D103: =+D28-D53-D78 -> 0 | E103: =+E28-E53-E78 -> 0 | F103: =+F28-F53-F78 -> 0 | G103: =+G28-G53-G78 -> 0 | H103: =+H28-H53-H78 -> 0 | I103: =+I28-I53-I78 -> 0 | J103: =+J28-J53-J78 -> 0 | ... Q103: =+Q28-Q53-Q78 -> 0 | S103: =+S28-S53-S78 -> 0 | T103: =+T28-T53-T78 -> 0 | U103: =+U28-U53-U78 -> 0 | V103: =+V28-V53-V78 -> 0 | W103: =+W28-W53-W78 -> 0 | X103: =+X28-X53-X78 -> 0 | Y103: =+Y28-Y53-Y78 -> 0 | Z103: =+Z28-Z53-Z78 -> 0 | ... AG103: =+AG28-AG53-AG78 -> 0 | AI103: =+AI28-AI53-AI78 -> 0 | AJ103: =+AJ28-AJ53-AJ78 -> 0 | AL103: =+AA106+AB106+AC106 -> 1.3430216e+08 | AM103: =+AD106 -> 48004738
A104: Otros Servicios | C104: =+C29-C54-C79 -> 0 | D104: =+D29-D54-D79 -> 0 | E104: =+E29-E54-E79 -> 0 | F104: =+F29-F54-F79 -> 0 | G104: =+G29-G54-G79 -> 0 | H104: =+H29-H54-H79 -> 0 | I104: =+I29-I54-I79 -> 0 | J104: =+J29-J54-J79 -> 0 | ... Q104: =+Q29-Q54-Q79 -> 0 | S104: =+S29-S54-S79 -> 0 | T104: =+T29-T54-T79 -> 0 | U104: =+U29-U54-U79 -> 0 | V104: =+V29-V54-V79 -> 0 | W104: =+W29-W54-W79 -> 0 | X104: =+X29-X54-X79 -> 0 | Y104: =+Y29-Y54-Y79 -> 0 | Z104: =+Z29-Z54-Z79 -> 0 | ... AG104: =+AG29-AG54-AG79 -> 0 | AI104: =+AI29-AI54-AI79 -> 0 | AJ104: =+AJ29-AJ54-AJ79 -> 0 | AL104: 1.0888289e+08 | AM104: 27566200
A106: Total Ingresos Netos | C106: =+C85+C95 -> 16254512 | D106: =+D85+D95 -> 9448412.4 | E106: =+E85+E95 -> 10766404 | F106: =+F85+F95 -> 857264.25 | G106: =+G85+G95 -> 0 | H106: =+H85+H95 -> 5253152 | I106: =+I85+I95 -> 993670.92 | J106: =+J85+J95 -> 0 | ... Q106: =+Q85+Q95 -> 2222465.7 | S106: =+S85+S95 -> 94714338 | T106: =+T85+T95 -> 55926379 | U106: =+U85+U95 -> 65349973 | V106: =+V85+V95 -> 5189143.3 | W106: =+W85+W95 -> 0 | X106: =+X85+X95 -> 32681434 | Y106: =+Y85+Y95 -> 6014245.2 | Z106: =+Z85+Z95 -> 0 | ... AG106: =+AG85+AG95 -> 14235942 | AI106: =+AI85+AI95 -> 83497331 | AJ106: =+AJ85+AJ95 -> 4.7166206e+08 | AL106: =+AL103-AL104 -> 25419271 | AM106: =+AM103-AM104 -> 20438538
A108: COSTO DE INGRESOS
A110: Ingresos por Operación de Plazas: | C110: =+SUM(C111:C119) -> 0 | D110: =+SUM(D111:D119) -> 0 | E110: =+SUM(E111:E119) -> 0 | F110: =+SUM(F111:F119) -> 0 | G110: =+SUM(G111:G119) -> 0 | H110: =+SUM(H111:H119) -> 0 | I110: =+SUM(I111:I119) -> 0 | J110: =+SUM(J111:J119) -> 0 | ... Q110: =+SUM(Q111:Q119) -> 0 | S110: =+SUM(S111:S119) -> 0 | T110: =+SUM(T111:T119) -> 0 | U110: =+SUM(U111:U119) -> 0 | V110: =+SUM(V111:V119) -> 0 | W110: =+SUM(W111:W119) -> 0 | X110: =+SUM(X111:X119) -> 0 | Y110: =+SUM(Y111:Y119) -> 0 | Z110: =+SUM(Z111:Z119) -> 0 | ... AG110: =+SUM(AG111:AG119) -> 0 | AI110: =+SUM(AI111:AI119) -> 0 | AJ110: =+SUM(AJ111:AJ119) -> 0
A111: Renta Mínima | C111: 0 | D111: 0 | E111: 0 | F111: 0 | G111: 0 | H111: 0 | I111: 0 | J111: 0 | K111: 0 | L111: 0 | M111: 0 | N111: 0 | O111: 0 | P111: 0 | Q111: 0 | S111: 0 | T111: 0 | U111: 0 | V111: 0 | W111: 0 | X111: 0 | Y111: 0 | Z111: 0 | AA111: 0 | AB111: 0 | AC111: 0 | AD111: 0 | AE111: 0 | AF111: 0 | AG111: 0 | AI111: =+SUM(R111:AF111) -> 0 | AJ111: =+SUM(S111:AG111) -> 0
A112: Renta Variable | C112: 0 | D112: 0 | E112: 0 | F112: 0 | G112: 0 | H112: 0 | I112: 0 | J112: 0 | K112: 0 | L112: 0 | M112: 0 | N112: 0 | O112: 0 | P112: 0 | Q112: 0 | S112: 0 | T112: 0 | U112: 0 | V112: 0 | W112: 0 | X112: 0 | Y112: 0 | Z112: 0 | AA112: 0 | AB112: 0 | AC112: 0 | AD112: 0 | AE112: 0 | AF112: 0 | AG112: 0 | AI112: =+SUM(R112:AF112) -> 0 | AJ112: =+SUM(S112:AG112) -> 0
A113: Cuota de Mantenimiento | C113: 0 | D113: 0 | E113: 0 | F113: 0 | G113: 0 | H113: 0 | I113: 0 | J113: 0 | K113: 0 | L113: 0 | M113: 0 | N113: 0 | O113: 0 | P113: 0 | Q113: 0 | S113: 0 | T113: 0 | U113: 0 | V113: 0 | W113: 0 | X113: 0 | Y113: 0 | Z113: 0 | AA113: 0 | AB113: 0 | AC113: 0 | AD113: 0 | AE113: 0 | AF113: 0 | AG113: 0 | AI113: =+SUM(R113:AF113) -> 0 | AJ113: =+SUM(S113:AG113) -> 0
A114: Publicidad | C114: 0 | D114: 0 | E114: 0 | F114: 0 | G114: 0 | H114: 0 | I114: 0 | J114: 0 | K114: 0 | L114: 0 | M114: 0 | N114: 0 | O114: 0 | P114: 0 | Q114: 0 | S114: 0 | T114: 0 | U114: 0 | V114: 0 | W114: 0 | X114: 0 | Y114: 0 | Z114: 0 | AA114: 0 | AB114: 0 | AC114: 0 | AD114: 0 | AE114: 0 | AF114: 0 | AG114: 0 | AI114: =+SUM(R114:AF114) -> 0 | AJ114: =+SUM(S114:AG114) -> 0
A115: Estacionamiento | C115: 0 | D115: 0 | E115: 0 | F115: 0 | G115: 0 | H115: 0 | I115: 0 | J115: 0 | K115: 0 | L115: 0 | M115: 0 | N115: 0 | O115: 0 | P115: 0 | Q115: 0 | S115: 0 | T115: 0 | U115: 0 | V115: 0 | W115: 0 | X115: 0 | Y115: 0 | Z115: 0 | AA115: 0 | AB115: 0 | AC115: 0 | AD115: 0 | AE115: 0 | AF115: 0 | AG115: 0 | AI115: =+SUM(R115:AF115) -> 0 | AJ115: =+SUM(S115:AG115) -> 0
A116: Cuotas Condominales | C116: 0 | D116: 0 | E116: 0 | F116: 0 | G116: 0 | H116: 0 | I116: 0 | J116: 0 | K116: 0 | L116: 0 | M116: 0 | N116: 0 | O116: 0 | P116: 0 | Q116: 0 | S116: 0 | T116: 0 | U116: 0 | V116: 0 | W116: 0 | X116: 0 | Y116: 0 | Z116: 0 | AA116: 0 | AB116: 0 | AC116: 0 | AD116: 0 | AE116: 0 | AF116: 0 | AG116: 0 | AI116: =+SUM(R116:AF116) -> 0 | AJ116: =+SUM(S116:AG116) -> 0
A117: Guantes | C117: 0 | D117: 0 | E117: 0 | F117: 0 | G117: 0 | H117: 0 | I117: 0 | J117: 0 | K117: 0 | L117: 0 | M117: 0 | N117: 0 | O117: 0 | P117: 0 | Q117: 0 | S117: 0 | T117: 0 | U117: 0 | V117: 0 | W117: 0 | X117: 0 | Y117: 0 | Z117: 0 | AA117: 0 | AB117: 0 | AC117: 0 | AD117: 0 | AE117: 0 | AF117: 0 | AG117: 0 | AI117: =+SUM(R117:AF117) -> 0 | AJ117: =+SUM(S117:AG117) -> 0
...

Sheet AAC
C2: ACUMULADO
A5: ESTADO DE RESULTADOS | C5: 45657 | D5: % | F5: =+EOMONTH(C5,-12) -> 45291 | G5: % | H5: DIFERENCIAS | I5: % | K5: =+EOMONTH(F5,-12) -> 44926 | L5: % | M5: DIFERENCIAS | N5: % | P5: =+EOMONTH(K5,-12) -> 44561 | Q5: % | R5: DIFERENCIAS | S5: % | U5: =+EOMONTH(P5,-24) -> 43830 | V5: % | W5: DIFERENCIAS | X5: %
A6: ARCO ÁREAS COMERCIALES | C6: PPTO | F6: REAL | H6: 2024P vs 2023R | K6: REAL | M6: 2024P vs 2022R | P6: REAL | R6: 2024P vs 2021R | U6: REAL | W6: 2024P vs 2019R
A8: INGRESOS BRUTOS
A10: Ingresos por Operación de Plazas: | C10: =+SUM(C11:C19) -> 3.5583403e+08 | D10: =+IF(ISERROR(C10/C31),"N. D.",C10/C31) -> 1 | F10: =+SUM(F11:F19) -> 3.5583403e+08 | G10: =+IF(ISERROR(F10/F31),"N. D.",F10/F31) -> 1 | H10: =+$C10-F10 -> 0 | I10: =+IF(ISERROR(H10/F10),"N. D.",H10/F10) -> 0 | K10: =+SUM(K11:K19) -> 3.3032255e+08 | L10: =+IF(ISERROR(K10/K31),"N. D.",K10/K31) -> 1 | M10: =+$C10-K10 -> 25511483 | N10: =+IF(ISERROR(M10/K10),"N. D.",M10/K10) -> 0.077232038 | P10: =+SUM(P11:P19) -> 3.084476e+08 | Q10: =+IF(ISERROR(P10/P31),"N. D.",P10/P31) -> 1 | R10: =+$C10-P10 -> 47386425 | S10: =+IF(ISERROR(R10/P10),"N. D.",R10/P10) -> 0.15362877 | U10: =+SUM(U11:U19) -> 2.7768113e+08 | V10: =+IF(ISERROR(U10/U31),"N. D.",U10/U31) -> 1 | W10: =+$C10-U10 -> 78152899 | X10: =+IF(ISERROR(W10/U10),"N. D.",W10/U10) -> 0.28144836
A11: Renta Mínima | C11: 2.523077e+08 | D11: =+IF(ISERROR(C11/C86),"N. D.",C11/C86) -> 1.0068414 | F11: 2.523077e+08 | G11: =+IF(ISERROR(F11/F86),"N. D.",F11/F86) -> 1.0068414 | H11: =+$C11-F11 -> 0 | I11: =+IF(ISERROR(H11/F11),"N. D.",H11/F11) -> 0 | K11: 2.3925162e+08 | L11: =+IF(ISERROR(K11/K86),"N. D.",K11/K86) -> 1.0173979 | M11: =+$C11-K11 -> 13056082 | N11: =+IF(ISERROR(M11/K11),"N. D.",M11/K11) -> 0.054570508 | P11: 2.2831932e+08 | Q11: =+IF(ISERROR(P11/P86),"N. D.",P11/P86) -> 1.1250227 | R11: =+$C11-P11 -> 23988377 | S11: =+IF(ISERROR(R11/P11),"N. D.",R11/P11) -> 0.10506503 | U11: 1.9936345e+08 | V11: =+IF(ISERROR(U11/U86),"N. D.",U11/U86) -> 1.0080862 | W11: =+$C11-U11 -> 52944250 | X11: =+IF(ISERROR(W11/U11),"N. D.",W11/U11) -> 0.26556648
A12: Renta Variable | C12: 19073723 | D12: =+IF(ISERROR(C12/C87),"N. D.",C12/C87) -> 1 | F12: 19073723 | G12: =+IF(ISERROR(F12/F87),"N. D.",F12/F87) -> 1 | H12: =+$C12-F12 -> 0 | I12: =+IF(ISERROR(H12/F12),"N. D.",H12/F12) -> 0 | K12: 16701280 | L12: =+IF(ISERROR(K12/K87),"N. D.",K12/K87) -> 1.0295517 | M12: =+$C12-K12 -> 2372443.4 | N12: =+IF(ISERROR(M12/K12),"N. D.",M12/K12) -> 0.1420516 | P12: 10644857 | Q12: =+IF(ISERROR(P12/P87),"N. D.",P12/P87) -> 1.0956618 | R12: =+$C12-P12 -> 8428866.3 | S12: =+IF(ISERROR(R12/P12),"N. D.",R12/P12) -> 0.79182524 | U12: 21509016 | V12: =+IF(ISERROR(U12/U87),"N. D.",U12/U87) -> 1 | W12: =+$C12-U12 -> -2435293.1 | X12: =+IF(ISERROR(W12/U12),"N. D.",W12/U12) -> -0.11322197
A13: Cuota de Mantenimiento | C13: 33058690 | D13: =+IF(ISERROR(C13/C88),"N. D.",C13/C88) -> 1.014248 | F13: 33058690 | G13: =+IF(ISERROR(F13/F88),"N. D.",F13/F88) -> 1.014248 | H13: =+$C13-F13 -> 0 | I13: =+IF(ISERROR(H13/F13),"N. D.",H13/F13) -> 0 | K13: 30271442 | L13: =+IF(ISERROR(K13/K88),"N. D.",K13/K88) -> 1.0135118 | M13: =+$C13-K13 -> 2787248 | N13: =+IF(ISERROR(M13/K13),"N. D.",M13/K13) -> 0.092075165 | P13: 28632576 | Q13: =+IF(ISERROR(P13/P88),"N. D.",P13/P88) -> 1.0165332 | R13: =+$C13-P13 -> 4426114.1 | S13: =+IF(ISERROR(R13/P13),"N. D.",R13/P13) -> 0.15458316 | U13: 22640054 | V13: =+IF(ISERROR(U13/U88),"N. D.",U13/U88) -> 1.0012074 | W13: =+$C13-U13 -> 10418636 | X13: =+IF(ISERROR(W13/U13),"N. D.",W13/U13) -> 0.46018598
A14: Publicidad | C14: 547963.6 | D14: =+IF(ISERROR(C14/C89),"N. D.",C14/C89) -> 1.0056995 | F14: 547963.6 | G14: =+IF(ISERROR(F14/F89),"N. D.",F14/F89) -> 1.0056995 | H14: =+$C14-F14 -> 0 | I14: =+IF(ISERROR(H14/F14),"N. D.",H14/F14) -> 0 | K14: 737968.82 | L14: =+IF(ISERROR(K14/K89),"N. D.",K14/K89) -> 1.0187545 | M14: =+$C14-K14 -> -190005.22 | N14: =+IF(ISERROR(M14/K14),"N. D.",M14/K14) -> -0.25747053 | P14: 838053.61 | Q14: =+IF(ISERROR(P14/P89),"N. D.",P14/P89) -> 1.0572143 | R14: =+$C14-P14 -> -290090.01 | S14: =+IF(ISERROR(R14/P14),"N. D.",R14/P14) -> -0.34614732 | U14: 1229834.1 | V14: =+IF(ISERROR(U14/U89),"N. D.",U14/U89) -> 1 | W14: =+$C14-U14 -> -681870.48 | X14: =+IF(ISERROR(W14/U14),"N. D.",W14/U14) -> -0.55444103
A15: Estacionamiento | C15: 50309657 | D15: =+IF(ISERROR(C15/C90),"N. D.",C15/C90) -> 1 | F15: 50309657 | G15: =+IF(ISERROR(F15/F90),"N. D.",F15/F90) -> 1 | H15: =+$C15-F15 -> 0 | I15: =+IF(ISERROR(H15/F15),"N. D.",H15/F15) -> 0 | K15: 42850646 | L15: =+IF(ISERROR(K15/K90),"N. D.",K15/K90) -> 1.0028667 | M15: =+$C15-K15 -> 7459011.3 | N15: =+IF(ISERROR(M15/K15),"N. D.",M15/K15) -> 0.17406998 | P15: 39926644 | Q15: =+IF(ISERROR(P15/P90),"N. D.",P15/P90) -> 1.0002545 | R15: =+$C15-P15 -> 10383013 | S15: =+IF(ISERROR(R15/P15),"N. D.",R15/P15) -> 0.26005223 | U15: 32829885 | V15: =+IF(ISERROR(U15/U90),"N. D.",U15/U90) -> 1 | W15: =+$C15-U15 -> 17479772 | X15: =+IF(ISERROR(W15/U15),"N. D.",W15/U15) -> 0.53243478
A16: Cuotas Condominales | C16: 0 | D16: =+IF(ISERROR(C16/C91),"N. D.",C16/C91) -> N. D. | F16: 0 | G16: =+IF(ISERROR(F16/F91),"N. D.",F16/F91) -> N. D. | H16: =+$C16-F16 -> 0 | I16: =+IF(ISERROR(H16/F16),"N. D.",H16/F16) -> N. D. | K16: 0 | L16: =+IF(ISERROR(K16/K91),"N. D.",K16/K91) -> N. D. | M16: =+$C16-K16 -> 0 | N16: =+IF(ISERROR(M16/K16),"N. D.",M16/K16) -> N. D. | P16: 0 | Q16: =+IF(ISERROR(P16/P91),"N. D.",P16/P91) -> N. D. | R16: =+$C16-P16 -> 0 | S16: =+IF(ISERROR(R16/P16),"N. D.",R16/P16) -> N. D. | U16: 0 | V16: =+IF(ISERROR(U16/U91),"N. D.",U16/U91) -> N. D. | W16: =+$C16-U16 -> 0 | X16: =+IF(ISERROR(W16/U16),"N. D.",W16/U16) -> N. D.
A17: Guantes | C17: 454591.36 | D17: =+IF(ISERROR(C17/C92),"N. D.",C17/C92) -> 1 | F17: 454591.36 | G17: =+IF(ISERROR(F17/F92),"N. D.",F17/F92) -> 1 | H17: =+$C17-F17 -> 0 | I17: =+IF(ISERROR(H17/F17),"N. D.",H17/F17) -> 0 | K17: 143423.73 | L17: =+IF(ISERROR(K17/K92),"N. D.",K17/K92) -> 1 | M17: =+$C17-K17 -> 311167.63 | N17: =+IF(ISERROR(M17/K17),"N. D.",M17/K17) -> 2.1695687 | P17: 8364 | Q17: =+IF(ISERROR(P17/P92),"N. D.",P17/P92) -> 1 | R17: =+$C17-P17 -> 446227.36 | S17: =+IF(ISERROR(R17/P17),"N. D.",R17/P17) -> 53.350952 | U17: 0 | V17: =+IF(ISERROR(U17/U92),"N. D.",U17/U92) -> N. D. | W17: =+$C17-U17 -> 454591.36 | X17: =+IF(ISERROR(W17/U17),"N. D.",W17/U17) -> N. D.
A18: Penalizaciones | C18: 81701.01 | D18: =+IF(ISERROR(C18/C93),"N. D.",C18/C93) -> 1 | F18: 81701.01 | G18: =+IF(ISERROR(F18/F93),"N. D.",F18/F93) -> 1 | H18: =+$C18-F18 -> 0 | I18: =+IF(ISERROR(H18/F18),"N. D.",H18/F18) -> 0 | K18: 366165.08 | L18: =+IF(ISERROR(K18/K93),"N. D.",K18/K93) -> 1 | M18: =+$C18-K18 -> -284464.07 | N18: =+IF(ISERROR(M18/K18),"N. D.",M18/K18) -> -0.77687384 | P18: 77784.11 | Q18: =+IF(ISERROR(P18/P93),"N. D.",P18/P93) -> 1 | R18: =+$C18-P18 -> 3916.9 | S18: =+IF(ISERROR(R18/P18),"N. D.",R18/P18) -> 0.050356043 | U18: 20713.8 | V18: =+IF(ISERROR(U18/U93),"N. D.",U18/U93) -> 1 | W18: =+$C18-U18 -> 60987.21 | X18: =+IF(ISERROR(W18/U18),"N. D.",W18/U18) -> 2.9442792
A19: Otros Ingresos Operativos de Plazas | C19: 0 | D19: =+IF(ISERROR(C19/C94),"N. D.",C19/C94) -> N. D. | F19: 0 | G19: =+IF(ISERROR(F19/F94),"N. D.",F19/F94) -> N. D. | H19: =+$C19-F19 -> 0 | I19: =+IF(ISERROR(H19/F19),"N. D.",H19/F19) -> N. D. | K19: 0 | L19: =+IF(ISERROR(K19/K94),"N. D.",K19/K94) -> N. D. | M19: =+$C19-K19 -> 0 | N19: =+IF(ISERROR(M19/K19),"N. D.",M19/K19) -> N. D. | P19: 0 | Q19: =+IF(ISERROR(P19/P94),"N. D.",P19/P94) -> N. D. | R19: =+$C19-P19 -> 0 | S19: =+IF(ISERROR(R19/P19),"N. D.",R19/P19) -> N. D. | U19: 88174.26 | V19: =+IF(ISERROR(U19/U94),"N. D.",U19/U94) -> 1 | W19: =+$C19-U19 -> -88174.26 | X19: =+IF(ISERROR(W19/U19),"N. D.",W19/U19) -> -1
A20: Ingresos por Servicios: | C20: =+SUM(C21:C29) -> 0 | D20: =+IF(ISERROR(C20/C31),"N. D.",C20/C31) -> 0 | F20: =+SUM(F21:F29) -> 0 | G20: =+IF(ISERROR(F20/F31),"N. D.",F20/F31) -> 0 | H20: =+$C20-F20 -> 0 | I20: =+IF(ISERROR(H20/F20),"N. D.",H20/F20) -> N. D. | K20: =+SUM(K21:K29) -> 0 | L20: =+IF(ISERROR(K20/K31),"N. D.",K20/K31) -> 0 | M20: =+$C20-K20 -> 0 | N20: =+IF(ISERROR(M20/K20),"N. D.",M20/K20) -> N. D. | P20: =+SUM(P21:P29) -> 0 | Q20: =+IF(ISERROR(P20/P31),"N. D.",P20/P31) -> 0 | R20: =+$C20-P20 -> 0 | S20: =+IF(ISERROR(R20/P20),"N. D.",R20/P20) -> N. D. | U20: =+SUM(U21:U29) -> 0 | V20: =+IF(ISERROR(U20/U31),"N. D.",U20/U31) -> 0 | W20: =+$C20-U20 -> 0 | X20: =+IF(ISERROR(W20/U20),"N. D.",W20/U20) -> N. D.
A21: Administración de Nómina | C21: 0 | D21: =+IF(ISERROR(C21/C96),"N. D.",C21/C96) -> N. D. | F21: 0 | G21: =+IF(ISERROR(F21/F96),"N. D.",F21/F96) -> N. D. | H21: =+$C21-F21 -> 0 | I21: =+IF(ISERROR(H21/F21),"N. D.",H21/F21) -> N. D. | K21: 0 | L21: =+IF(ISERROR(K21/K96),"N. D.",K21/K96) -> N. D. | M21: =+$C21-K21 -> 0 | N21: =+IF(ISERROR(M21/K21),"N. D.",M21/K21) -> N. D. | P21: 0 | Q21: =+IF(ISERROR(P21/P96),"N. D.",P21/P96) -> N. D. | R21: =+$C21-P21 -> 0 | S21: =+IF(ISERROR(R21/P21),"N. D.",R21/P21) -> N. D. | U21: 0 | V21: =+IF(ISERROR(U21/U96),"N. D.",U21/U96) -> N. D. | W21: =+$C21-U21 -> 0 | X21: =+IF(ISERROR(W21/U21),"N. D.",W21/U21) -> N. D.
A22: Apertura/Cierre de Contratos | C22: 0 | D22: =+IF(ISERROR(C22/C97),"N. D.",C22/C97) -> N. D. | F22: 0 | G22: =+IF(ISERROR(F22/F97),"N. D.",F22/F97) -> N. D. | H22: =+$C22-F22 -> 0 | I22: =+IF(ISERROR(H22/F22),"N. D.",H22/F22) -> N. D. | K22: 0 | L22: =+IF(ISERROR(K22/K97),"N. D.",K22/K97) -> N. D. | M22: =+$C22-K22 -> 0 | N22: =+IF(ISERROR(M22/K22),"N. D.",M22/K22) -> N. D. | P22: 0 | Q22: =+IF(ISERROR(P22/P97),"N. D.",P22/P97) -> N. D. | R22: =+$C22-P22 -> 0 | S22: =+IF(ISERROR(R22/P22),"N. D.",R22/P22) -> N. D. | U22: 0 | V22: =+IF(ISERROR(U22/U97),"N. D.",U22/U97) -> N. D. | W22: =+$C22-U22 -> 0 | X22: =+IF(ISERROR(W22/U22),"N. D.",W22/U22) -> N. D.
A23: Renovación de Contratos | C23: 0 | D23: =+IF(ISERROR(C23/C98),"N. D.",C23/C98) -> N. D. | F23: 0 | G23: =+IF(ISERROR(F23/F98),"N. D.",F23/F98) -> N. D. | H23: =+$C23-F23 -> 0 | I23: =+IF(ISERROR(H23/F23),"N. D.",H23/F23) -> N. D. | K23: 0 | L23: =+IF(ISERROR(K23/K98),"N. D.",K23/K98) -> N. D. | M23: =+$C23-K23 -> 0 | N23: =+IF(ISERROR(M23/K23),"N. D.",M23/K23) -> N. D. | P23: 0 | Q23: =+IF(ISERROR(P23/P98),"N. D.",P23/P98) -> N. D. | R23: =+$C23-P23 -> 0 | S23: =+IF(ISERROR(R23/P23),"N. D.",R23/P23) -> N. D. | U23: 0 | V23: =+IF(ISERROR(U23/U98),"N. D.",U23/U98) -> N. D. | W23: =+$C23-U23 -> 0 | X23: =+IF(ISERROR(W23/U23),"N. D.",W23/U23) -> N. D.
A24: Administración de Obra | C24: 0 | D24: =+IF(ISERROR(C24/C99),"N. D.",C24/C99) -> N. D. | F24: 0 | G24: =+IF(ISERROR(F24/F99),"N. D.",F24/F99) -> N. D. | H24: =+$C24-F24 -> 0 | I24: =+IF(ISERROR(H24/F24),"N. D.",H24/F24) -> N. D. | K24: 0 | L24: =+IF(ISERROR(K24/K99),"N. D.",K24/K99) -> N. D. | M24: =+$C24-K24 -> 0 | N24: =+IF(ISERROR(M24/K24),"N. D.",M24/K24) -> N. D. | P24: 0 | Q24: =+IF(ISERROR(P24/P99),"N. D.",P24/P99) -> N. D. | R24: =+$C24-P24 -> 0 | S24: =+IF(ISERROR(R24/P24),"N. D.",R24/P24) -> N. D. | U24: 0 | V24: =+IF(ISERROR(U24/U99),"N. D.",U24/U99) -> N. D. | W24: =+$C24-U24 -> 0 | X24: =+IF(ISERROR(W24/U24),"N. D.",W24/U24) -> N. D.
A25: Administración de Plaza | C25: 0 | D25: =+IF(ISERROR(C25/C100),"N. D.",C25/C100) -> N. D. | F25: 0 | G25: =+IF(ISERROR(F25/F100),"N. D.",F25/F100) -> N. D. | H25: =+$C25-F25 -> 0 | I25: =+IF(ISERROR(H25/F25),"N. D.",H25/F25) -> N. D. | K25: 0 | L25: =+IF(ISERROR(K25/K100),"N. D.",K25/K100) -> N. D. | M25: =+$C25-K25 -> 0 | N25: =+IF(ISERROR(M25/K25),"N. D.",M25/K25) -> N. D. | P25: 0 | Q25: =+IF(ISERROR(P25/P100),"N. D.",P25/P100) -> N. D. | R25: =+$C25-P25 -> 0 | S25: =+IF(ISERROR(R25/P25),"N. D.",R25/P25) -> N. D. | U25: 0 | V25: =+IF(ISERROR(U25/U100),"N. D.",U25/U100) -> N. D. | W25: =+$C25-U25 -> 0 | X25: =+IF(ISERROR(W25/U25),"N. D.",W25/U25) -> N. D.
A26: Consultoría | C26: 0 | D26: =+IF(ISERROR(C26/C101),"N. D.",C26/C101) -> N. D. | F26: 0 | G26: =+IF(ISERROR(F26/F101),"N. D.",F26/F101) -> N. D. | H26: =+$C26-F26 -> 0 | I26: =+IF(ISERROR(H26/F26),"N. D.",H26/F26) -> N. D. | K26: 0 | L26: =+IF(ISERROR(K26/K101),"N. D.",K26/K101) -> N. D. | M26: =+$C26-K26 -> 0 | N26: =+IF(ISERROR(M26/K26),"N. D.",M26/K26) -> N. D. | P26: 0 | Q26: =+IF(ISERROR(P26/P101),"N. D.",P26/P101) -> N. D. | R26: =+$C26-P26 -> 0 | S26: =+IF(ISERROR(R26/P26),"N. D.",R26/P26) -> N. D. | U26: 0 | V26: =+IF(ISERROR(U26/U101),"N. D.",U26/U101) -> N. D. | W26: =+$C26-U26 -> 0 | X26: =+IF(ISERROR(W26/U26),"N. D.",W26/U26) -> N. D.
A27: Renta de Terrenos | C27: 0 | D27: =+IF(ISERROR(C27/C102),"N. D.",C27/C102) -> N. D. | F27: 0 | G27: =+IF(ISERROR(F27/F102),"N. D.",F27/F102) -> N. D. | H27: =+$C27-F27 -> 0 | I27: =+IF(ISERROR(H27/F27),"N. D.",H27/F27) -> N. D. | K27: 0 | L27: =+IF(ISERROR(K27/K102),"N. D.",K27/K102) -> N. D. | M27: =+$C27-K27 -> 0 | N27: =+IF(ISERROR(M27/K27),"N. D.",M27/K27) -> N. D. | P27: 0 | Q27: =+IF(ISERROR(P27/P102),"N. D.",P27/P102) -> N. D. | R27: =+$C27-P27 -> 0 | S27: =+IF(ISERROR(R27/P27),"N. D.",R27/P27) -> N. D. | U27: 0 | V27: =+IF(ISERROR(U27/U102),"N. D.",U27/U102) -> N. D. | W27: =+$C27-U27 -> 0 | X27: =+IF(ISERROR(W27/U27),"N. D.",W27/U27) -> N. D.
A28: Operación de Hotel | C28: 0 | D28: =+IF(ISERROR(C28/C103),"N. D.",C28/C103) -> N. D. | F28: 0 | G28: =+IF(ISERROR(F28/F103),"N. D.",F28/F103) -> N. D. | H28: =+$C28-F28 -> 0 | I28: =+IF(ISERROR(H28/F28),"N. D.",H28/F28) -> N. D. | K28: 0 | L28: =+IF(ISERROR(K28/K103),"N. D.",K28/K103) -> N. D. | M28: =+$C28-K28 -> 0 | N28: =+IF(ISERROR(M28/K28),"N. D.",M28/K28) -> N. D. | P28: 0 | Q28: =+IF(ISERROR(P28/P103),"N. D.",P28/P103) -> N. D. | R28: =+$C28-P28 -> 0 | S28: =+IF(ISERROR(R28/P28),"N. D.",R28/P28) -> N. D. | U28: 0 | V28: =+IF(ISERROR(U28/U103),"N. D.",U28/U103) -> N. D. | W28: =+$C28-U28 -> 0 | X28: =+IF(ISERROR(W28/U28),"N. D.",W28/U28) -> N. D.
A29: Otros Servicios | C29: 0 | D29: =+IF(ISERROR(C29/C104),"N. D.",C29/C104) -> N. D. | F29: 0 | G29: =+IF(ISERROR(F29/F104),"N. D.",F29/F104) -> N. D. | H29: =+$C29-F29 -> 0 | I29: =+IF(ISERROR(H29/F29),"N. D.",H29/F29) -> N. D. | K29: 0 | L29: =+IF(ISERROR(K29/K104),"N. D.",K29/K104) -> N. D. | M29: =+$C29-K29 -> 0 | N29: =+IF(ISERROR(M29/K29),"N. D.",M29/K29) -> N. D. | P29: 0 | Q29: =+IF(ISERROR(P29/P104),"N. D.",P29/P104) -> N. D. | R29: =+$C29-P29 -> 0 | S29: =+IF(ISERROR(R29/P29),"N. D.",R29/P29) -> N. D. | U29: 0 | V29: =+IF(ISERROR(U29/U104),"N. D.",U29/U104) -> N. D. | W29: =+$C29-U29 -> 0 | X29: =+IF(ISERROR(W29/U29),"N. D.",W29/U29) -> N. D.
A31: Total Ingresos Brutos | C31: =+C10+C20 -> 3.5583403e+08 | D31: =+IF(ISERROR(C31/C106),"N. D.",C31/C106) -> 1.0061696 | F31: =+F10+F20 -> 3.5583403e+08 | G31: =+IF(ISERROR(F31/F106),"N. D.",F31/F106) -> 1.0061696 | H31: =+$C31-F31 -> 0 | I31: =+IF(ISERROR(H31/F31),"N. D.",H31/F31) -> 0 | K31: =+K10+K20 -> 3.3032255e+08 | L31: =+IF(ISERROR(K31/K106),"N. D.",K31/K106) -> 1.0157138 | M31: =+$C31-K31 -> 25511483 | N31: =+IF(ISERROR(M31/K31),"N. D.",M31/K31) -> 0.077232038 | P31: =+P10+P20 -> 3.084476e+08 | Q31: =+IF(ISERROR(P31/P106),"N. D.",P31/P106) -> 1.0952458 | R31: =+$C31-P31 -> 47386425 | S31: =+IF(ISERROR(R31/P31),"N. D.",R31/P31) -> 0.15362877 | U31: =+U10+U20 -> 2.7768113e+08 | V31: =+IF(ISERROR(U31/U106),"N. D.",U31/U106) -> 1.0058918 | W31: =+$C31-U31 -> 78152899 | X31: =+IF(ISERROR(W31/U31),"N. D.",W31/U31) -> 0.28144836
A33: BONIFICACIONES SOBRE INGRESOS
A35: Ingresos por Operación de Plazas: | C35: =+SUM(C36:C44) -> 1681687.5 | D35: =+IF(ISERROR(C35/C56),"N. D.",C35/C56) -> 1 | F35: =+SUM(F36:F44) -> 1681687.5 | G35: =+IF(ISERROR(F35/F56),"N. D.",F35/F56) -> 1 | H35: =+$C35-F35 -> 0 | I35: =+IF(ISERROR(H35/F35),"N. D.",H35/F35) -> 0 | K35: =+SUM(K36:K44) -> 3132840 | L35: =+IF(ISERROR(K35/K56),"N. D.",K35/K56) -> 1 | M35: =+$C35-K35 -> -1451152.4 | N35: =+IF(ISERROR(M35/K35),"N. D.",M35/K35) -> -0.46320669 | P35: =+SUM(P36:P44) -> 22645531 | Q35: =+IF(ISERROR(P35/P56),"N. D.",P35/P56) -> 1 | R35: =+$C35-P35 -> -20963843 | S35: =+IF(ISERROR(R35/P35),"N. D.",R35/P35) -> -0.92573866 | U35: =+SUM(U36:U44) -> 695225.11 | V35: =+IF(ISERROR(U35/U56),"N. D.",U35/U56) -> 1 | W35: =+$C35-U35 -> 986462.44 | X35: =+IF(ISERROR(W35/U35),"N. D.",W35/U35) -> 1.4189108
A36: Renta Mínima | C36: 1455699.4 | D36: =+IF(ISERROR(C36/C86),"N. D.",C36/C86) -> 0.0058090117 | F36: 1455699.4 | G36: =+IF(ISERROR(F36/F86),"N. D.",F36/F86) -> 0.0058090117 | H36: =+$C36-F36 -> 0 | I36: =+IF(ISERROR(H36/F36),"N. D.",H36/F36) -> 0 | K36: 2367187.9 | L36: =+IF(ISERROR(K36/K86),"N. D.",K36/K86) -> 0.010066272 | M36: =+$C36-K36 -> -911488.46 | N36: =+IF(ISERROR(M36/K36),"N. D.",M36/K36) -> -0.38505117 | P36: 22340768 | Q36: =+IF(ISERROR(P36/P86),"N. D.",P36/P86) -> 0.1100821 | R36: =+$C36-P36 -> -20885069 | S36: =+IF(ISERROR(R36/P36),"N. D.",R36/P36) -> -0.93484112 | U36: 667922.79 | V36: =+IF(ISERROR(U36/U86),"N. D.",U36/U86) -> 0.0033773681 | W36: =+$C36-U36 -> 787776.64 | X36: =+IF(ISERROR(W36/U36),"N. D.",W36/U36) -> 1.1794427
A37: Renta Variable | C37: 0 | D37: =+IF(ISERROR(C37/C87),"N. D.",C37/C87) -> 0 | F37: 0 | G37: =+IF(ISERROR(F37/F87),"N. D.",F37/F87) -> 0 | H37: =+$C37-F37 -> 0 | I37: =+IF(ISERROR(H37/F37),"N. D.",H37/F37) -> N. D. | K37: 479385.12 | L37: =+IF(ISERROR(K37/K87),"N. D.",K37/K87) -> 0.029551735 | M37: =+$C37-K37 -> -479385.12 | N37: =+IF(ISERROR(M37/K37),"N. D.",M37/K37) -> -1 | P37: 95928.15 | Q37: =+IF(ISERROR(P37/P87),"N. D.",P37/P87) -> 0.0098737648 | R37: =+$C37-P37 -> -95928.15 | S37: =+IF(ISERROR(R37/P37),"N. D.",R37/P37) -> -1 | U37: 0 | V37: =+IF(ISERROR(U37/U87),"N. D.",U37/U87) -> 0 | W37: =+$C37-U37 -> 0 | X37: =+IF(ISERROR(W37/U37),"N. D.",W37/U37) -> N. D.
A38: Cuota de Mantenimiento | C38: 222882.72 | D38: =+IF(ISERROR(C38/C88),"N. D.",C38/C88) -> 0.006838092 | F38: 222882.72 | G38: =+IF(ISERROR(F38/F88),"N. D.",F38/F88) -> 0.006838092 | H38: =+$C38-F38 -> 0 | I38: =+IF(ISERROR(H38/F38),"N. D.",H38/F38) -> 0 | K38: 150932.51 | L38: =+IF(ISERROR(K38/K88),"N. D.",K38/K88) -> 0.0050533396 | M38: =+$C38-K38 -> 71950.21 | N38: =+IF(ISERROR(M38/K38),"N. D.",M38/K38) -> 0.47670452 | P38: 193935.2 | Q38: =+IF(ISERROR(P38/P88),"N. D.",P38/P88) -> 0.0068852193 | R38: =+$C38-P38 -> 28947.52 | S38: =+IF(ISERROR(R38/P38),"N. D.",R38/P38) -> 0.14926388 | U38: 27302.32 | V38: =+IF(ISERROR(U38/U88),"N. D.",U38/U88) -> 0.001207386 | W38: =+$C38-U38 -> 195580.4 | X38: =+IF(ISERROR(W38/U38),"N. D.",W38/U38) -> 7.1635084
A39: Publicidad | C39: 3105.4 | D39: =+IF(ISERROR(C39/C89),"N. D.",C39/C89) -> 0.0056994646 | F39: 3105.4 | G39: =+IF(ISERROR(F39/F89),"N. D.",F39/F89) -> 0.0056994646 | H39: =+$C39-F39 -> 0 | I39: =+IF(ISERROR(H39/F39),"N. D.",H39/F39) -> 0 | K39: 13402.94 | L39: =+IF(ISERROR(K39/K89),"N. D.",K39/K89) -> 0.018502551 | M39: =+$C39-K39 -> -10297.54 | N39: =+IF(ISERROR(M39/K39),"N. D.",M39/K39) -> -0.76830457 | P39: 4742.48 | Q39: =+IF(ISERROR(P39/P89),"N. D.",P39/P89) -> 0.0059826935 | R39: =+$C39-P39 -> -1637.08 | S39: =+IF(ISERROR(R39/P39),"N. D.",R39/P39) -> -0.34519492 | U39: 0 | V39: =+IF(ISERROR(U39/U89),"N. D.",U39/U89) -> 0 | W39: =+$C39-U39 -> 3105.4 | X39: =+IF(ISERROR(W39/U39),"N. D.",W39/U39) -> N. D.
A40: Estacionamiento | C40: 0 | D40: =+IF(ISERROR(C40/C90),"N. D.",C40/C90) -> 0 | F40: 0 | G40: =+IF(ISERROR(F40/F90),"N. D.",F40/F90) -> 0 | H40: =+$C40-F40 -> 0 | I40: =+IF(ISERROR(H40/F40),"N. D.",H40/F40) -> N. D. | K40: 121931.53 | L40: =+IF(ISERROR(K40/K90),"N. D.",K40/K90) -> 0.0028536575 | M40: =+$C40-K40 -> -121931.53 | N40: =+IF(ISERROR(M40/K40),"N. D.",M40/K40) -> -1 | P40: 10156.91 | Q40: =+IF(ISERROR(P40/P90),"N. D.",P40/P90) -> 0.000254454 | R40: =+$C40-P40 -> -10156.91 | S40: =+IF(ISERROR(R40/P40),"N. D.",R40/P40) -> -1 | U40: 0 | V40: =+IF(ISERROR(U40/U90),"N. D.",U40/U90) -> 0 | W40: =+$C40-U40 -> 0 | X40: =+IF(ISERROR(W40/U40),"N. D.",W40/U40) -> N. D.
A41: Cuotas Condominales | C41: 0 | D41: =+IF(ISERROR(C41/C91),"N. D.",C41/C91) -> N. D. | F41: 0 | G41: =+IF(ISERROR(F41/F91),"N. D.",F41/F91) -> N. D. | H41: =+$C41-F41 -> 0 | I41: =+IF(ISERROR(H41/F41),"N. D.",H41/F41) -> N. D. | K41: 0 | L41: =+IF(ISERROR(K41/K91),"N. D.",K41/K91) -> N. D. | M41: =+$C41-K41 -> 0 | N41: =+IF(ISERROR(M41/K41),"N. D.",M41/K41) -> N. D. | P41: 0 | Q41: =+IF(ISERROR(P41/P91),"N. D.",P41/P91) -> N. D. | R41: =+$C41-P41 -> 0 | S41: =+IF(ISERROR(R41/P41),"N. D.",R41/P41) -> N. D. | U41: 0 | V41: =+IF(ISERROR(U41/U91),"N. D.",U41/U91) -> N. D. | W41: =+$C41-U41 -> 0 | X41: =+IF(ISERROR(W41/U41),"N. D.",W41/U41) -> N. D.
A42: Guantes | C42: 0 | D42: =+IF(ISERROR(C42/C92),"N. D.",C42/C92) -> 0 | F42: 0 | G42: =+IF(ISERROR(F42/F92),"N. D.",F42/F92) -> 0 | H42: =+$C42-F42 -> 0 | I42: =+IF(ISERROR(H42/F42),"N. D.",H42/F42) -> N. D. | K42: 0 | L42: =+IF(ISERROR(K42/K92),"N. D.",K42/K92) -> 0 | M42: =+$C42-K42 -> 0 | N42: =+IF(ISERROR(M42/K42),"N. D.",M42/K42) -> N. D. | P42: 0 | Q42: =+IF(ISERROR(P42/P92),"N. D.",P42/P92) -> 0 | R42: =+$C42-P42 -> 0 | S42: =+IF(ISERROR(R42/P42),"N. D.",R42/P42) -> N. D. | U42: 0 | V42: =+IF(ISERROR(U42/U92),"N. D.",U42/U92) -> N. D. | W42: =+$C42-U42 -> 0 | X42: =+IF(ISERROR(W42/U42),"N. D.",W42/U42) -> N. D.
A43: Penalizaciones | C43: 0 | D43: =+IF(ISERROR(C43/C93),"N. D.",C43/C93) -> 0 | F43: 0 | G43: =+IF(ISERROR(F43/F93),"N. D.",F43/F93) -> 0 | H43: =+$C43-F43 -> 0 | I43: =+IF(ISERROR(H43/F43),"N. D.",H43/F43) -> N. D. | K43: 0 | L43: =+IF(ISERROR(K43/K93),"N. D.",K43/K93) -> 0 | M43: =+$C43-K43 -> 0 | N43: =+IF(ISERROR(M43/K43),"N. D.",M43/K43) -> N. D. | P43: 0 | Q43: =+IF(ISERROR(P43/P93),"N. D.",P43/P93) -> 0 | R43: =+$C43-P43 -> 0 | S43: =+IF(ISERROR(R43/P43),"N. D.",R43/P43) -> N. D. | U43: 0 | V43: =+IF(ISERROR(U43/U93),"N. D.",U43/U93) -> 0 | W43: =+$C43-U43 -> 0 | X43: =+IF(ISERROR(W43/U43),"N. D.",W43/U43) -> N. D.
A44: Otros Ingresos Operativos de Plazas | C44: 0 | D44: =+IF(ISERROR(C44/C94),"N. D.",C44/C94) -> N. D. | F44: 0 | G44: =+IF(ISERROR(F44/F94),"N. D.",F44/F94) -> N. D. | H44: =+$C44-F44 -> 0 | I44: =+IF(ISERROR(H44/F44),"N. D.",H44/F44) -> N. D. | K44: 0 | L44: =+IF(ISERROR(K44/K94),"N. D.",K44/K94) -> N. D. | M44: =+$C44-K44 -> 0 | N44: =+IF(ISERROR(M44/K44),"N. D.",M44/K44) -> N. D. | P44: 0 | Q44: =+IF(ISERROR(P44/P94),"N. D.",P44/P94) -> N. D. | R44: =+$C44-P44 -> 0 | S44: =+IF(ISERROR(R44/P44),"N. D.",R44/P44) -> N. D. | U44: 0 | V44: =+IF(ISERROR(U44/U94),"N. D.",U44/U94) -> 0 | W44: =+$C44-U44 -> 0 | X44: =+IF(ISERROR(W44/U44),"N. D.",W44/U44) -> N. D.
A45: Ingresos por Servicios: | C45: =+SUM(C46:C54) -> 0 | D45: =+IF(ISERROR(C45/C56),"N. D.",C45/C56) -> 0 | F45: =+SUM(F46:F54) -> 0 | G45: =+IF(ISERROR(F45/F56),"N. D.",F45/F56) -> 0 | H45: =+$C45-F45 -> 0 | I45: =+IF(ISERROR(H45/F45),"N. D.",H45/F45) -> N. D. | K45: =+SUM(K46:K54) -> 0 | L45: =+IF(ISERROR(K45/K56),"N. D.",K45/K56) -> 0 | M45: =+$C45-K45 -> 0 | N45: =+IF(ISERROR(M45/K45),"N. D.",M45/K45) -> N. D. | P45: =+SUM(P46:P54) -> 0 | Q45: =+IF(ISERROR(P45/P56),"N. D.",P45/P56) -> 0 | R45: =+$C45-P45 -> 0 | S45: =+IF(ISERROR(R45/P45),"N. D.",R45/P45) -> N. D. | U45: =+SUM(U46:U54) -> 0 | V45: =+IF(ISERROR(U45/U56),"N. D.",U45/U56) -> 0 | W45: =+$C45-U45 -> 0 | X45: =+IF(ISERROR(W45/U45),"N. D.",W45/U45) -> N. D.
A46: Administración de Nómina | C46: 0 | D46: =+IF(ISERROR(C46/C96),"N. D.",C46/C96) -> N. D. | F46: 0 | G46: =+IF(ISERROR(F46/F96),"N. D.",F46/F96) -> N. D. | H46: =+$C46-F46 -> 0 | I46: =+IF(ISERROR(H46/F46),"N. D.",H46/F46) -> N. D. | K46: 0 | L46: =+IF(ISERROR(K46/K96),"N. D.",K46/K96) -> N. D. | M46: =+$C46-K46 -> 0 | N46: =+IF(ISERROR(M46/K46),"N. D.",M46/K46) -> N. D. | P46: 0 | Q46: =+IF(ISERROR(P46/P96),"N. D.",P46/P96) -> N. D. | R46: =+$C46-P46 -> 0 | S46: =+IF(ISERROR(R46/P46),"N. D.",R46/P46) -> N. D. | U46: 0 | V46: =+IF(ISERROR(U46/U96),"N. D.",U46/U96) -> N. D. | W46: =+$C46-U46 -> 0 | X46: =+IF(ISERROR(W46/U46),"N. D.",W46/U46) -> N. D.
A47: Apertura/Cierre de Contratos | C47: 0 | D47: =+IF(ISERROR(C47/C97),"N. D.",C47/C97) -> N. D. | F47: 0 | G47: =+IF(ISERROR(F47/F97),"N. D.",F47/F97) -> N. D. | H47: =+$C47-F47 -> 0 | I47: =+IF(ISERROR(H47/F47),"N. D.",H47/F47) -> N. D. | K47: 0 | L47: =+IF(ISERROR(K47/K97),"N. D.",K47/K97) -> N. D. | M47: =+$C47-K47 -> 0 | N47: =+IF(ISERROR(M47/K47),"N. D.",M47/K47) -> N. D. | P47: 0 | Q47: =+IF(ISERROR(P47/P97),"N. D.",P47/P97) -> N. D. | R47: =+$C47-P47 -> 0 | S47: =+IF(ISERROR(R47/P47),"N. D.",R47/P47) -> N. D. | U47: 0 | V47: =+IF(ISERROR(U47/U97),"N. D.",U47/U97) -> N. D. | W47: =+$C47-U47 -> 0 | X47: =+IF(ISERROR(W47/U47),"N. D.",W47/U47) -> N. D.
A48: Renovación de Contratos | C48: 0 | D48: =+IF(ISERROR(C48/C98),"N. D.",C48/C98) -> N. D. | F48: 0 | G48: =+IF(ISERROR(F48/F98),"N. D.",F48/F98) -> N. D. | H48: =+$C48-F48 -> 0 | I48: =+IF(ISERROR(H48/F48),"N. D.",H48/F48) -> N. D. | K48: 0 | L48: =+IF(ISERROR(K48/K98),"N. D.",K48/K98) -> N. D. | M48: =+$C48-K48 -> 0 | N48: =+IF(ISERROR(M48/K48),"N. D.",M48/K48) -> N. D. | P48: 0 | Q48: =+IF(ISERROR(P48/P98),"N. D.",P48/P98) -> N. D. | R48: =+$C48-P48 -> 0 | S48: =+IF(ISERROR(R48/P48),"N. D.",R48/P48) -> N. D. | U48: 0 | V48: =+IF(ISERROR(U48/U98),"N. D.",U48/U98) -> N. D. | W48: =+$C48-U48 -> 0 | X48: =+IF(ISERROR(W48/U48),"N. D.",W48/U48) -> N. D.
A49: Administración de Obra | C49: 0 | D49: =+IF(ISERROR(C49/C99),"N. D.",C49/C99) -> N. D. | F49: 0 | G49: =+IF(ISERROR(F49/F99),"N. D.",F49/F99) -> N. D. | H49: =+$C49-F49 -> 0 | I49: =+IF(ISERROR(H49/F49),"N. D.",H49/F49) -> N. D. | K49: 0 | L49: =+IF(ISERROR(K49/K99),"N. D.",K49/K99) -> N. D. | M49: =+$C49-K49 -> 0 | N49: =+IF(ISERROR(M49/K49),"N. D.",M49/K49) -> N. D. | P49: 0 | Q49: =+IF(ISERROR(P49/P99),"N. D.",P49/P99) -> N. D. | R49: =+$C49-P49 -> 0 | S49: =+IF(ISERROR(R49/P49),"N. D.",R49/P49) -> N. D. | U49: 0 | V49: =+IF(ISERROR(U49/U99),"N. D.",U49/U99) -> N. D. | W49: =+$C49-U49 -> 0 | X49: =+IF(ISERROR(W49/U49),"N. D.",W49/U49) -> N. D.
A50: Administración de Plaza | C50: 0 | D50: =+IF(ISERROR(C50/C100),"N. D.",C50/C100) -> N. D. | F50: 0 | G50: =+IF(ISERROR(F50/F100),"N. D.",F50/F100) -> N. D. | H50: =+$C50-F50 -> 0 | I50: =+IF(ISERROR(H50/F50),"N. D.",H50/F50) -> N. D. | K50: 0 | L50: =+IF(ISERROR(K50/K100),"N. D.",K50/K100) -> N. D. | M50: =+$C50-K50 -> 0 | N50: =+IF(ISERROR(M50/K50),"N. D.",M50/K50) -> N. D. | P50: 0 | Q50: =+IF(ISERROR(P50/P100),"N. D.",P50/P100) -> N. D. | R50: =+$C50-P50 -> 0 | S50: =+IF(ISERROR(R50/P50),"N. D.",R50/P50) -> N. D. | U50: 0 | V50: =+IF(ISERROR(U50/U100),"N. D.",U50/U100) -> N. D. | W50: =+$C50-U50 -> 0 | X50: =+IF(ISERROR(W50/U50),"N. D.",W50/U50) -> N. D.
A51: Consultoría | C51: 0 | D51: =+IF(ISERROR(C51/C101),"N. D.",C51/C101) -> N. D. | F51: 0 | G51: =+IF(ISERROR(F51/F101),"N. D.",F51/F101) -> N. D. | H51: =+$C51-F51 -> 0 | I51: =+IF(ISERROR(H51/F51),"N. D.",H51/F51) -> N. D. | K51: 0 | L51: =+IF(ISERROR(K51/K101),"N. D.",K51/K101) -> N. D. | M51: =+$C51-K51 -> 0 | N51: =+IF(ISERROR(M51/K51),"N. D.",M51/K51) -> N. D. | P51: 0 | Q51: =+IF(ISERROR(P51/P101),"N. D.",P51/P101) -> N. D. | R51: =+$C51-P51 -> 0 | S51: =+IF(ISERROR(R51/P51),"N. D.",R51/P51) -> N. D. | U51: 0 | V51: =+IF(ISERROR(U51/U101),"N. D.",U51/U101) -> N. D. | W51: =+$C51-U51 -> 0 | X51: =+IF(ISERROR(W51/U51),"N. D.",W51/U51) -> N. D.
A52: Renta de Terrenos | C52: 0 | D52: =+IF(ISERROR(C52/C102),"N. D.",C52/C102) -> N. D. | F52: 0 | G52: =+IF(ISERROR(F52/F102),"N. D.",F52/F102) -> N. D. | H52: =+$C52-F52 -> 0 | I52: =+IF(ISERROR(H52/F52),"N. D.",H52/F52) -> N. D. | K52: 0 | L52: =+IF(ISERROR(K52/K102),"N. D.",K52/K102) -> N. D. | M52: =+$C52-K52 -> 0 | N52: =+IF(ISERROR(M52/K52),"N. D.",M52/K52) -> N. D. | P52: 0 | Q52: =+IF(ISERROR(P52/P102),"N. D.",P52/P102) -> N. D. | R52: =+$C52-P52 -> 0 | S52: =+IF(ISERROR(R52/P52),"N. D.",R52/P52) -> N. D. | U52: 0 | V52: =+IF(ISERROR(U52/U102),"N. D.",U52/U102) -> N. D. | W52: =+$C52-U52 -> 0 | X52: =+IF(ISERROR(W52/U52),"N. D.",W52/U52) -> N. D.
A53: Operación de Hotel | C53: 0 | D53: =+IF(ISERROR(C53/C103),"N. D.",C53/C103) -> N. D. | F53: 0 | G53: =+IF(ISERROR(F53/F103),"N. D.",F53/F103) -> N. D. | H53: =+$C53-F53 -> 0 | I53: =+IF(ISERROR(H53/F53),"N. D.",H53/F53) -> N. D. | K53: 0 | L53: =+IF(ISERROR(K53/K103),"N. D.",K53/K103) -> N. D. | M53: =+$C53-K53 -> 0 | N53: =+IF(ISERROR(M53/K53),"N. D.",M53/K53) -> N. D. | P53: 0 | Q53: =+IF(ISERROR(P53/P103),"N. D.",P53/P103) -> N. D. | R53: =+$C53-P53 -> 0 | S53: =+IF(ISERROR(R53/P53),"N. D.",R53/P53) -> N. D. | U53: 0 | V53: =+IF(ISERROR(U53/U103),"N. D.",U53/U103) -> N. D. | W53: =+$C53-U53 -> 0 | X53: =+IF(ISERROR(W53/U53),"N. D.",W53/U53) -> N. D.
A54: Otros Servicios | C54: 0 | D54: =+IF(ISERROR(C54/C104),"N. D.",C54/C104) -> N. D. | F54: 0 | G54: =+IF(ISERROR(F54/F104),"N. D.",F54/F104) -> N. D. | H54: =+$C54-F54 -> 0 | I54: =+IF(ISERROR(H54/F54),"N. D.",H54/F54) -> N. D. | K54: 0 | L54: =+IF(ISERROR(K54/K104),"N. D.",K54/K104) -> N. D. | M54: =+$C54-K54 -> 0 | N54: =+IF(ISERROR(M54/K54),"N. D.",M54/K54) -> N. D. | P54: 0 | Q54: =+IF(ISERROR(P54/P104),"N. D.",P54/P104) -> N. D. | R54: =+$C54-P54 -> 0 | S54: =+IF(ISERROR(R54/P54),"N. D.",R54/P54) -> N. D. | U54: 0 | V54: =+IF(ISERROR(U54/U104),"N. D.",U54/U104) -> N. D. | W54: =+$C54-U54 -> 0 | X54: =+IF(ISERROR(W54/U54),"N. D.",W54/U54) -> N. D.
A56: Total Bonificaciones sobre Ingresos | C56: =+C35+C45 -> 1681687.5 | D56: =+IF(ISERROR(C56/C106),"N. D.",C56/C106) -> 0.0047552028 | F56: =+F35+F45 -> 1681687.5 | G56: =+IF(ISERROR(F56/F106),"N. D.",F56/F106) -> 0.0047552028 | H56: =+$C56-F56 -> 0 | I56: =+IF(ISERROR(H56/F56),"N. D.",H56/F56) -> 0 | K56: =+K35+K45 -> 3132840 | L56: =+IF(ISERROR(K56/K106),"N. D.",K56/K106) -> 0.0096332172 | M56: =+$C56-K56 -> -1451152.4 | N56: =+IF(ISERROR(M56/K56),"N. D.",M56/K56) -> -0.46320669 | P56: =+P35+P45 -> 22645531 | Q56: =+IF(ISERROR(P56/P106),"N. D.",P56/P106) -> 0.080410488 | R56: =+$C56-P56 -> -20963843 | S56: =+IF(ISERROR(R56/P56),"N. D.",R56/P56) -> -0.92573866 | U56: =+U35+U45 -> 695225.11 | V56: =+IF(ISERROR(U56/U106),"N. D.",U56/U106) -> 0.0025184328 | W56: =+$C56-U56 -> 986462.44 | X56: =+IF(ISERROR(W56/U56),"N. D.",W56/U56) -> 1.4189108
A58: DEVOLUCIONES SOBRE INGRESOS
A60: Ingresos por Operación de Plazas: | C60: =+SUM(C61:C69) -> 500220.48 | D60: =+IF(ISERROR(C60/C81),"N. D.",C60/C81) -> 1 | F60: =+SUM(F61:F69) -> 500220.48 | G60: =+IF(ISERROR(F60/F81),"N. D.",F60/F81) -> 1 | H60: =+$C60-F60 -> 0 | I60: =+IF(ISERROR(H60/F60),"N. D.",H60/F60) -> 0 | K60: =+SUM(K61:K69) -> 1977481.9 | L60: =+IF(ISERROR(K60/K81),"N. D.",K60/K81) -> 1 | M60: =+$C60-K60 -> -1477261.5 | N60: =+IF(ISERROR(M60/K60),"N. D.",M60/K60) -> -0.74704169 | P60: =+SUM(P61:P69) -> 4177978.5 | Q60: =+IF(ISERROR(P60/P81),"N. D.",P60/P81) -> 1 | R60: =+$C60-P60 -> -3677758 | S60: =+IF(ISERROR(R60/P60),"N. D.",R60/P60) -> -0.88027213 | U60: =+SUM(U61:U69) -> 931241.73 | V60: =+IF(ISERROR(U60/U81),"N. D.",U60/U81) -> 1 | W60: =+$C60-U60 -> -431021.25 | X60: =+IF(ISERROR(W60/U60),"N. D.",W60/U60) -> -0.46284572
A61: Renta Mínima | C61: 258698.6 | D61: =+IF(ISERROR(C61/C86),"N. D.",C61/C86) -> 0.0010323444 | F61: 258698.6 | G61: =+IF(ISERROR(F61/F86),"N. D.",F61/F86) -> 0.0010323444 | H61: =+$C61-F61 -> 0 | I61: =+IF(ISERROR(H61/F61),"N. D.",H61/F61) -> 0 | K61: 1724108.2 | L61: =+IF(ISERROR(K61/K86),"N. D.",K61/K86) -> 0.0073316288 | M61: =+$C61-K61 -> -1465409.6 | N61: =+IF(ISERROR(M61/K61),"N. D.",M61/K61) -> -0.84995223 | P61: 3032144.1 | Q61: =+IF(ISERROR(P61/P86),"N. D.",P61/P86) -> 0.014940614 | R61: =+$C61-P61 -> -2773445.5 | S61: =+IF(ISERROR(R61/P61),"N. D.",R61/P61) -> -0.9146813 | U61: 931241.73 | V61: =+IF(ISERROR(U61/U86),"N. D.",U61/U86) -> 0.0047088468 | W61: =+$C61-U61 -> -672543.13 | X61: =+IF(ISERROR(W61/U61),"N. D.",W61/U61) -> -0.72220038
A62: Renta Variable | C62: 0 | D62: =+IF(ISERROR(C62/C87),"N. D.",C62/C87) -> 0 | F62: 0 | G62: =+IF(ISERROR(F62/F87),"N. D.",F62/F87) -> 0 | H62: =+$C62-F62 -> 0 | I62: =+IF(ISERROR(H62/F62),"N. D.",H62/F62) -> N. D. | K62: 0 | L62: =+IF(ISERROR(K62/K87),"N. D.",K62/K87) -> 0 | M62: =+$C62-K62 -> 0 | N62: =+IF(ISERROR(M62/K62),"N. D.",M62/K62) -> N. D. | P62: 833470.37 | Q62: =+IF(ISERROR(P62/P87),"N. D.",P62/P87) -> 0.085788065 | R62: =+$C62-P62 -> -833470.37 | S62: =+IF(ISERROR(R62/P62),"N. D.",R62/P62) -> -1 | U62: 0 | V62: =+IF(ISERROR(U62/U87),"N. D.",U62/U87) -> 0 | W62: =+$C62-U62 -> 0 | X62: =+IF(ISERROR(W62/U62),"N. D.",W62/U62) -> N. D.
A63: Cuota de Mantenimiento | C63: 241521.88 | D63: =+IF(ISERROR(C63/C88),"N. D.",C63/C88) -> 0.0074099456 | F63: 241521.88 | G63: =+IF(ISERROR(F63/F88),"N. D.",F63/F88) -> 0.0074099456 | H63: =+$C63-F63 -> 0 | I63: =+IF(ISERROR(H63/F63),"N. D.",H63/F63) -> 0 | K63: 252635.65 | L63: =+IF(ISERROR(K63/K88),"N. D.",K63/K88) -> 0.0084584411 | M63: =+$C63-K63 -> -11113.77 | N63: =+IF(ISERROR(M63/K63),"N. D.",M63/K63) -> -0.043991297 | P63: 271752.72 | Q63: =+IF(ISERROR(P63/P88),"N. D.",P63/P88) -> 0.0096479498 | R63: =+$C63-P63 -> -30230.84 | S63: =+IF(ISERROR(R63/P63),"N. D.",R63/P63) -> -0.11124393 | U63: 0 | V63: =+IF(ISERROR(U63/U88),"N. D.",U63/U88) -> 0 | W63: =+$C63-U63 -> 241521.88 | X63: =+IF(ISERROR(W63/U63),"N. D.",W63/U63) -> N. D.
A64: Publicidad | C64: 0 | D64: =+IF(ISERROR(C64/C89),"N. D.",C64/C89) -> 0 | F64: 0 | G64: =+IF(ISERROR(F64/F89),"N. D.",F64/F89) -> 0 | H64: =+$C64-F64 -> 0 | I64: =+IF(ISERROR(H64/F64),"N. D.",H64/F64) -> N. D. | K64: 182.52 | L64: =+IF(ISERROR(K64/K89),"N. D.",K64/K89) -> 0.00025196603 | M64: =+$C64-K64 -> -182.52 | N64: =+IF(ISERROR(M64/K64),"N. D.",M64/K64) -> -1 | P64: 40611.32 | Q64: =+IF(ISERROR(P64/P89),"N. D.",P64/P89) -> 0.051231651 | R64: =+$C64-P64 -> -40611.32 | S64: =+IF(ISERROR(R64/P64),"N. D.",R64/P64) -> -1 | U64: 0 | V64: =+IF(ISERROR(U64/U89),"N. D.",U64/U89) -> 0 | W64: =+$C64-U64 -> 0 | X64: =+IF(ISERROR(W64/U64),"N. D.",W64/U64) -> N. D.
A65: Estacionamiento | C65: 0 | D65: =+IF(ISERROR(C65/C90),"N. D.",C65/C90) -> 0 | F65: 0 | G65: =+IF(ISERROR(F65/F90),"N. D.",F65/F90) -> 0 | H65: =+$C65-F65 -> 0 | I65: =+IF(ISERROR(H65/F65),"N. D.",H65/F65) -> N. D. | K65: 555.56 | L65: =+IF(ISERROR(K65/K90),"N. D.",K65/K90) -> 1.3002198e-05 | M65: =+$C65-K65 -> -555.56 | N65: =+IF(ISERROR(M65/K65),"N. D.",M65/K65) -> -1 | P65: 0 | Q65: =+IF(ISERROR(P65/P90),"N. D.",P65/P90) -> 0 | R65: =+$C65-P65 -> 0 | S65: =+IF(ISERROR(R65/P65),"N. D.",R65/P65) -> N. D. | U65: 0 | V65: =+IF(ISERROR(U65/U90),"N. D.",U65/U90) -> 0 | W65: =+$C65-U65 -> 0 | X65: =+IF(ISERROR(W65/U65),"N. D.",W65/U65) -> N. D.
A66: Cuotas Condominales | C66: 0 | D66: =+IF(ISERROR(C66/C91),"N. D.",C66/C91) -> N. D. | F66: 0 | G66: =+IF(ISERROR(F66/F91),"N. D.",F66/F91) -> N. D. | H66: =+$C66-F66 -> 0 | I66: =+IF(ISERROR(H66/F66),"N. D.",H66/F66) -> N. D. | K66: 0 | L66: =+IF(ISERROR(K66/K91),"N. D.",K66/K91) -> N. D. | M66: =+$C66-K66 -> 0 | N66: =+IF(ISERROR(M66/K66),"N. D.",M66/K66) -> N. D. | P66: 0 | Q66: =+IF(ISERROR(P66/P91),"N. D.",P66/P91) -> N. D. | R66: =+$C66-P66 -> 0 | S66: =+IF(ISERROR(R66/P66),"N. D.",R66/P66) -> N. D. | U66: 0 | V66: =+IF(ISERROR(U66/U91),"N. D.",U66/U91) -> N. D. | W66: =+$C66-U66 -> 0 | X66: =+IF(ISERROR(W66/U66),"N. D.",W66/U66) -> N. D.
A67: Guantes | C67: 0 | D67: =+IF(ISERROR(C67/C92),"N. D.",C67/C92) -> 0 | F67: 0 | G67: =+IF(ISERROR(F67/F92),"N. D.",F67/F92) -> 0 | H67: =+$C67-F67 -> 0 | I67: =+IF(ISERROR(H67/F67),"N. D.",H67/F67) -> N. D. | K67: 0 | L67: =+IF(ISERROR(K67/K92),"N. D.",K67/K92) -> 0 | M67: =+$C67-K67 -> 0 | N67: =+IF(ISERROR(M67/K67),"N. D.",M67/K67) -> N. D. | P67: 0 | Q67: =+IF(ISERROR(P67/P92),"N. D.",P67/P92) -> 0 | R67: =+$C67-P67 -> 0 | S67: =+IF(ISERROR(R67/P67),"N. D.",R67/P67) -> N. D. | U67: 0 | V67: =+IF(ISERROR(U67/U92),"N. D.",U67/U92) -> N. D. | W67: =+$C67-U67 -> 0 | X67: =+IF(ISERROR(W67/U67),"N. D.",W67/U67) -> N. D.
A68: Penalizaciones | C68: 0 | D68: =+IF(ISERROR(C68/C93),"N. D.",C68/C93) -> 0 | F68: 0 | G68: =+IF(ISERROR(F68/F93),"N. D.",F68/F93) -> 0 | H68: =+$C68-F68 -> 0 | I68: =+IF(ISERROR(H68/F68),"N. D.",H68/F68) -> N. D. | K68: 0 | L68: =+IF(ISERROR(K68/K93),"N. D.",K68/K93) -> 0 | M68: =+$C68-K68 -> 0 | N68: =+IF(ISERROR(M68/K68),"N. D.",M68/K68) -> N. D. | P68: 0 | Q68: =+IF(ISERROR(P68/P93),"N. D.",P68/P93) -> 0 | R68: =+$C68-P68 -> 0 | S68: =+IF(ISERROR(R68/P68),"N. D.",R68/P68) -> N. D. | U68: 0 | V68: =+IF(ISERROR(U68/U93),"N. D.",U68/U93) -> 0 | W68: =+$C68-U68 -> 0 | X68: =+IF(ISERROR(W68/U68),"N. D.",W68/U68) -> N. D.
A69: Otros Ingresos Operativos de Plazas | C69: 0 | D69: =+IF(ISERROR(C69/C94),"N. D.",C69/C94) -> N. D. | F69: 0 | G69: =+IF(ISERROR(F69/F94),"N. D.",F69/F94) -> N. D. | H69: =+$C69-F69 -> 0 | I69: =+IF(ISERROR(H69/F69),"N. D.",H69/F69) -> N. D. | K69: 0 | L69: =+IF(ISERROR(K69/K94),"N. D.",K69/K94) -> N. D. | M69: =+$C69-K69 -> 0 | N69: =+IF(ISERROR(M69/K69),"N. D.",M69/K69) -> N. D. | P69: 0 | Q69: =+IF(ISERROR(P69/P94),"N. D.",P69/P94) -> N. D. | R69: =+$C69-P69 -> 0 | S69: =+IF(ISERROR(R69/P69),"N. D.",R69/P69) -> N. D. | U69: 0 | V69: =+IF(ISERROR(U69/U94),"N. D.",U69/U94) -> 0 | W69: =+$C69-U69 -> 0 | X69: =+IF(ISERROR(W69/U69),"N. D.",W69/U69) -> N. D.
A70: Ingresos por Servicios: | C70: =+SUM(C71:C79) -> 0 | D70: =+IF(ISERROR(C70/C81),"N. D.",C70/C81) -> 0 | F70: =+SUM(F71:F79) -> 0 | G70: =+IF(ISERROR(F70/F81),"N. D.",F70/F81) -> 0 | H70: =+$C70-F70 -> 0 | I70: =+IF(ISERROR(H70/F70),"N. D.",H70/F70) -> N. D. | K70: =+SUM(K71:K79) -> 0 | L70: =+IF(ISERROR(K70/K81),"N. D.",K70/K81) -> 0 | M70: =+$C70-K70 -> 0 | N70: =+IF(ISERROR(M70/K70),"N. D.",M70/K70) -> N. D. | P70: =+SUM(P71:P79) -> 0 | Q70: =+IF(ISERROR(P70/P81),"N. D.",P70/P81) -> 0 | R70: =+$C70-P70 -> 0 | S70: =+IF(ISERROR(R70/P70),"N. D.",R70/P70) -> N. D. | U70: =+SUM(U71:U79) -> 0 | V70: =+IF(ISERROR(U70/U81),"N. D.",U70/U81) -> 0 | W70: =+$C70-U70 -> 0 | X70: =+IF(ISERROR(W70/U70),"N. D.",W70/U70) -> N. D.
A71: Administración de Nómina | C71: 0 | D71: =+IF(ISERROR(C71/C96),"N. D.",C71/C96) -> N. D. | F71: 0 | G71: =+IF(ISERROR(F71/F96),"N. D.",F71/F96) -> N. D. | H71: =+$C71-F71 -> 0 | I71: =+IF(ISERROR(H71/F71),"N. D.",H71/F71) -> N. D. | K71: 0 | L71: =+IF(ISERROR(K71/K96),"N. D.",K71/K96) -> N. D. | M71: =+$C71-K71 -> 0 | N71: =+IF(ISERROR(M71/K71),"N. D.",M71/K71) -> N. D. | P71: 0 | Q71: =+IF(ISERROR(P71/P96),"N. D.",P71/P96) -> N. D. | R71: =+$C71-P71 -> 0 | S71: =+IF(ISERROR(R71/P71),"N. D.",R71/P71) -> N. D. | U71: 0 | V71: =+IF(ISERROR(U71/U96),"N. D.",U71/U96) -> N. D. | W71: =+$C71-U71 -> 0 | X71: =+IF(ISERROR(W71/U71),"N. D.",W71/U71) -> N. D.
A72: Apertura/Cierre de Contratos | C72: 0 | D72: =+IF(ISERROR(C72/C97),"N. D.",C72/C97) -> N. D. | F72: 0 | G72: =+IF(ISERROR(F72/F97),"N. D.",F72/F97) -> N. D. | H72: =+$C72-F72 -> 0 | I72: =+IF(ISERROR(H72/F72),"N. D.",H72/F72) -> N. D. | K72: 0 | L72: =+IF(ISERROR(K72/K97),"N. D.",K72/K97) -> N. D. | M72: =+$C72-K72 -> 0 | N72: =+IF(ISERROR(M72/K72),"N. D.",M72/K72) -> N. D. | P72: 0 | Q72: =+IF(ISERROR(P72/P97),"N. D.",P72/P97) -> N. D. | R72: =+$C72-P72 -> 0 | S72: =+IF(ISERROR(R72/P72),"N. D.",R72/P72) -> N. D. | U72: 0 | V72: =+IF(ISERROR(U72/U97),"N. D.",U72/U97) -> N. D. | W72: =+$C72-U72 -> 0 | X72: =+IF(ISERROR(W72/U72),"N. D.",W72/U72) -> N. D.
A73: Renovación de Contratos | C73: 0 | D73: =+IF(ISERROR(C73/C98),"N. D.",C73/C98) -> N. D. | F73: 0 | G73: =+IF(ISERROR(F73/F98),"N. D.",F73/F98) -> N. D. | H73: =+$C73-F73 -> 0 | I73: =+IF(ISERROR(H73/F73),"N. D.",H73/F73) -> N. D. | K73: 0 | L73: =+IF(ISERROR(K73/K98),"N. D.",K73/K98) -> N. D. | M73: =+$C73-K73 -> 0 | N73: =+IF(ISERROR(M73/K73),"N. D.",M73/K73) -> N. D. | P73: 0 | Q73: =+IF(ISERROR(P73/P98),"N. D.",P73/P98) -> N. D. | R73: =+$C73-P73 -> 0 | S73: =+IF(ISERROR(R73/P73),"N. D.",R73/P73) -> N. D. | U73: 0 | V73: =+IF(ISERROR(U73/U98),"N. D.",U73/U98) -> N. D. | W73: =+$C73-U73 -> 0 | X73: =+IF(ISERROR(W73/U73),"N. D.",W73/U73) -> N. D.
A74: Administración de Obra | C74: 0 | D74: =+IF(ISERROR(C74/C99),"N. D.",C74/C99) -> N. D. | F74: 0 | G74: =+IF(ISERROR(F74/F99),"N. D.",F74/F99) -> N. D. | H74: =+$C74-F74 -> 0 | I74: =+IF(ISERROR(H74/F74),"N. D.",H74/F74) -> N. D. | K74: 0 | L74: =+IF(ISERROR(K74/K99),"N. D.",K74/K99) -> N. D. | M74: =+$C74-K74 -> 0 | N74: =+IF(ISERROR(M74/K74),"N. D.",M74/K74) -> N. D. | P74: 0 | Q74: =+IF(ISERROR(P74/P99),"N. D.",P74/P99) -> N. D. | R74: =+$C74-P74 -> 0 | S74: =+IF(ISERROR(R74/P74),"N. D.",R74/P74) -> N. D. | U74: 0 | V74: =+IF(ISERROR(U74/U99),"N. D.",U74/U99) -> N. D. | W74: =+$C74-U74 -> 0 | X74: =+IF(ISERROR(W74/U74),"N. D.",W74/U74) -> N. D.
A75: Administración de Plaza | C75: 0 | D75: =+IF(ISERROR(C75/C100),"N. D.",C75/C100) -> N. D. | F75: 0 | G75: =+IF(ISERROR(F75/F100),"N. D.",F75/F100) -> N. D. | H75: =+$C75-F75 -> 0 | I75: =+IF(ISERROR(H75/F75),"N. D.",H75/F75) -> N. D. | K75: 0 | L75: =+IF(ISERROR(K75/K100),"N. D.",K75/K100) -> N. D. | M75: =+$C75-K75 -> 0 | N75: =+IF(ISERROR(M75/K75),"N. D.",M75/K75) -> N. D. | P75: 0 | Q75: =+IF(ISERROR(P75/P100),"N. D.",P75/P100) -> N. D. | R75: =+$C75-P75 -> 0 | S75: =+IF(ISERROR(R75/P75),"N. D.",R75/P75) -> N. D. | U75: 0 | V75: =+IF(ISERROR(U75/U100),"N. D.",U75/U100) -> N. D. | W75: =+$C75-U75 -> 0 | X75: =+IF(ISERROR(W75/U75),"N. D.",W75/U75) -> N. D.
A76: Consultoría | C76: 0 | D76: =+IF(ISERROR(C76/C101),"N. D.",C76/C101) -> N. D. | F76: 0 | G76: =+IF(ISERROR(F76/F101),"N. D.",F76/F101) -> N. D. | H76: =+$C76-F76 -> 0 | I76: =+IF(ISERROR(H76/F76),"N. D.",H76/F76) -> N. D. | K76: 0 | L76: =+IF(ISERROR(K76/K101),"N. D.",K76/K101) -> N. D. | M76: =+$C76-K76 -> 0 | N76: =+IF(ISERROR(M76/K76),"N. D.",M76/K76) -> N. D. | P76: 0 | Q76: =+IF(ISERROR(P76/P101),"N. D.",P76/P101) -> N. D. | R76: =+$C76-P76 -> 0 | S76: =+IF(ISERROR(R76/P76),"N. D.",R76/P76) -> N. D. | U76: 0 | V76: =+IF(ISERROR(U76/U101),"N. D.",U76/U101) -> N. D. | W76: =+$C76-U76 -> 0 | X76: =+IF(ISERROR(W76/U76),"N. D.",W76/U76) -> N. D.
A77: Renta de Terrenos | C77: 0 | D77: =+IF(ISERROR(C77/C102),"N. D.",C77/C102) -> N. D. | F77: 0 | G77: =+IF(ISERROR(F77/F102),"N. D.",F77/F102) -> N. D. | H77: =+$C77-F77 -> 0 | I77: =+IF(ISERROR(H77/F77),"N. D.",H77/F77) -> N. D. | K77: 0 | L77: =+IF(ISERROR(K77/K102),"N. D.",K77/K102) -> N. D. | M77: =+$C77-K77 -> 0 | N77: =+IF(ISERROR(M77/K77),"N. D.",M77/K77) -> N. D. | P77: 0 | Q77: =+IF(ISERROR(P77/P102),"N. D.",P77/P102) -> N. D. | R77: =+$C77-P77 -> 0 | S77: =+IF(ISERROR(R77/P77),"N. D.",R77/P77) -> N. D. | U77: 0 | V77: =+IF(ISERROR(U77/U102),"N. D.",U77/U102) -> N. D. | W77: =+$C77-U77 -> 0 | X77: =+IF(ISERROR(W77/U77),"N. D.",W77/U77) -> N. D.
A78: Operación de Hotel | C78: 0 | D78: =+IF(ISERROR(C78/C103),"N. D.",C78/C103) -> N. D. | F78: 0 | G78: =+IF(ISERROR(F78/F103),"N. D.",F78/F103) -> N. D. | H78: =+$C78-F78 -> 0 | I78: =+IF(ISERROR(H78/F78),"N. D.",H78/F78) -> N. D. | K78: 0 | L78: =+IF(ISERROR(K78/K103),"N. D.",K78/K103) -> N. D. | M78: =+$C78-K78 -> 0 | N78: =+IF(ISERROR(M78/K78),"N. D.",M78/K78) -> N. D. | P78: 0 | Q78: =+IF(ISERROR(P78/P103),"N. D.",P78/P103) -> N. D. | R78: =+$C78-P78 -> 0 | S78: =+IF(ISERROR(R78/P78),"N. D.",R78/P78) -> N. D. | U78: 0 | V78: =+IF(ISERROR(U78/U103),"N. D.",U78/U103) -> N. D. | W78: =+$C78-U78 -> 0 | X78: =+IF(ISERROR(W78/U78),"N. D.",W78/U78) -> N. D.
A79: Otros Servicios | C79: 0 | D79: =+IF(ISERROR(C79/C104),"N. D.",C79/C104) -> N. D. | F79: 0 | G79: =+IF(ISERROR(F79/F104),"N. D.",F79/F104) -> N. D. | H79: =+$C79-F79 -> 0 | I79: =+IF(ISERROR(H79/F79),"N. D.",H79/F79) -> N. D. | K79: 0 | L79: =+IF(ISERROR(K79/K104),"N. D.",K79/K104) -> N. D. | M79: =+$C79-K79 -> 0 | N79: =+IF(ISERROR(M79/K79),"N. D.",M79/K79) -> N. D. | P79: 0 | Q79: =+IF(ISERROR(P79/P104),"N. D.",P79/P104) -> N. D. | R79: =+$C79-P79 -> 0 | S79: =+IF(ISERROR(R79/P79),"N. D.",R79/P79) -> N. D. | U79: 0 | V79: =+IF(ISERROR(U79/U104),"N. D.",U79/U104) -> N. D. | W79: =+$C79-U79 -> 0 | X79: =+IF(ISERROR(W79/U79),"N. D.",W79/U79) -> N. D.
A81: Total Devoluciones sobre Ventas | C81: =+C60+C70 -> 500220.48 | D81: =+IF(ISERROR(C81/C106),"N. D.",C81/C106) -> 0.0014144422 | F81: =+F60+F70 -> 500220.48 | G81: =+IF(ISERROR(F81/F106),"N. D.",F81/F106) -> 0.0014144422 | H81: =+$C81-F81 -> 0 | I81: =+IF(ISERROR(H81/F81),"N. D.",H81/F81) -> 0 | K81: =+K60+K70 -> 1977481.9 | L81: =+IF(ISERROR(K81/K106),"N. D.",K81/K106) -> 0.0060805892 | M81: =+$C81-K81 -> -1477261.5 | N81: =+IF(ISERROR(M81/K81),"N. D.",M81/K81) -> -0.74704169 | P81: =+P60+P70 -> 4177978.5 | Q81: =+IF(ISERROR(P81/P106),"N. D.",P81/P106) -> 0.014835302 | R81: =+$C81-P81 -> -3677758 | S81: =+IF(ISERROR(R81/P81),"N. D.",R81/P81) -> -0.88027213 | U81: =+U60+U70 -> 931241.73 | V81: =+IF(ISERROR(U81/U106),"N. D.",U81/U106) -> 0.0033733961 | W81: =+$C81-U81 -> -431021.25 | X81: =+IF(ISERROR(W81/U81),"N. D.",W81/U81) -> -0.46284572
A83: INGRESOS NETOS
A85: Ingresos por Operación de Plazas: | C85: =+SUM(C86:C94) -> 3.5365212e+08 | D85: =+IF(ISERROR(C85/C106),"N. D.",C85/C106) -> 1 | F85: =+SUM(F86:F94) -> 3.5365212e+08 | G85: =+IF(ISERROR(F85/F106),"N. D.",F85/F106) -> 1 | H85: =+$C85-F85 -> 0 | I85: =+IF(ISERROR(H85/F85),"N. D.",H85/F85) -> 0 | K85: =+SUM(K86:K94) -> 3.2521222e+08 | L85: =+IF(ISERROR(K85/K106),"N. D.",K85/K106) -> 1 | M85: =+$C85-K85 -> 28439897 | N85: =+IF(ISERROR(M85/K85),"N. D.",M85/K85) -> 0.087450272 | P85: =+SUM(P86:P94) -> 2.8162409e+08 | Q85: =+IF(ISERROR(P85/P106),"N. D.",P85/P106) -> 1 | R85: =+$C85-P85 -> 72028026 | S85: =+IF(ISERROR(R85/P85),"N. D.",R85/P85) -> 0.25575946 | U85: =+SUM(U86:U94) -> 2.7605466e+08 | V85: =+IF(ISERROR(U85/U106),"N. D.",U85/U106) -> 1 | W85: =+$C85-U85 -> 77597458 | X85: =+IF(ISERROR(W85/U85),"N. D.",W85/U85) -> 0.28109454
A86: Renta Mínima | C86: =+C11-C36-C61 -> 2.505933e+08 | D86: =+IF(ISERROR(C86/C86),"N. D.",C86/C86) -> 1 | F86: =+F11-F36-F61 -> 2.505933e+08 | G86: =+IF(ISERROR(F86/F86),"N. D.",F86/F86) -> 1 | H86: =+$C86-F86 -> 0 | I86: =+IF(ISERROR(H86/F86),"N. D.",H86/F86) -> 0 | K86: =+K11-K36-K61 -> 2.3516032e+08 | L86: =+IF(ISERROR(K86/K86),"N. D.",K86/K86) -> 1 | M86: =+$C86-K86 -> 15432981 | N86: =+IF(ISERROR(M86/K86),"N. D.",M86/K86) -> 0.065627485 | P86: =+P11-P36-P61 -> 2.0294641e+08 | Q86: =+IF(ISERROR(P86/P86),"N. D.",P86/P86) -> 1 | R86: =+$C86-P86 -> 47646892 | S86: =+IF(ISERROR(R86/P86),"N. D.",R86/P86) -> 0.23477573 | U86: =+U11-U36-U61 -> 1.9776429e+08 | V86: =+IF(ISERROR(U86/U86),"N. D.",U86/U86) -> 1 | W86: =+$C86-U86 -> 52829017 | X86: =+IF(ISERROR(W86/U86),"N. D.",W86/U86) -> 0.26713123
A87: Renta Variable | C87: =+C12-C37-C62 -> 19073723 | D87: =+IF(ISERROR(C87/C87),"N. D.",C87/C87) -> 1 | F87: =+F12-F37-F62 -> 19073723 | G87: =+IF(ISERROR(F87/F87),"N. D.",F87/F87) -> 1 | H87: =+$C87-F87 -> 0 | I87: =+IF(ISERROR(H87/F87),"N. D.",H87/F87) -> 0 | K87: =+K12-K37-K62 -> 16221895 | L87: =+IF(ISERROR(K87/K87),"N. D.",K87/K87) -> 1 | M87: =+$C87-K87 -> 2851828.5 | N87: =+IF(ISERROR(M87/K87),"N. D.",M87/K87) -> 0.1758012 | P87: =+P12-P37-P62 -> 9715458.3 | Q87: =+IF(ISERROR(P87/P87),"N. D.",P87/P87) -> 1 | R87: =+$C87-P87 -> 9358264.8 | S87: =+IF(ISERROR(R87/P87),"N. D.",R87/P87) -> 0.96323452 | U87: =+U12-U37-U62 -> 21509016 | V87: =+IF(ISERROR(U87/U87),"N. D.",U87/U87) -> 1 | W87: =+$C87-U87 -> -2435293.1 | X87: =+IF(ISERROR(W87/U87),"N. D.",W87/U87) -> -0.11322197
A88: Cuota de Mantenimiento | C88: =+C13-C38-C63 -> 32594285 | D88: =+IF(ISERROR(C88/C88),"N. D.",C88/C88) -> 1 | F88: =+F13-F38-F63 -> 32594285 | G88: =+IF(ISERROR(F88/F88),"N. D.",F88/F88) -> 1 | H88: =+$C88-F88 -> 0 | I88: =+IF(ISERROR(H88/F88),"N. D.",H88/F88) -> 0 | K88: =+K13-K38-K63 -> 29867874 | L88: =+IF(ISERROR(K88/K88),"N. D.",K88/K88) -> 1 | M88: =+$C88-K88 -> 2726411.6 | N88: =+IF(ISERROR(M88/K88),"N. D.",M88/K88) -> 0.091282412 | P88: =+P13-P38-P63 -> 28166888 | Q88: =+IF(ISERROR(P88/P88),"N. D.",P88/P88) -> 1 | R88: =+$C88-P88 -> 4427397.4 | S88: =+IF(ISERROR(R88/P88),"N. D.",R88/P88) -> 0.15718447 | U88: =+U13-U38-U63 -> 22612752 | V88: =+IF(ISERROR(U88/U88),"N. D.",U88/U88) -> 1 | W88: =+$C88-U88 -> 9981533.3 | X88: =+IF(ISERROR(W88/U88),"N. D.",W88/U88) -> 0.4414117
A89: Publicidad | C89: =+C14-C39-C64 -> 544858.2 | D89: =+IF(ISERROR(C89/C89),"N. D.",C89/C89) -> 1 | F89: =+F14-F39-F64 -> 544858.2 | G89: =+IF(ISERROR(F89/F89),"N. D.",F89/F89) -> 1 | H89: =+$C89-F89 -> 0 | I89: =+IF(ISERROR(H89/F89),"N. D.",H89/F89) -> 0 | K89: =+K14-K39-K64 -> 724383.36 | L89: =+IF(ISERROR(K89/K89),"N. D.",K89/K89) -> 1 | M89: =+$C89-K89 -> -179525.16 | N89: =+IF(ISERROR(M89/K89),"N. D.",M89/K89) -> -0.2478317 | P89: =+P14-P39-P64 -> 792699.81 | Q89: =+IF(ISERROR(P89/P89),"N. D.",P89/P89) -> 1 | R89: =+$C89-P89 -> -247841.61 | S89: =+IF(ISERROR(R89/P89),"N. D.",R89/P89) -> -0.31265506 | U89: =+U14-U39-U64 -> 1229834.1 | V89: =+IF(ISERROR(U89/U89),"N. D.",U89/U89) -> 1 | W89: =+$C89-U89 -> -684975.88 | X89: =+IF(ISERROR(W89/U89),"N. D.",W89/U89) -> -0.55696609
A90: Estacionamiento | C90: =+C15-C40-C65 -> 50309657 | D90: =+IF(ISERROR(C90/C90),"N. D.",C90/C90) -> 1 | F90: =+F15-F40-F65 -> 50309657 | G90: =+IF(ISERROR(F90/F90),"N. D.",F90/F90) -> 1 | H90: =+$C90-F90 -> 0 | I90: =+IF(ISERROR(H90/F90),"N. D.",H90/F90) -> 0 | K90: =+K15-K40-K65 -> 42728159 | L90: =+IF(ISERROR(K90/K90),"N. D.",K90/K90) -> 1 | M90: =+$C90-K90 -> 7581498.4 | N90: =+IF(ISERROR(M90/K90),"N. D.",M90/K90) -> 0.17743564 | P90: =+P15-P40-P65 -> 39916488 | Q90: =+IF(ISERROR(P90/P90),"N. D.",P90/P90) -> 1 | R90: =+$C90-P90 -> 10393170 | S90: =+IF(ISERROR(R90/P90),"N. D.",R90/P90) -> 0.26037285 | U90: =+U15-U40-U65 -> 32829885 | V90: =+IF(ISERROR(U90/U90),"N. D.",U90/U90) -> 1 | W90: =+$C90-U90 -> 17479772 | X90: =+IF(ISERROR(W90/U90),"N. D.",W90/U90) -> 0.53243478
A91: Cuotas Condominales | C91: =+C16-C41-C66 -> 0 | D91: =+IF(ISERROR(C91/C91),"N. D.",C91/C91) -> N. D. | F91: =+F16-F41-F66 -> 0 | G91: =+IF(ISERROR(F91/F91),"N. D.",F91/F91) -> N. D. | H91: =+$C91-F91 -> 0 | I91: =+IF(ISERROR(H91/F91),"N. D.",H91/F91) -> N. D. | K91: =+K16-K41-K66 -> 0 | L91: =+IF(ISERROR(K91/K91),"N. D.",K91/K91) -> N. D. | M91: =+$C91-K91 -> 0 | N91: =+IF(ISERROR(M91/K91),"N. D.",M91/K91) -> N. D. | P91: =+P16-P41-P66 -> 0 | Q91: =+IF(ISERROR(P91/P91),"N. D.",P91/P91) -> N. D. | R91: =+$C91-P91 -> 0 | S91: =+IF(ISERROR(R91/P91),"N. D.",R91/P91) -> N. D. | U91: =+U16-U41-U66 -> 0 | V91: =+IF(ISERROR(U91/U91),"N. D.",U91/U91) -> N. D. | W91: =+$C91-U91 -> 0 | X91: =+IF(ISERROR(W91/U91),"N. D.",W91/U91) -> N. D.
A92: Guantes | C92: =+C17-C42-C67 -> 454591.36 | D92: =+IF(ISERROR(C92/C92),"N. D.",C92/C92) -> 1 | F92: =+F17-F42-F67 -> 454591.36 | G92: =+IF(ISERROR(F92/F92),"N. D.",F92/F92) -> 1 | H92: =+$C92-F92 -> 0 | I92: =+IF(ISERROR(H92/F92),"N. D.",H92/F92) -> 0 | K92: =+K17-K42-K67 -> 143423.73 | L92: =+IF(ISERROR(K92/K92),"N. D.",K92/K92) -> 1 | M92: =+$C92-K92 -> 311167.63 | N92: =+IF(ISERROR(M92/K92),"N. D.",M92/K92) -> 2.1695687 | P92: =+P17-P42-P67 -> 8364 | Q92: =+IF(ISERROR(P92/P92),"N. D.",P92/P92) -> 1 | R92: =+$C92-P92 -> 446227.36 | S92: =+IF(ISERROR(R92/P92),"N. D.",R92/P92) -> 53.350952 | U92: =+U17-U42-U67 -> 0 | V92: =+IF(ISERROR(U92/U92),"N. D.",U92/U92) -> N. D. | W92: =+$C92-U92 -> 454591.36 | X92: =+IF(ISERROR(W92/U92),"N. D.",W92/U92) -> N. D.
A93: Penalizaciones | C93: =+C18-C43-C68 -> 81701.01 | D93: =+IF(ISERROR(C93/C93),"N. D.",C93/C93) -> 1 | F93: =+F18-F43-F68 -> 81701.01 | G93: =+IF(ISERROR(F93/F93),"N. D.",F93/F93) -> 1 | H93: =+$C93-F93 -> 0 | I93: =+IF(ISERROR(H93/F93),"N. D.",H93/F93) -> 0 | K93: =+K18-K43-K68 -> 366165.08 | L93: =+IF(ISERROR(K93/K93),"N. D.",K93/K93) -> 1 | M93: =+$C93-K93 -> -284464.07 | N93: =+IF(ISERROR(M93/K93),"N. D.",M93/K93) -> -0.77687384 | P93: =+P18-P43-P68 -> 77784.11 | Q93: =+IF(ISERROR(P93/P93),"N. D.",P93/P93) -> 1 | R93: =+$C93-P93 -> 3916.9 | S93: =+IF(ISERROR(R93/P93),"N. D.",R93/P93) -> 0.050356043 | U93: =+U18-U43-U68 -> 20713.8 | V93: =+IF(ISERROR(U93/U93),"N. D.",U93/U93) -> 1 | W93: =+$C93-U93 -> 60987.21 | X93: =+IF(ISERROR(W93/U93),"N. D.",W93/U93) -> 2.9442792
A94: Otros Ingresos Operativos de Plazas | C94: =+C19-C44-C69 -> 0 | D94: =+IF(ISERROR(C94/C94),"N. D.",C94/C94) -> N. D. | F94: =+F19-F44-F69 -> 0 | G94: =+IF(ISERROR(F94/F94),"N. D.",F94/F94) -> N. D. | H94: =+$C94-F94 -> 0 | I94: =+IF(ISERROR(H94/F94),"N. D.",H94/F94) -> N. D. | K94: =+K19-K44-K69 -> 0 | L94: =+IF(ISERROR(K94/K94),"N. D.",K94/K94) -> N. D. | M94: =+$C94-K94 -> 0 | N94: =+IF(ISERROR(M94/K94),"N. D.",M94/K94) -> N. D. | P94: =+P19-P44-P69 -> 0 | Q94: =+IF(ISERROR(P94/P94),"N. D.",P94/P94) -> N. D. | R94: =+$C94-P94 -> 0 | S94: =+IF(ISERROR(R94/P94),"N. D.",R94/P94) -> N. D. | U94: =+U19-U44-U69 -> 88174.26 | V94: =+IF(ISERROR(U94/U94),"N. D.",U94/U94) -> 1 | W94: =+$C94-U94 -> -88174.26 | X94: =+IF(ISERROR(W94/U94),"N. D.",W94/U94) -> -1
A95: Ingresos por Servicios: | C95: =+SUM(C96:C104) -> 0 | D95: =+IF(ISERROR(C95/C106),"N. D.",C95/C106) -> 0 | F95: =+SUM(F96:F104) -> 0 | G95: =+IF(ISERROR(F95/F106),"N. D.",F95/F106) -> 0 | H95: =+$C95-F95 -> 0 | I95: =+IF(ISERROR(H95/F95),"N. D.",H95/F95) -> N. D. | K95: =+SUM(K96:K104) -> 0 | L95: =+IF(ISERROR(K95/K106),"N. D.",K95/K106) -> 0 | M95: =+$C95-K95 -> 0 | N95: =+IF(ISERROR(M95/K95),"N. D.",M95/K95) -> N. D. | P95: =+SUM(P96:P104) -> 0 | Q95: =+IF(ISERROR(P95/P106),"N. D.",P95/P106) -> 0 | R95: =+$C95-P95 -> 0 | S95: =+IF(ISERROR(R95/P95),"N. D.",R95/P95) -> N. D. | U95: =+SUM(U96:U104) -> 0 | V95: =+IF(ISERROR(U95/U106),"N. D.",U95/U106) -> 0 | W95: =+$C95-U95 -> 0 | X95: =+IF(ISERROR(W95/U95),"N. D.",W95/U95) -> N. D.
A96: Administración de Nómina | C96: =+C21-C46-C71 -> 0 | D96: =+IF(ISERROR(C96/C96),"N. D.",C96/C96) -> N. D. | F96: =+F21-F46-F71 -> 0 | G96: =+IF(ISERROR(F96/F96),"N. D.",F96/F96) -> N. D. | H96: =+$C96-F96 -> 0 | I96: =+IF(ISERROR(H96/F96),"N. D.",H96/F96) -> N. D. | K96: =+K21-K46-K71 -> 0 | L96: =+IF(ISERROR(K96/K96),"N. D.",K96/K96) -> N. D. | M96: =+$C96-K96 -> 0 | N96: =+IF(ISERROR(M96/K96),"N. D.",M96/K96) -> N. D. | P96: =+P21-P46-P71 -> 0 | Q96: =+IF(ISERROR(P96/P96),"N. D.",P96/P96) -> N. D. | R96: =+$C96-P96 -> 0 | S96: =+IF(ISERROR(R96/P96),"N. D.",R96/P96) -> N. D. | U96: =+U21-U46-U71 -> 0 | V96: =+IF(ISERROR(U96/U96),"N. D.",U96/U96) -> N. D. | W96: =+$C96-U96 -> 0 | X96: =+IF(ISERROR(W96/U96),"N. D.",W96/U96) -> N. D.
A97: Apertura/Cierre de Contratos | C97: =+C22-C47-C72 -> 0 | D97: =+IF(ISERROR(C97/C97),"N. D.",C97/C97) -> N. D. | F97: =+F22-F47-F72 -> 0 | G97: =+IF(ISERROR(F97/F97),"N. D.",F97/F97) -> N. D. | H97: =+$C97-F97 -> 0 | I97: =+IF(ISERROR(H97/F97),"N. D.",H97/F97) -> N. D. | K97: =+K22-K47-K72 -> 0 | L97: =+IF(ISERROR(K97/K97),"N. D.",K97/K97) -> N. D. | M97: =+$C97-K97 -> 0 | N97: =+IF(ISERROR(M97/K97),"N. D.",M97/K97) -> N. D. | P97: =+P22-P47-P72 -> 0 | Q97: =+IF(ISERROR(P97/P97),"N. D.",P97/P97) -> N. D. | R97: =+$C97-P97 -> 0 | S97: =+IF(ISERROR(R97/P97),"N. D.",R97/P97) -> N. D. | U97: =+U22-U47-U72 -> 0 | V97: =+IF(ISERROR(U97/U97),"N. D.",U97/U97) -> N. D. | W97: =+$C97-U97 -> 0 | X97: =+IF(ISERROR(W97/U97),"N. D.",W97/U97) -> N. D.
A98: Renovación de Contratos | C98: =+C23-C48-C73 -> 0 | D98: =+IF(ISERROR(C98/C98),"N. D.",C98/C98) -> N. D. | F98: =+F23-F48-F73 -> 0 | G98: =+IF(ISERROR(F98/F98),"N. D.",F98/F98) -> N. D. | H98: =+$C98-F98 -> 0 | I98: =+IF(ISERROR(H98/F98),"N. D.",H98/F98) -> N. D. | K98: =+K23-K48-K73 -> 0 | L98: =+IF(ISERROR(K98/K98),"N. D.",K98/K98) -> N. D. | M98: =+$C98-K98 -> 0 | N98: =+IF(ISERROR(M98/K98),"N. D.",M98/K98) -> N. D. | P98: =+P23-P48-P73 -> 0 | Q98: =+IF(ISERROR(P98/P98),"N. D.",P98/P98) -> N. D. | R98: =+$C98-P98 -> 0 | S98: =+IF(ISERROR(R98/P98),"N. D.",R98/P98) -> N. D. | U98: =+U23-U48-U73 -> 0 | V98: =+IF(ISERROR(U98/U98),"N. D.",U98/U98) -> N. D. | W98: =+$C98-U98 -> 0 | X98: =+IF(ISERROR(W98/U98),"N. D.",W98/U98) -> N. D.
A99: Administración de Obra | C99: =+C24-C49-C74 -> 0 | D99: =+IF(ISERROR(C99/C99),"N. D.",C99/C99) -> N. D. | F99: =+F24-F49-F74 -> 0 | G99: =+IF(ISERROR(F99/F99),"N. D.",F99/F99) -> N. D. | H99: =+$C99-F99 -> 0 | I99: =+IF(ISERROR(H99/F99),"N. D.",H99/F99) -> N. D. | K99: =+K24-K49-K74 -> 0 | L99: =+IF(ISERROR(K99/K99),"N. D.",K99/K99) -> N. D. | M99: =+$C99-K99 -> 0 | N99: =+IF(ISERROR(M99/K99),"N. D.",M99/K99) -> N. D. | P99: =+P24-P49-P74 -> 0 | Q99: =+IF(ISERROR(P99/P99),"N. D.",P99/P99) -> N. D. | R99: =+$C99-P99 -> 0 | S99: =+IF(ISERROR(R99/P99),"N. D.",R99/P99) -> N. D. | U99: =+U24-U49-U74 -> 0 | V99: =+IF(ISERROR(U99/U99),"N. D.",U99/U99) -> N. D. | W99: =+$C99-U99 -> 0 | X99: =+IF(ISERROR(W99/U99),"N. D.",W99/U99) -> N. D.
A100: Administración de Plaza | C100: =+C25-C50-C75 -> 0 | D100: =+IF(ISERROR(C100/C100),"N. D.",C100/C100) -> N. D. | F100: =+F25-F50-F75 -> 0 | G100: =+IF(ISERROR(F100/F100),"N. D.",F100/F100) -> N. D. | H100: =+$C100-F100 -> 0 | I100: =+IF(ISERROR(H100/F100),"N. D.",H100/F100) -> N. D. | K100: =+K25-K50-K75 -> 0 | L100: =+IF(ISERROR(K100/K100),"N. D.",K100/K100) -> N. D. | M100: =+$C100-K100 -> 0 | N100: =+IF(ISERROR(M100/K100),"N. D.",M100/K100) -> N. D. | P100: =+P25-P50-P75 -> 0 | Q100: =+IF(ISERROR(P100/P100),"N. D.",P100/P100) -> N. D. | R100: =+$C100-P100 -> 0 | S100: =+IF(ISERROR(R100/P100),"N. D.",R100/P100) -> N. D. | U100: =+U25-U50-U75 -> 0 | V100: =+IF(ISERROR(U100/U100),"N. D.",U100/U100) -> N. D. | W100: =+$C100-U100 -> 0 | X100: =+IF(ISERROR(W100/U100),"N. D.",W100/U100) -> N. D.
A101: Consultoría | C101: =+C26-C51-C76 -> 0 | D101: =+IF(ISERROR(C101/C101),"N. D.",C101/C101) -> N. D. | F101: =+F26-F51-F76 -> 0 | G101: =+IF(ISERROR(F101/F101),"N. D.",F101/F101) -> N. D. | H101: =+$C101-F101 -> 0 | I101: =+IF(ISERROR(H101/F101),"N. D.",H101/F101) -> N. D. | K101: =+K26-K51-K76 -> 0 | L101: =+IF(ISERROR(K101/K101),"N. D.",K101/K101) -> N. D. | M101: =+$C101-K101 -> 0 | N101: =+IF(ISERROR(M101/K101),"N. D.",M101/K101) -> N. D. | P101: =+P26-P51-P76 -> 0 | Q101: =+IF(ISERROR(P101/P101),"N. D.",P101/P101) -> N. D. | R101: =+$C101-P101 -> 0 | S101: =+IF(ISERROR(R101/P101),"N. D.",R101/P101) -> N. D. | U101: =+U26-U51-U76 -> 0 | V101: =+IF(ISERROR(U101/U101),"N. D.",U101/U101) -> N. D. | W101: =+$C101-U101 -> 0 | X101: =+IF(ISERROR(W101/U101),"N. D.",W101/U101) -> N. D.
A102: Renta de Terrenos | C102: =+C27-C52-C77 -> 0 | D102: =+IF(ISERROR(C102/C102),"N. D.",C102/C102) -> N. D. | F102: =+F27-F52-F77 -> 0 | G102: =+IF(ISERROR(F102/F102),"N. D.",F102/F102) -> N. D. | H102: =+$C102-F102 -> 0 | I102: =+IF(ISERROR(H102/F102),"N. D.",H102/F102) -> N. D. | K102: =+K27-K52-K77 -> 0 | L102: =+IF(ISERROR(K102/K102),"N. D.",K102/K102) -> N. D. | M102: =+$C102-K102 -> 0 | N102: =+IF(ISERROR(M102/K102),"N. D.",M102/K102) -> N. D. | P102: =+P27-P52-P77 -> 0 | Q102: =+IF(ISERROR(P102/P102),"N. D.",P102/P102) -> N. D. | R102: =+$C102-P102 -> 0 | S102: =+IF(ISERROR(R102/P102),"N. D.",R102/P102) -> N. D. | U102: =+U27-U52-U77 -> 0 | V102: =+IF(ISERROR(U102/U102),"N. D.",U102/U102) -> N. D. | W102: =+$C102-U102 -> 0 | X102: =+IF(ISERROR(W102/U102),"N. D.",W102/U102) -> N. D.
A103: Operación de Hotel | C103: =+C28-C53-C78 -> 0 | D103: =+IF(ISERROR(C103/C103),"N. D.",C103/C103) -> N. D. | F103: =+F28-F53-F78 -> 0 | G103: =+IF(ISERROR(F103/F103),"N. D.",F103/F103) -> N. D. | H103: =+$C103-F103 -> 0 | I103: =+IF(ISERROR(H103/F103),"N. D.",H103/F103) -> N. D. | K103: =+K28-K53-K78 -> 0 | L103: =+IF(ISERROR(K103/K103),"N. D.",K103/K103) -> N. D. | M103: =+$C103-K103 -> 0 | N103: =+IF(ISERROR(M103/K103),"N. D.",M103/K103) -> N. D. | P103: =+P28-P53-P78 -> 0 | Q103: =+IF(ISERROR(P103/P103),"N. D.",P103/P103) -> N. D. | R103: =+$C103-P103 -> 0 | S103: =+IF(ISERROR(R103/P103),"N. D.",R103/P103) -> N. D. | U103: =+U28-U53-U78 -> 0 | V103: =+IF(ISERROR(U103/U103),"N. D.",U103/U103) -> N. D. | W103: =+$C103-U103 -> 0 | X103: =+IF(ISERROR(W103/U103),"N. D.",W103/U103) -> N. D.
A104: Otros Servicios | C104: =+C29-C54-C79 -> 0 | D104: =+IF(ISERROR(C104/C104),"N. D.",C104/C104) -> N. D. | F104: =+F29-F54-F79 -> 0 | G104: =+IF(ISERROR(F104/F104),"N. D.",F104/F104) -> N. D. | H104: =+$C104-F104 -> 0 | I104: =+IF(ISERROR(H104/F104),"N. D.",H104/F104) -> N. D. | K104: =+K29-K54-K79 -> 0 | L104: =+IF(ISERROR(K104/K104),"N. D.",K104/K104) -> N. D. | M104: =+$C104-K104 -> 0 | N104: =+IF(ISERROR(M104/K104),"N. D.",M104/K104) -> N. D. | P104: =+P29-P54-P79 -> 0 | Q104: =+IF(ISERROR(P104/P104),"N. D.",P104/P104) -> N. D. | R104: =+$C104-P104 -> 0 | S104: =+IF(ISERROR(R104/P104),"N. D.",R104/P104) -> N. D. | U104: =+U29-U54-U79 -> 0 | V104: =+IF(ISERROR(U104/U104),"N. D.",U104/U104) -> N. D. | W104: =+$C104-U104 -> 0 | X104: =+IF(ISERROR(W104/U104),"N. D.",W104/U104) -> N. D.
A106: Total Ingresos Netos | C106: =+C85+C95 -> 3.5365212e+08 | D106: =+IF(ISERROR(C106/C106),"N. D.",C106/C106) -> 1 | F106: =+F85+F95 -> 3.5365212e+08 | G106: =+IF(ISERROR(F106/F106),"N. D.",F106/F106) -> 1 | H106: =+$C106-F106 -> 0 | I106: =+IF(ISERROR(H106/F106),"N. D.",H106/F106) -> 0 | K106: =+K85+K95 -> 3.2521222e+08 | L106: =+IF(ISERROR(K106/K106),"N. D.",K106/K106) -> 1 | M106: =+$C106-K106 -> 28439897 | N106: =+IF(ISERROR(M106/K106),"N. D.",M106/K106) -> 0.087450272 | P106: =+P85+P95 -> 2.8162409e+08 | Q106: =+IF(ISERROR(P106/P106),"N. D.",P106/P106) -> 1 | R106: =+$C106-P106 -> 72028026 | S106: =+IF(ISERROR(R106/P106),"N. D.",R106/P106) -> 0.25575946 | U106: =+U85+U95 -> 2.7605466e+08 | V106: =+IF(ISERROR(U106/U106),"N. D.",U106/U106) -> 1 | W106: =+$C106-U106 -> 77597458 | X106: =+IF(ISERROR(W106/U106),"N. D.",W106/U106) -> 0.28109454
A108: COSTO DE INGRESOS
A110: Ingresos por Operación de Plazas: | C110: =+SUM(C111:C119) -> 0 | D110: =+IF(ISERROR(C110/#REF!),"N. D.",C110/#REF!) -> N. D. | F110: =+SUM(F111:F119) -> 0 | G110: =+IF(ISERROR(F110/#REF!),"N. D.",F110/#REF!) -> N. D. | H110: =+$C110-F110 -> 0 | I110: =+IF(ISERROR(H110/F110),"N. D.",H110/F110) -> N. D. | K110: =+SUM(K111:K119) -> 0 | L110: =+IF(ISERROR(K110/#REF!),"N. D.",K110/#REF!) -> N. D. | M110: =+$C110-K110 -> 0 | N110: =+IF(ISERROR(M110/K110),"N. D.",M110/K110) -> N. D. | P110: =+SUM(P111:P119) -> 0 | Q110: =+IF(ISERROR(P110/#REF!),"N. D.",P110/#REF!) -> N. D. | R110: =+$C110-P110 -> 0 | S110: =+IF(ISERROR(R110/P110),"N. D.",R110/P110) -> N. D. | U110: =+SUM(U111:U119) -> 0 | V110: =+IF(ISERROR(U110/#REF!),"N. D.",U110/#REF!) -> N. D. | W110: =+$C110-U110 -> 0 | X110: =+IF(ISERROR(W110/U110),"N. D.",W110/U110) -> N. D.
A111: Renta Mínima | C111: 0 | D111: =+IF(ISERROR(C111/#REF!),"N. D.",C111/#REF!) -> N. D. | F111: 0 | G111: =+IF(ISERROR(F111/#REF!),"N. D.",F111/#REF!) -> N. D. | H111: =+$C111-F111 -> 0 | I111: =+IF(ISERROR(H111/F111),"N. D.",H111/F111) -> N. D. | K111: 0 | L111: =+IF(ISERROR(K111/#REF!),"N. D.",K111/#REF!) -> N. D. | M111: =+$C111-K111 -> 0 | N111: =+IF(ISERROR(M111/K111),"N. D.",M111/K111) -> N. D. | P111: 0 | Q111: =+IF(ISERROR(P111/#REF!),"N. D.",P111/#REF!) -> N. D. | R111: =+$C111-P111 -> 0 | S111: =+IF(ISERROR(R111/P111),"N. D.",R111/P111) -> N. D. | U111: 0 | V111: =+IF(ISERROR(U111/#REF!),"N. D.",U111/#REF!) -> N. D. | W111: =+$C111-U111 -> 0 | X111: =+IF(ISERROR(W111/U111),"N. D.",W111/U111) -> N. D.
A112: Renta Variable | C112: 0 | D112: =+IF(ISERROR(C112/#REF!),"N. D.",C112/#REF!) -> N. D. | F112: 0 | G112: =+IF(ISERROR(F112/#REF!),"N. D.",F112/#REF!) -> N. D. | H112: =+$C112-F112 -> 0 | I112: =+IF(ISERROR(H112/F112),"N. D.",H112/F112) -> N. D. | K112: 0 | L112: =+IF(ISERROR(K112/#REF!),"N. D.",K112/#REF!) -> N. D. | M112: =+$C112-K112 -> 0 | N112: =+IF(ISERROR(M112/K112),"N. D.",M112/K112) -> N. D. | P112: 0 | Q112: =+IF(ISERROR(P112/#REF!),"N. D.",P112/#REF!) -> N. D. | R112: =+$C112-P112 -> 0 | S112: =+IF(ISERROR(R112/P112),"N. D.",R112/P112) -> N. D. | U112: 0 | V112: =+IF(ISERROR(U112/#REF!),"N. D.",U112/#REF!) -> N. D. | W112: =+$C112-U112 -> 0 | X112: =+IF(ISERROR(W112/U112),"N. D.",W112/U112) -> N. D.
A113: Cuota de Mantenimiento | C113: 0 | D113: =+IF(ISERROR(C113/#REF!),"N. D.",C113/#REF!) -> N. D. | F113: 0 | G113: =+IF(ISERROR(F113/#REF!),"N. D.",F113/#REF!) -> N. D. | H113: =+$C113-F113 -> 0 | I113: =+IF(ISERROR(H113/F113),"N. D.",H113/F113) -> N. D. | K113: 0 | L113: =+IF(ISERROR(K113/#REF!),"N. D.",K113/#REF!) -> N. D. | M113: =+$C113-K113 -> 0 | N113: =+IF(ISERROR(M113/K113),"N. D.",M113/K113) -> N. D. | P113: 0 | Q113: =+IF(ISERROR(P113/#REF!),"N. D.",P113/#REF!) -> N. D. | R113: =+$C113-P113 -> 0 | S113: =+IF(ISERROR(R113/P113),"N. D.",R113/P113) -> N. D. | U113: 0 | V113: =+IF(ISERROR(U113/#REF!),"N. D.",U113/#REF!) -> N. D. | W113: =+$C113-U113 -> 0 | X113: =+IF(ISERROR(W113/U113),"N. D.",W113/U113) -> N. D.
A114: Publicidad | C114: 0 | D114: =+IF(ISERROR(C114/#REF!),"N. D.",C114/#REF!) -> N. D. | F114: 0 | G114: =+IF(ISERROR(F114/#REF!),"N. D.",F114/#REF!) -> N. D. | H114: =+$C114-F114 -> 0 | I114: =+IF(ISERROR(H114/F114),"N. D.",H114/F114) -> N. D. | K114: 0 | L114: =+IF(ISERROR(K114/#REF!),"N. D.",K114/#REF!) -> N. D. | M114: =+$C114-K114 -> 0 | N114: =+IF(ISERROR(M114/K114),"N. D.",M114/K114) -> N. D. | P114: 0 | Q114: =+IF(ISERROR(P114/#REF!),"N. D.",P114/#REF!) -> N. D. | R114: =+$C114-P114 -> 0 | S114: =+IF(ISERROR(R114/P114),"N. D.",R114/P114) -> N. D. | U114: 0 | V114: =+IF(ISERROR(U114/#REF!),"N. D.",U114/#REF!) -> N. D. | W114: =+$C114-U114 -> 0 | X114: =+IF(ISERROR(W114/U114),"N. D.",W114/U114) -> N. D.
A115: Estacionamiento | C115: 0 | D115: =+IF(ISERROR(C115/#REF!),"N. D.",C115/#REF!) -> N. D. | F115: 0 | G115: =+IF(ISERROR(F115/#REF!),"N. D.",F115/#REF!) -> N. D. | H115: =+$C115-F115 -> 0 | I115: =+IF(ISERROR(H115/F115),"N. D.",H115/F115) -> N. D. | K115: 0 | L115: =+IF(ISERROR(K115/#REF!),"N. D.",K115/#REF!) -> N. D. | M115: =+$C115-K115 -> 0 | N115: =+IF(ISERROR(M115/K115),"N. D.",M115/K115) -> N. D. | P115: 0 | Q115: =+IF(ISERROR(P115/#REF!),"N. D.",P115/#REF!) -> N. D. | R115: =+$C115-P115 -> 0 | S115: =+IF(ISERROR(R115/P115),"N. D.",R115/P115) -> N. D. | U115: 0 | V115: =+IF(ISERROR(U115/#REF!),"N. D.",U115/#REF!) -> N. D. | W115: =+$C115-U115 -> 0 | X115: =+IF(ISERROR(W115/U115),"N. D.",W115/U115) -> N. D.
A116: Cuotas Condominales | C116: 0 | D116: =+IF(ISERROR(C116/#REF!),"N. D.",C116/#REF!) -> N. D. | F116: 0 | G116: =+IF(ISERROR(F116/#REF!),"N. D.",F116/#REF!) -> N. D. | H116: =+$C116-F116 -> 0 | I116: =+IF(ISERROR(H116/F116),"N. D.",H116/F116) -> N. D. | K116: 0 | L116: =+IF(ISERROR(K116/#REF!),"N. D.",K116/#REF!) -> N. D. | M116: =+$C116-K116 -> 0 | N116: =+IF(ISERROR(M116/K116),"N. D.",M116/K116) -> N. D. | P116: 0 | Q116: =+IF(ISERROR(P116/#REF!),"N. D.",P116/#REF!) -> N. D. | R116: =+$C116-P116 -> 0 | S116: =+IF(ISERROR(R116/P116),"N. D.",R116/P116) -> N. D. | U116: 0 | V116: =+IF(ISERROR(U116/#REF!),"N. D.",U116/#REF!) -> N. D. | W116: =+$C116-U116 -> 0 | X116: =+IF(ISERROR(W116/U116),"N. D.",W116/U116) -> N. D.
A117: Guantes | C117: 0 | D117: =+IF(ISERROR(C117/#REF!),"N. D.",C117/#REF!) -> N. D. | F117: 0 | G117: =+IF(ISERROR(F117/#REF!),"N. D.",F117/#REF!) -> N. D. | H117: =+$C117-F117 -> 0 | I117: =+IF(ISERROR(H117/F117),"N. D.",H117/F117) -> N. D. | K117: 0 | L117: =+IF(ISERROR(K117/#REF!),"N. D.",K117/#REF!) -> N. D. | M117: =+$C117-K117 -> 0 | N117: =+IF(ISERROR(M117/K117),"N. D.",M117/K117) -> N. D. | P117: 0 | Q117: =+IF(ISERROR(P117/#REF!),"N. D.",P117/#REF!) -> N. D. | R117: =+$C117-P117 -> 0 | S117: =+IF(ISERROR(R117/P117),"N. D.",R117/P117) -> N. D. | U117: 0 | V117: =+IF(ISERROR(U117/#REF!),"N. D.",U117/#REF!) -> N. D. | W117: =+$C117-U117 -> 0 | X117: =+IF(ISERROR(W117/U117),"N. D.",W117/U117) -> N. D.
...

Sheet 2026P
C2: MENSUAL | S2: ACUMULADO
A5: ESTADO DE RESULTADOS | C5: P2K | D5: PSP | E5: PRG | F5: PC | G5: PLA | H5: PSI | I5: PPA | J5: PPB | K5: CBA | L5: TORR | M5: HOT | N5: PV | O5: DEPTOS | P5: PLP | Q5: PE | S5: P2K | T5: PSP | U5: PRG | V5: PC | W5: PLA | X5: PSI | Y5: PPA | Z5: PPB | AA5: CBA | AB5: TORR | AC5: HOT | AD5: PV | AE5: DEPTOS | AF5: PLP | AG5: PE | AI5: TOTAL | AJ5: TOTAL
A6: 2026P | AI6: MENSUAL | AJ6: ACUMULADO
A8: INGRESOS BRUTOS
A10: Ingresos por Operación de Plazas: | C10: =+SUM(C11:C19) -> 17030565 | D10: =+SUM(D11:D19) -> 10366156 | E10: =+SUM(E11:E19) -> 10888271 | F10: =+SUM(F11:F19) -> 878182.57 | G10: =+SUM(G11:G19) -> 0 | H10: =+SUM(H11:H19) -> 5814505.6 | I10: =+SUM(I11:I19) -> 1107544.9 | J10: =+SUM(J11:J19) -> 0 | ... Q10: =+SUM(Q11:Q19) -> 2316478.4 | S10: =+SUM(S11:S19) -> 96097240 | T10: =+SUM(T11:T19) -> 57983340 | U10: =+SUM(U11:U19) -> 63888277 | V10: =+SUM(V11:V19) -> 5158569.2 | W10: =+SUM(W11:W19) -> 0 | X10: =+SUM(X11:X19) -> 34142898 | Y10: =+SUM(Y11:Y19) -> 6041278.8 | Z10: =+SUM(Z11:Z19) -> 0 | ... AG10: =+SUM(AG11:AG19) -> 14408583 | AI10: =+SUM(AI11:AI19) -> 82481643 | AJ10: =+SUM(AJ11:AJ19) -> 4.7780709e+08
A11: Renta Mínima | C11: 10447173 | D11: 6660185 | E11: 8048538.4 | F11: 753371.17 | G11: 0 | H11: 4530714.4 | I11: 888433.2 | J11: 0 | K11: 7128167.8 | L11: 7150033 | M11: 416514.23 | N11: 5576387.1 | O11: 0 | P11: 1960687.3 | Q11: 1670117.6 | S11: 60754716 | T11: 38997584 | U11: 47740380 | V11: 4460732.8 | W11: 0 | X11: 26670084 | Y11: 5227015.1 | Z11: 0 | AA11: 41806192 | AB11: 42273569 | AC11: 2493454.5 | AD11: 32008726 | AE11: 0 | AF11: 11664485 | AG11: 9969443.3 | AI11: =+SUM(C11:Q11) -> 55230322 | AJ11: =+SUM(S11:AG11) -> 3.2406638e+08
A12: Renta Variable | C12: 1632424.5 | D12: 930917.75 | E12: 431731.42 | F12: 36095.693 | G12: 0 | H12: 50275.906 | I12: 116061.26 | J12: 0 | K12: 2951270.3 | L12: 405024.22 | M12: 462160 | N12: 811618.5 | O12: 0 | P12: 79138.997 | Q12: 375410.27 | S12: 6891213.6 | T12: 2947253.3 | U12: 2750351.5 | V12: 177440.95 | W12: 0 | X12: 566607.55 | Y12: 216084.25 | Z12: 0 | AA12: 18818463 | AB12: 2534091.2 | AC12: 3534533 | AD12: 2879190.6 | AE12: 0 | AF12: 440555.55 | AG12: 2776823.8 | AI12: =+SUM(C12:Q12) -> 8282128.9 | AJ12: =+SUM(S12:AG12) -> 44532608
A13: Cuota de Mantenimiento | C13: 1380058.4 | D13: 934548.12 | E13: 1093709.1 | F13: 86270.547 | G13: 0 | H13: 602917.35 | I13: 103050.48 | J13: 0 | K13: 1235489.8 | L13: 957861.69 | M13: 16651.423 | N13: 792080.76 | O13: 0 | P13: 300344 | Q13: 270950.55 | S13: 8033909 | T13: 5456779.4 | U13: 6482638.7 | V13: 505724.45 | W13: 0 | X13: 3581970.9 | Y13: 598179.49 | Z13: 0 | AA13: 7230183.9 | AB13: 5664654.4 | AC13: 99345.448 | AD13: 4532528.9 | AE13: 0 | AF13: 1769199.6 | AG13: 1662316.2 | AI13: =+SUM(C13:Q13) -> 7773932.2 | AJ13: =+SUM(S13:AG13) -> 45617430
A14: Publicidad | C14: 21434.397 | D14: 0 | E14: 13043.385 | F14: 2445.1647 | G14: 0 | H14: 2891.423 | I14: 0 | J14: 0 | K14: 0 | L14: 0 | M14: 0 | N14: 0 | O14: 0 | P14: 521.68626 | Q14: 0 | S14: 128606.38 | T14: 0 | U14: 78260.307 | V14: 14670.988 | W14: 0 | X14: 17348.538 | Y14: 0 | Z14: 0 | AA14: 0 | AB14: 0 | AC14: 0 | AD14: 0 | AE14: 0 | AF14: 3130.1176 | AG14: 0 | AI14: =+SUM(C14:Q14) -> 40336.055 | AJ14: =+SUM(S14:AG14) -> 242016.33
A15: Estacionamiento | C15: 3511434.6 | D15: 1826234.9 | E15: 1285428.9 | F15: 0 | G15: 0 | H15: 624489.6 | I15: 0 | J15: 0 | K15: 2210917 | L15: 0 | M15: 0 | N15: 1129810.5 | O15: 0 | P15: 0 | Q15: 0 | S15: 20041883 | T15: 10496100 | U15: 6741727.1 | V15: 0 | W15: 0 | X15: 3287585.2 | Y15: 0 | Z15: 0 | AA15: 12476577 | AB15: 0 | AC15: 0 | AD15: 6696350.6 | AE15: 0 | AF15: 0 | AG15: 0 | AI15: =+SUM(C15:Q15) -> 10588316 | AJ15: =+SUM(S15:AG15) -> 59740223
A16: Cuotas Condominales | C16: 0 | D16: 0 | E16: 0 | F16: 0 | G16: 0 | H16: 0 | I16: 0 | J16: 0 | K16: 0 | L16: 0 | M16: 0 | N16: 44486.447 | O16: 86447.167 | P16: 148558.08 | Q16: 0 | S16: 0 | T16: 0 | U16: 0 | V16: 0 | W16: 0 | X16: 0 | Y16: 0 | Z16: 0 | AA16: 0 | AB16: 0 | AC16: 0 | AD16: 270946.87 | AE16: 379212 | AF16: 981319.84 | AG16: 0 | AI16: =+SUM(C16:Q16) -> 279491.69 | AJ16: =+SUM(S16:AG16) -> 1631478.7
A17: Guantes | C17: 38040.223 | D17: 14270.551 | E17: 15819.824 | F17: 0 | G17: 0 | H17: 3216.9621 | I17: 0 | J17: 0 | K17: 163075.96 | L17: 0 | M17: 0 | N17: 1739.95 | O17: 0 | P17: 1452.4 | Q17: 0 | S17: 246912.44 | T17: 85623.306 | U17: 94918.943 | V17: 0 | W17: 0 | X17: 19301.773 | Y17: 0 | Z17: 0 | AA17: 978455.75 | AB17: 0 | AC17: 0 | AD17: 10439.7 | AE17: 0 | AF17: 8714.4 | AG17: 0 | AI17: =+SUM(C17:Q17) -> 237615.87 | AJ17: =+SUM(S17:AG17) -> 1444366.3
A18: Penalizaciones | C18: 0 | D18: 0 | E18: 0 | F18: 0 | G18: 0 | H18: 0 | I18: 0 | J18: 0 | K18: 0 | L18: 0 | M18: 0 | N18: 0 | O18: 0 | P18: 0 | Q18: 0 | S18: 0 | T18: 0 | U18: 0 | V18: 0 | W18: 0 | X18: 0 | Y18: 0 | Z18: 0 | AA18: 0 | AB18: 0 | AC18: 0 | AD18: 0 | AE18: 0 | AF18: 0 | AG18: 0 | AI18: =+SUM(C18:Q18) -> 0 | AJ18: =+SUM(S18:AG18) -> 0
A19: Otros Ingresos Operativos de Plazas | C19: 0 | D19: 0 | E19: 0 | F19: 0 | G19: 0 | H19: 0 | I19: 0 | J19: 0 | K19: 49500 | L19: 0 | M19: 0 | N19: 0 | O19: 0 | P19: 0 | Q19: 0 | S19: 0 | T19: 0 | U19: 0 | V19: 0 | W19: 0 | X19: 0 | Y19: 0 | Z19: 0 | AA19: 532588 | AB19: 0 | AC19: 0 | AD19: 0 | AE19: 0 | AF19: 0 | AG19: 0 | AI19: =+SUM(C19:Q19) -> 49500 | AJ19: =+SUM(S19:AG19) -> 532588
A20: Ingresos por Servicios: | C20: =+SUM(C21:C29) -> 0 | D20: =+SUM(D21:D29) -> 0 | E20: =+SUM(E21:E29) -> 0 | F20: =+SUM(F21:F29) -> 0 | G20: =+SUM(G21:G29) -> 0 | H20: =+SUM(H21:H29) -> 0 | I20: =+SUM(I21:I29) -> 0 | J20: =+SUM(J21:J29) -> 0 | ... Q20: =+SUM(Q21:Q29) -> 0 | S20: =+SUM(S21:S29) -> 0 | T20: =+SUM(T21:T29) -> 0 | U20: =+SUM(U21:U29) -> 0 | V20: =+SUM(V21:V29) -> 0 | W20: =+SUM(W21:W29) -> 0 | X20: =+SUM(X21:X29) -> 0 | Y20: =+SUM(Y21:Y29) -> 0 | Z20: =+SUM(Z21:Z29) -> 0 | ... AG20: =+SUM(AG21:AG29) -> 0 | AI20: =+SUM(AI21:AI29) -> 0 | AJ20: =+SUM(AJ21:AJ29) -> 0
A21: Administración de Nómina | C21: 0 | D21: 0 | E21: 0 | F21: 0 | G21: 0 | H21: 0 | I21: 0 | J21: 0 | K21: 0 | L21: 0 | M21: 0 | N21: 0 | O21: 0 | P21: 0 | Q21: 0 | S21: 0 | T21: 0 | U21: 0 | V21: 0 | W21: 0 | X21: 0 | Y21: 0 | Z21: 0 | AA21: 0 | AB21: 0 | AC21: 0 | AD21: 0 | AE21: 0 | AF21: 0 | AG21: 0 | AI21: =+SUM(R21:AF21) -> 0 | AJ21: =+SUM(S21:AG21) -> 0
A22: Apertura/Cierre de Contratos | C22: 0 | D22: 0 | E22: 0 | F22: 0 | G22: 0 | H22: 0 | I22: 0 | J22: 0 | K22: 0 | L22: 0 | M22: 0 | N22: 0 | O22: 0 | P22: 0 | Q22: 0 | S22: 0 | T22: 0 | U22: 0 | V22: 0 | W22: 0 | X22: 0 | Y22: 0 | Z22: 0 | AA22: 0 | AB22: 0 | AC22: 0 | AD22: 0 | AE22: 0 | AF22: 0 | AG22: 0 | AI22: =+SUM(R22:AF22) -> 0 | AJ22: =+SUM(S22:AG22) -> 0
A23: Renovación de Contratos | C23: 0 | D23: 0 | E23: 0 | F23: 0 | G23: 0 | H23: 0 | I23: 0 | J23: 0 | K23: 0 | L23: 0 | M23: 0 | N23: 0 | O23: 0 | P23: 0 | Q23: 0 | S23: 0 | T23: 0 | U23: 0 | V23: 0 | W23: 0 | X23: 0 | Y23: 0 | Z23: 0 | AA23: 0 | AB23: 0 | AC23: 0 | AD23: 0 | AE23: 0 | AF23: 0 | AG23: 0 | AI23: =+SUM(R23:AF23) -> 0 | AJ23: =+SUM(S23:AG23) -> 0
A24: Administración de Obra | C24: 0 | D24: 0 | E24: 0 | F24: 0 | G24: 0 | H24: 0 | I24: 0 | J24: 0 | K24: 0 | L24: 0 | M24: 0 | N24: 0 | O24: 0 | P24: 0 | Q24: 0 | S24: 0 | T24: 0 | U24: 0 | V24: 0 | W24: 0 | X24: 0 | Y24: 0 | Z24: 0 | AA24: 0 | AB24: 0 | AC24: 0 | AD24: 0 | AE24: 0 | AF24: 0 | AG24: 0 | AI24: =+SUM(R24:AF24) -> 0 | AJ24: =+SUM(S24:AG24) -> 0
A25: Administración de Plaza | C25: 0 | D25: 0 | E25: 0 | F25: 0 | G25: 0 | H25: 0 | I25: 0 | J25: 0 | K25: 0 | L25: 0 | M25: 0 | N25: 0 | O25: 0 | P25: 0 | Q25: 0 | S25: 0 | T25: 0 | U25: 0 | V25: 0 | W25: 0 | X25: 0 | Y25: 0 | Z25: 0 | AA25: 0 | AB25: 0 | AC25: 0 | AD25: 0 | AE25: 0 | AF25: 0 | AG25: 0 | AI25: =+SUM(R25:AF25) -> 0 | AJ25: =+SUM(S25:AG25) -> 0
A26: Consultoría | C26: 0 | D26: 0 | E26: 0 | F26: 0 | G26: 0 | H26: 0 | I26: 0 | J26: 0 | K26: 0 | L26: 0 | M26: 0 | N26: 0 | O26: 0 | P26: 0 | Q26: 0 | S26: 0 | T26: 0 | U26: 0 | V26: 0 | W26: 0 | X26: 0 | Y26: 0 | Z26: 0 | AA26: 0 | AB26: 0 | AC26: 0 | AD26: 0 | AE26: 0 | AF26: 0 | AG26: 0 | AI26: =+SUM(R26:AF26) -> 0 | AJ26: =+SUM(S26:AG26) -> 0
A27: Renta de Terrenos | C27: 0 | D27: 0 | E27: 0 | F27: 0 | G27: 0 | H27: 0 | I27: 0 | J27: 0 | K27: 0 | L27: 0 | M27: 0 | N27: 0 | O27: 0 | P27: 0 | Q27: 0 | S27: 0 | T27: 0 | U27: 0 | V27: 0 | W27: 0 | X27: 0 | Y27: 0 | Z27: 0 | AA27: 0 | AB27: 0 | AC27: 0 | AD27: 0 | AE27: 0 | AF27: 0 | AG27: 0 | AI27: =+SUM(R27:AF27) -> 0 | AJ27: =+SUM(S27:AG27) -> 0
A28: Operación de Hotel | C28: 0 | D28: 0 | E28: 0 | F28: 0 | G28: 0 | H28: 0 | I28: 0 | J28: 0 | K28: 0 | L28: 0 | M28: 0 | N28: 0 | O28: 0 | P28: 0 | Q28: 0 | S28: 0 | T28: 0 | U28: 0 | V28: 0 | W28: 0 | X28: 0 | Y28: 0 | Z28: 0 | AA28: 0 | AB28: 0 | AC28: 0 | AD28: 0 | AE28: 0 | AF28: 0 | AG28: 0 | AI28: =+SUM(R28:AF28) -> 0 | AJ28: =+SUM(S28:AG28) -> 0
A29: Otros Servicios | C29: 0 | D29: 0 | E29: 0 | F29: 0 | G29: 0 | H29: 0 | I29: 0 | J29: 0 | K29: 0 | L29: 0 | M29: 0 | N29: 0 | O29: 0 | P29: 0 | Q29: 0 | S29: 0 | T29: 0 | U29: 0 | V29: 0 | W29: 0 | X29: 0 | Y29: 0 | Z29: 0 | AA29: 0 | AB29: 0 | AC29: 0 | AD29: 0 | AE29: 0 | AF29: 0 | AG29: 0 | AI29: =+SUM(R29:AF29) -> 0 | AJ29: =+SUM(S29:AG29) -> 0
A31: Total Ingresos Brutos | C31: =+C10+C20 -> 17030565 | D31: =+D10+D20 -> 10366156 | E31: =+E10+E20 -> 10888271 | F31: =+F10+F20 -> 878182.57 | G31: =+G10+G20 -> 0 | H31: =+H10+H20 -> 5814505.6 | I31: =+I10+I20 -> 1107544.9 | J31: =+J10+J20 -> 0 | ... Q31: =+Q10+Q20 -> 2316478.4 | S31: =+S10+S20 -> 96097240 | T31: =+T10+T20 -> 57983340 | U31: =+U10+U20 -> 63888277 | V31: =+V10+V20 -> 5158569.2 | W31: =+W10+W20 -> 0 | X31: =+X10+X20 -> 34142898 | Y31: =+Y10+Y20 -> 6041278.8 | Z31: =+Z10+Z20 -> 0 | ... AG31: =+AG10+AG20 -> 14408583 | AI31: =+AI10+AI20 -> 82481643 | AJ31: =+AJ10+AJ20 -> 4.7780709e+08
A33: BONIFICACIONES SOBRE INGRESOS
A35: Ingresos por Operación de Plazas: | C35: =+SUM(C36:C44) -> 0 | D35: =+SUM(D36:D44) -> 0 | E35: =+SUM(E36:E44) -> 0 | F35: =+SUM(F36:F44) -> 0 | G35: =+SUM(G36:G44) -> 0 | H35: =+SUM(H36:H44) -> 15410 | I35: =+SUM(I36:I44) -> 0 | J35: =+SUM(J36:J44) -> 0 | ... Q35: =+SUM(Q36:Q44) -> 0 | S35: =+SUM(S36:S44) -> 0 | T35: =+SUM(T36:T44) -> 0 | U35: =+SUM(U36:U44) -> 0 | V35: =+SUM(V36:V44) -> 0 | W35: =+SUM(W36:W44) -> 0 | X35: =+SUM(X36:X44) -> 811348 | Y35: =+SUM(Y36:Y44) -> 0 | Z35: =+SUM(Z36:Z44) -> 0 | ... AG35: =+SUM(AG36:AG44) -> 0 | AI35: =+SUM(AI36:AI44) -> 182790.79 | AJ35: =+SUM(AJ36:AJ44) -> 2841644.6
A36: Renta Mínima | C36: 0 | D36: 0 | E36: 0 | F36: 0 | G36: 0 | H36: 15410 | I36: 0 | J36: 0 | K36: 0 | L36: 0 | M36: 0 | N36: 167380.79 | O36: 0 | P36: 0 | Q36: 0 | S36: 0 | T36: 0 | U36: 0 | V36: 0 | W36: 0 | X36: 811348 | Y36: 0 | Z36: 0 | AA36: 556490.16 | AB36: 0 | AC36: 0 | AD36: 1473806.5 | AE36: 0 | AF36: 0 | AG36: 0 | AI36: =+SUM(C36:Q36) -> 182790.79 | AJ36: =+SUM(S36:AG36) -> 2841644.6
A37: Renta Variable | C37: 0 | D37: 0 | E37: 0 | F37: 0 | G37: 0 | H37: 0 | I37: 0 | J37: 0 | K37: 0 | L37: 0 | M37: 0 | N37: 0 | O37: 0 | P37: 0 | Q37: 0 | S37: 0 | T37: 0 | U37: 0 | V37: 0 | W37: 0 | X37: 0 | Y37: 0 | Z37: 0 | AA37: 0 | AB37: 0 | AC37: 0 | AD37: 0 | AE37: 0 | AF37: 0 | AG37: 0 | AI37: =+SUM(C37:Q37) -> 0 | AJ37: =+SUM(S37:AG37) -> 0
A38: Cuota de Mantenimiento | C38: 0 | D38: 0 | E38: 0 | F38: 0 | G38: 0 | H38: 0 | I38: 0 | J38: 0 | K38: 0 | L38: 0 | M38: 0 | N38: 0 | O38: 0 | P38: 0 | Q38: 0 | S38: 0 | T38: 0 | U38: 0 | V38: 0 | W38: 0 | X38: 0 | Y38: 0 | Z38: 0 | AA38: 0 | AB38: 0 | AC38: 0 | AD38: 0 | AE38: 0 | AF38: 0 | AG38: 0 | AI38: =+SUM(C38:Q38) -> 0 | AJ38: =+SUM(S38:AG38) -> 0
A39: Publicidad | C39: 0 | D39: 0 | E39: 0 | F39: 0 | G39: 0 | H39: 0 | I39: 0 | J39: 0 | K39: 0 | L39: 0 | M39: 0 | N39: 0 | O39: 0 | P39: 0 | Q39: 0 | S39: 0 | T39: 0 | U39: 0 | V39: 0 | W39: 0 | X39: 0 | Y39: 0 | Z39: 0 | AA39: 0 | AB39: 0 | AC39: 0 | AD39: 0 | AE39: 0 | AF39: 0 | AG39: 0 | AI39: =+SUM(C39:Q39) -> 0 | AJ39: =+SUM(S39:AG39) -> 0
A40: Estacionamiento | C40: 0 | D40: 0 | E40: 0 | F40: 0 | G40: 0 | H40: 0 | I40: 0 | J40: 0 | K40: 0 | L40: 0 | M40: 0 | N40: 0 | O40: 0 | P40: 0 | Q40: 0 | S40: 0 | T40: 0 | U40: 0 | V40: 0 | W40: 0 | X40: 0 | Y40: 0 | Z40: 0 | AA40: 0 | AB40: 0 | AC40: 0 | AD40: 0 | AE40: 0 | AF40: 0 | AG40: 0 | AI40: =+SUM(C40:Q40) -> 0 | AJ40: =+SUM(S40:AG40) -> 0
A41: Cuotas Condominales | C41: 0 | D41: 0 | E41: 0 | F41: 0 | G41: 0 | H41: 0 | I41: 0 | J41: 0 | K41: 0 | L41: 0 | M41: 0 | N41: 0 | O41: 0 | P41: 0 | Q41: 0 | S41: 0 | T41: 0 | U41: 0 | V41: 0 | W41: 0 | X41: 0 | Y41: 0 | Z41: 0 | AA41: 0 | AB41: 0 | AC41: 0 | AD41: 0 | AE41: 0 | AF41: 0 | AG41: 0 | AI41: =+SUM(C41:Q41) -> 0 | AJ41: =+SUM(S41:AG41) -> 0
A42: Guantes | C42: 0 | D42: 0 | E42: 0 | F42: 0 | G42: 0 | H42: 0 | I42: 0 | J42: 0 | K42: 0 | L42: 0 | M42: 0 | N42: 0 | O42: 0 | P42: 0 | Q42: 0 | S42: 0 | T42: 0 | U42: 0 | V42: 0 | W42: 0 | X42: 0 | Y42: 0 | Z42: 0 | AA42: 0 | AB42: 0 | AC42: 0 | AD42: 0 | AE42: 0 | AF42: 0 | AG42: 0 | AI42: =+SUM(C42:Q42) -> 0 | AJ42: =+SUM(S42:AG42) -> 0
A43: Penalizaciones | C43: 0 | D43: 0 | E43: 0 | F43: 0 | G43: 0 | H43: 0 | I43: 0 | J43: 0 | K43: 0 | L43: 0 | M43: 0 | N43: 0 | O43: 0 | P43: 0 | Q43: 0 | S43: 0 | T43: 0 | U43: 0 | V43: 0 | W43: 0 | X43: 0 | Y43: 0 | Z43: 0 | AA43: 0 | AB43: 0 | AC43: 0 | AD43: 0 | AE43: 0 | AF43: 0 | AG43: 0 | AI43: =+SUM(C43:Q43) -> 0 | AJ43: =+SUM(S43:AG43) -> 0
A44: Otros Ingresos Operativos de Plazas | C44: 0 | D44: 0 | E44: 0 | F44: 0 | G44: 0 | H44: 0 | I44: 0 | J44: 0 | K44: 0 | L44: 0 | M44: 0 | N44: 0 | O44: 0 | P44: 0 | Q44: 0 | S44: 0 | T44: 0 | U44: 0 | V44: 0 | W44: 0 | X44: 0 | Y44: 0 | Z44: 0 | AA44: 0 | AB44: 0 | AC44: 0 | AD44: 0 | AE44: 0 | AF44: 0 | AG44: 0 | AI44: =+SUM(C44:Q44) -> 0 | AJ44: =+SUM(S44:AG44) -> 0
A45: Ingresos por Servicios: | C45: =+SUM(C46:C54) -> 0 | D45: =+SUM(D46:D54) -> 0 | E45: =+SUM(E46:E54) -> 0 | F45: =+SUM(F46:F54) -> 0 | G45: =+SUM(G46:G54) -> 0 | H45: =+SUM(H46:H54) -> 0 | I45: =+SUM(I46:I54) -> 0 | J45: =+SUM(J46:J54) -> 0 | ... Q45: =+SUM(Q46:Q54) -> 0 | S45: =+SUM(S46:S54) -> 0 | T45: =+SUM(T46:T54) -> 0 | U45: =+SUM(U46:U54) -> 0 | V45: =+SUM(V46:V54) -> 0 | W45: =+SUM(W46:W54) -> 0 | X45: =+SUM(X46:X54) -> 0 | Y45: =+SUM(Y46:Y54) -> 0 | Z45: =+SUM(Z46:Z54) -> 0 | ... AG45: =+SUM(AG46:AG54) -> 0 | AI45: =+SUM(AI46:AI54) -> 0 | AJ45: =+SUM(AJ46:AJ54) -> 0
A46: Administración de Nómina | C46: 0 | D46: 0 | E46: 0 | F46: 0 | G46: 0 | H46: 0 | I46: 0 | J46: 0 | K46: 0 | L46: 0 | M46: 0 | N46: 0 | O46: 0 | P46: 0 | Q46: 0 | S46: 0 | T46: 0 | U46: 0 | V46: 0 | W46: 0 | X46: 0 | Y46: 0 | Z46: 0 | AA46: 0 | AB46: 0 | AC46: 0 | AD46: 0 | AE46: 0 | AF46: 0 | AG46: 0 | AI46: =+SUM(R46:AF46) -> 0 | AJ46: =+SUM(S46:AG46) -> 0
A47: Apertura/Cierre de Contratos | C47: 0 | D47: 0 | E47: 0 | F47: 0 | G47: 0 | H47: 0 | I47: 0 | J47: 0 | K47: 0 | L47: 0 | M47: 0 | N47: 0 | O47: 0 | P47: 0 | Q47: 0 | S47: 0 | T47: 0 | U47: 0 | V47: 0 | W47: 0 | X47: 0 | Y47: 0 | Z47: 0 | AA47: 0 | AB47: 0 | AC47: 0 | AD47: 0 | AE47: 0 | AF47: 0 | AG47: 0 | AI47: =+SUM(R47:AF47) -> 0 | AJ47: =+SUM(S47:AG47) -> 0
A48: Renovación de Contratos | C48: 0 | D48: 0 | E48: 0 | F48: 0 | G48: 0 | H48: 0 | I48: 0 | J48: 0 | K48: 0 | L48: 0 | M48: 0 | N48: 0 | O48: 0 | P48: 0 | Q48: 0 | S48: 0 | T48: 0 | U48: 0 | V48: 0 | W48: 0 | X48: 0 | Y48: 0 | Z48: 0 | AA48: 0 | AB48: 0 | AC48: 0 | AD48: 0 | AE48: 0 | AF48: 0 | AG48: 0 | AI48: =+SUM(R48:AF48) -> 0 | AJ48: =+SUM(S48:AG48) -> 0
A49: Administración de Obra | C49: 0 | D49: 0 | E49: 0 | F49: 0 | G49: 0 | H49: 0 | I49: 0 | J49: 0 | K49: 0 | L49: 0 | M49: 0 | N49: 0 | O49: 0 | P49: 0 | Q49: 0 | S49: 0 | T49: 0 | U49: 0 | V49: 0 | W49: 0 | X49: 0 | Y49: 0 | Z49: 0 | AA49: 0 | AB49: 0 | AC49: 0 | AD49: 0 | AE49: 0 | AF49: 0 | AG49: 0 | AI49: =+SUM(R49:AF49) -> 0 | AJ49: =+SUM(S49:AG49) -> 0
A50: Administración de Plaza | C50: 0 | D50: 0 | E50: 0 | F50: 0 | G50: 0 | H50: 0 | I50: 0 | J50: 0 | K50: 0 | L50: 0 | M50: 0 | N50: 0 | O50: 0 | P50: 0 | Q50: 0 | S50: 0 | T50: 0 | U50: 0 | V50: 0 | W50: 0 | X50: 0 | Y50: 0 | Z50: 0 | AA50: 0 | AB50: 0 | AC50: 0 | AD50: 0 | AE50: 0 | AF50: 0 | AG50: 0 | AI50: =+SUM(R50:AF50) -> 0 | AJ50: =+SUM(S50:AG50) -> 0
A51: Consultoría | C51: 0 | D51: 0 | E51: 0 | F51: 0 | G51: 0 | H51: 0 | I51: 0 | J51: 0 | K51: 0 | L51: 0 | M51: 0 | N51: 0 | O51: 0 | P51: 0 | Q51: 0 | S51: 0 | T51: 0 | U51: 0 | V51: 0 | W51: 0 | X51: 0 | Y51: 0 | Z51: 0 | AA51: 0 | AB51: 0 | AC51: 0 | AD51: 0 | AE51: 0 | AF51: 0 | AG51: 0 | AI51: =+SUM(R51:AF51) -> 0 | AJ51: =+SUM(S51:AG51) -> 0
A52: Renta de Terrenos | C52: 0 | D52: 0 | E52: 0 | F52: 0 | G52: 0 | H52: 0 | I52: 0 | J52: 0 | K52: 0 | L52: 0 | M52: 0 | N52: 0 | O52: 0 | P52: 0 | Q52: 0 | S52: 0 | T52: 0 | U52: 0 | V52: 0 | W52: 0 | X52: 0 | Y52: 0 | Z52: 0 | AA52: 0 | AB52: 0 | AC52: 0 | AD52: 0 | AE52: 0 | AF52: 0 | AG52: 0 | AI52: =+SUM(R52:AF52) -> 0 | AJ52: =+SUM(S52:AG52) -> 0
A53: Operación de Hotel | C53: 0 | D53: 0 | E53: 0 | F53: 0 | G53: 0 | H53: 0 | I53: 0 | J53: 0 | K53: 0 | L53: 0 | M53: 0 | N53: 0 | O53: 0 | P53: 0 | Q53: 0 | S53: 0 | T53: 0 | U53: 0 | V53: 0 | W53: 0 | X53: 0 | Y53: 0 | Z53: 0 | AA53: 0 | AB53: 0 | AC53: 0 | AD53: 0 | AE53: 0 | AF53: 0 | AG53: 0 | AI53: =+SUM(R53:AF53) -> 0 | AJ53: =+SUM(S53:AG53) -> 0
A54: Otros Servicios | C54: 0 | D54: 0 | E54: 0 | F54: 0 | G54: 0 | H54: 0 | I54: 0 | J54: 0 | K54: 0 | L54: 0 | M54: 0 | N54: 0 | O54: 0 | P54: 0 | Q54: 0 | S54: 0 | T54: 0 | U54: 0 | V54: 0 | W54: 0 | X54: 0 | Y54: 0 | Z54: 0 | AA54: 0 | AB54: 0 | AC54: 0 | AD54: 0 | AE54: 0 | AF54: 0 | AG54: 0 | AI54: =+SUM(R54:AF54) -> 0 | AJ54: =+SUM(S54:AG54) -> 0
A56: Total Bonificaciones sobre Ingresos | C56: =+C35+C45 -> 0 | D56: =+D35+D45 -> 0 | E56: =+E35+E45 -> 0 | F56: =+F35+F45 -> 0 | G56: =+G35+G45 -> 0 | H56: =+H35+H45 -> 15410 | I56: =+I35+I45 -> 0 | J56: =+J35+J45 -> 0 | ... Q56: =+Q35+Q45 -> 0 | S56: =+S35+S45 -> 0 | T56: =+T35+T45 -> 0 | U56: =+U35+U45 -> 0 | V56: =+V35+V45 -> 0 | W56: =+W35+W45 -> 0 | X56: =+X35+X45 -> 811348 | Y56: =+Y35+Y45 -> 0 | Z56: =+Z35+Z45 -> 0 | ... AG56: =+AG35+AG45 -> 0 | AI56: =+AI35+AI45 -> 182790.79 | AJ56: =+AJ35+AJ45 -> 2841644.6
A58: DEVOLUCIONES SOBRE INGRESOS
A60: Ingresos por Operación de Plazas: | C60: =+SUM(C61:C69) -> 0 | D60: =+SUM(D61:D69) -> 0 | E60: =+SUM(E61:E69) -> 0 | F60: =+SUM(F61:F69) -> 0 | G60: =+SUM(G61:G69) -> 0 | H60: =+SUM(H61:H69) -> 0 | I60: =+SUM(I61:I69) -> 0 | J60: =+SUM(J61:J69) -> 0 | ... Q60: =+SUM(Q61:Q69) -> 0 | S60: =+SUM(S61:S69) -> 0 | T60: =+SUM(T61:T69) -> 0 | U60: =+SUM(U61:U69) -> 0 | V60: =+SUM(V61:V69) -> 0 | W60: =+SUM(W61:W69) -> 0 | X60: =+SUM(X61:X69) -> 0 | Y60: =+SUM(Y61:Y69) -> 0 | Z60: =+SUM(Z61:Z69) -> 0 | ... AG60: =+SUM(AG61:AG69) -> 0 | AI60: =+SUM(AI61:AI69) -> 0 | AJ60: =+SUM(AJ61:AJ69) -> 0
A61: Renta Mínima | C61: 0 | D61: 0 | E61: 0 | F61: 0 | G61: 0 | H61: 0 | I61: 0 | J61: 0 | K61: 0 | L61: 0 | M61: 0 | N61: 0 | O61: 0 | P61: 0 | Q61: 0 | S61: 0 | T61: 0 | U61: 0 | V61: 0 | W61: 0 | X61: 0 | Y61: 0 | Z61: 0 | AA61: 0 | AB61: 0 | AC61: 0 | AD61: 0 | AE61: 0 | AF61: 0 | AG61: 0 | AI61: =+SUM(C61:Q61) -> 0 | AJ61: =+SUM(S61:AG61) -> 0
A62: Renta Variable | C62: 0 | D62: 0 | E62: 0 | F62: 0 | G62: 0 | H62: 0 | I62: 0 | J62: 0 | K62: 0 | L62: 0 | M62: 0 | N62: 0 | O62: 0 | P62: 0 | Q62: 0 | S62: 0 | T62: 0 | U62: 0 | V62: 0 | W62: 0 | X62: 0 | Y62: 0 | Z62: 0 | AA62: 0 | AB62: 0 | AC62: 0 | AD62: 0 | AE62: 0 | AF62: 0 | AG62: 0 | AI62: =+SUM(C62:Q62) -> 0 | AJ62: =+SUM(S62:AG62) -> 0
A63: Cuota de Mantenimiento | C63: 0 | D63: 0 | E63: 0 | F63: 0 | G63: 0 | H63: 0 | I63: 0 | J63: 0 | K63: 0 | L63: 0 | M63: 0 | N63: 0 | O63: 0 | P63: 0 | Q63: 0 | S63: 0 | T63: 0 | U63: 0 | V63: 0 | W63: 0 | X63: 0 | Y63: 0 | Z63: 0 | AA63: 0 | AB63: 0 | AC63: 0 | AD63: 0 | AE63: 0 | AF63: 0 | AG63: 0 | AI63: =+SUM(C63:Q63) -> 0 | AJ63: =+SUM(S63:AG63) -> 0
A64: Publicidad | C64: 0 | D64: 0 | E64: 0 | F64: 0 | G64: 0 | H64: 0 | I64: 0 | J64: 0 | K64: 0 | L64: 0 | M64: 0 | N64: 0 | O64: 0 | P64: 0 | Q64: 0 | S64: 0 | T64: 0 | U64: 0 | V64: 0 | W64: 0 | X64: 0 | Y64: 0 | Z64: 0 | AA64: 0 | AB64: 0 | AC64: 0 | AD64: 0 | AE64: 0 | AF64: 0 | AG64: 0 | AI64: =+SUM(C64:Q64) -> 0 | AJ64: =+SUM(S64:AG64) -> 0
A65: Estacionamiento | C65: 0 | D65: 0 | E65: 0 | F65: 0 | G65: 0 | H65: 0 | I65: 0 | J65: 0 | K65: 0 | L65: 0 | M65: 0 | N65: 0 | O65: 0 | P65: 0 | Q65: 0 | S65: 0 | T65: 0 | U65: 0 | V65: 0 | W65: 0 | X65: 0 | Y65: 0 | Z65: 0 | AA65: 0 | AB65: 0 | AC65: 0 | AD65: 0 | AE65: 0 | AF65: 0 | AG65: 0 | AI65: =+SUM(C65:Q65) -> 0 | AJ65: =+SUM(S65:AG65) -> 0
A66: Cuotas Condominales | C66: 0 | D66: 0 | E66: 0 | F66: 0 | G66: 0 | H66: 0 | I66: 0 | J66: 0 | K66: 0 | L66: 0 | M66: 0 | N66: 0 | O66: 0 | P66: 0 | Q66: 0 | S66: 0 | T66: 0 | U66: 0 | V66: 0 | W66: 0 | X66: 0 | Y66: 0 | Z66: 0 | AA66: 0 | AB66: 0 | AC66: 0 | AD66: 0 | AE66: 0 | AF66: 0 | AG66: 0 | AI66: =+SUM(C66:Q66) -> 0 | AJ66: =+SUM(S66:AG66) -> 0
A67: Guantes | C67: 0 | D67: 0 | E67: 0 | F67: 0 | G67: 0 | H67: 0 | I67: 0 | J67: 0 | K67: 0 | L67: 0 | M67: 0 | N67: 0 | O67: 0 | P67: 0 | Q67: 0 | S67: 0 | T67: 0 | U67: 0 | V67: 0 | W67: 0 | X67: 0 | Y67: 0 | Z67: 0 | AA67: 0 | AB67: 0 | AC67: 0 | AD67: 0 | AE67: 0 | AF67: 0 | AG67: 0 | AI67: =+SUM(C67:Q67) -> 0 | AJ67: =+SUM(S67:AG67) -> 0
A68: Penalizaciones | C68: 0 | D68: 0 | E68: 0 | F68: 0 | G68: 0 | H68: 0 | I68: 0 | J68: 0 | K68: 0 | L68: 0 | M68: 0 | N68: 0 | O68: 0 | P68: 0 | Q68: 0 | S68: 0 | T68: 0 | U68: 0 | V68: 0 | W68: 0 | X68: 0 | Y68: 0 | Z68: 0 | AA68: 0 | AB68: 0 | AC68: 0 | AD68: 0 | AE68: 0 | AF68: 0 | AG68: 0 | AI68: =+SUM(C68:Q68) -> 0 | AJ68: =+SUM(S68:AG68) -> 0
A69: Otros Ingresos Operativos de Plazas | C69: 0 | D69: 0 | E69: 0 | F69: 0 | G69: 0 | H69: 0 | I69: 0 | J69: 0 | K69: 0 | L69: 0 | M69: 0 | N69: 0 | O69: 0 | P69: 0 | Q69: 0 | S69: 0 | T69: 0 | U69: 0 | V69: 0 | W69: 0 | X69: 0 | Y69: 0 | Z69: 0 | AA69: 0 | AB69: 0 | AC69: 0 | AD69: 0 | AE69: 0 | AF69: 0 | AG69: 0 | AI69: =+SUM(C69:Q69) -> 0 | AJ69: =+SUM(S69:AG69) -> 0
A70: Ingresos por Servicios: | C70: =+SUM(C71:C79) -> 0 | D70: =+SUM(D71:D79) -> 0 | E70: =+SUM(E71:E79) -> 0 | F70: =+SUM(F71:F79) -> 0 | G70: =+SUM(G71:G79) -> 0 | H70: =+SUM(H71:H79) -> 0 | I70: =+SUM(I71:I79) -> 0 | J70: =+SUM(J71:J79) -> 0 | ... Q70: =+SUM(Q71:Q79) -> 0 | S70: =+SUM(S71:S79) -> 0 | T70: =+SUM(T71:T79) -> 0 | U70: =+SUM(U71:U79) -> 0 | V70: =+SUM(V71:V79) -> 0 | W70: =+SUM(W71:W79) -> 0 | X70: =+SUM(X71:X79) -> 0 | Y70: =+SUM(Y71:Y79) -> 0 | Z70: =+SUM(Z71:Z79) -> 0 | ... AG70: =+SUM(AG71:AG79) -> 0 | AI70: =+SUM(AI71:AI79) -> 0 | AJ70: =+SUM(AJ71:AJ79) -> 0
A71: Administración de Nómina | C71: 0 | D71: 0 | E71: 0 | F71: 0 | G71: 0 | H71: 0 | I71: 0 | J71: 0 | K71: 0 | L71: 0 | M71: 0 | N71: 0 | O71: 0 | P71: 0 | Q71: 0 | S71: 0 | T71: 0 | U71: 0 | V71: 0 | W71: 0 | X71: 0 | Y71: 0 | Z71: 0 | AA71: 0 | AB71: 0 | AC71: 0 | AD71: 0 | AE71: 0 | AF71: 0 | AG71: 0 | AI71: =+SUM(R71:AF71) -> 0 | AJ71: =+SUM(S71:AG71) -> 0
A72: Apertura/Cierre de Contratos | C72: 0 | D72: 0 | E72: 0 | F72: 0 | G72: 0 | H72: 0 | I72: 0 | J72: 0 | K72: 0 | L72: 0 | M72: 0 | N72: 0 | O72: 0 | P72: 0 | Q72: 0 | S72: 0 | T72: 0 | U72: 0 | V72: 0 | W72: 0 | X72: 0 | Y72: 0 | Z72: 0 | AA72: 0 | AB72: 0 | AC72: 0 | AD72: 0 | AE72: 0 | AF72: 0 | AG72: 0 | AI72: =+SUM(R72:AF72) -> 0 | AJ72: =+SUM(S72:AG72) -> 0
A73: Renovación de Contratos | C73: 0 | D73: 0 | E73: 0 | F73: 0 | G73: 0 | H73: 0 | I73: 0 | J73: 0 | K73: 0 | L73: 0 | M73: 0 | N73: 0 | O73: 0 | P73: 0 | Q73: 0 | S73: 0 | T73: 0 | U73: 0 | V73: 0 | W73: 0 | X73: 0 | Y73: 0 | Z73: 0 | AA73: 0 | AB73: 0 | AC73: 0 | AD73: 0 | AE73: 0 | AF73: 0 | AG73: 0 | AI73: =+SUM(R73:AF73) -> 0 | AJ73: =+SUM(S73:AG73) -> 0
A74: Administración de Obra | C74: 0 | D74: 0 | E74: 0 | F74: 0 | G74: 0 | H74: 0 | I74: 0 | J74: 0 | K74: 0 | L74: 0 | M74: 0 | N74: 0 | O74: 0 | P74: 0 | Q74: 0 | S74: 0 | T74: 0 | U74: 0 | V74: 0 | W74: 0 | X74: 0 | Y74: 0 | Z74: 0 | AA74: 0 | AB74: 0 | AC74: 0 | AD74: 0 | AE74: 0 | AF74: 0 | AG74: 0 | AI74: =+SUM(R74:AF74) -> 0 | AJ74: =+SUM(S74:AG74) -> 0
A75: Administración de Plaza | C75: 0 | D75: 0 | E75: 0 | F75: 0 | G75: 0 | H75: 0 | I75: 0 | J75: 0 | K75: 0 | L75: 0 | M75: 0 | N75: 0 | O75: 0 | P75: 0 | Q75: 0 | S75: 0 | T75: 0 | U75: 0 | V75: 0 | W75: 0 | X75: 0 | Y75: 0 | Z75: 0 | AA75: 0 | AB75: 0 | AC75: 0 | AD75: 0 | AE75: 0 | AF75: 0 | AG75: 0 | AI75: =+SUM(R75:AF75) -> 0 | AJ75: =+SUM(S75:AG75) -> 0
A76: Consultoría | C76: 0 | D76: 0 | E76: 0 | F76: 0 | G76: 0 | H76: 0 | I76: 0 | J76: 0 | K76: 0 | L76: 0 | M76: 0 | N76: 0 | O76: 0 | P76: 0 | Q76: 0 | S76: 0 | T76: 0 | U76: 0 | V76: 0 | W76: 0 | X76: 0 | Y76: 0 | Z76: 0 | AA76: 0 | AB76: 0 | AC76: 0 | AD76: 0 | AE76: 0 | AF76: 0 | AG76: 0 | AI76: =+SUM(R76:AF76) -> 0 | AJ76: =+SUM(S76:AG76) -> 0
A77: Renta de Terrenos | C77: 0 | D77: 0 | E77: 0 | F77: 0 | G77: 0 | H77: 0 | I77: 0 | J77: 0 | K77: 0 | L77: 0 | M77: 0 | N77: 0 | O77: 0 | P77: 0 | Q77: 0 | S77: 0 | T77: 0 | U77: 0 | V77: 0 | W77: 0 | X77: 0 | Y77: 0 | Z77: 0 | AA77: 0 | AB77: 0 | AC77: 0 | AD77: 0 | AE77: 0 | AF77: 0 | AG77: 0 | AI77: =+SUM(R77:AF77) -> 0 | AJ77: =+SUM(S77:AG77) -> 0
A78: Operación de Hotel | C78: 0 | D78: 0 | E78: 0 | F78: 0 | G78: 0 | H78: 0 | I78: 0 | J78: 0 | K78: 0 | L78: 0 | M78: 0 | N78: 0 | O78: 0 | P78: 0 | Q78: 0 | S78: 0 | T78: 0 | U78: 0 | V78: 0 | W78: 0 | X78: 0 | Y78: 0 | Z78: 0 | AA78: 0 | AB78: 0 | AC78: 0 | AD78: 0 | AE78: 0 | AF78: 0 | AG78: 0 | AI78: =+SUM(R78:AF78) -> 0 | AJ78: =+SUM(S78:AG78) -> 0
A79: Otros Servicios | C79: 0 | D79: 0 | E79: 0 | F79: 0 | G79: 0 | H79: 0 | I79: 0 | J79: 0 | K79: 0 | L79: 0 | M79: 0 | N79: 0 | O79: 0 | P79: 0 | Q79: 0 | S79: 0 | T79: 0 | U79: 0 | V79: 0 | W79: 0 | X79: 0 | Y79: 0 | Z79: 0 | AA79: 0 | AB79: 0 | AC79: 0 | AD79: 0 | AE79: 0 | AF79: 0 | AG79: 0 | AI79: =+SUM(R79:AF79) -> 0 | AJ79: =+SUM(S79:AG79) -> 0
A81: Total Devoluciones sobre Ventas | C81: =+C60+C70 -> 0 | D81: =+D60+D70 -> 0 | E81: =+E60+E70 -> 0 | F81: =+F60+F70 -> 0 | G81: =+G60+G70 -> 0 | H81: =+H60+H70 -> 0 | I81: =+I60+I70 -> 0 | J81: =+J60+J70 -> 0 | ... Q81: =+Q60+Q70 -> 0 | S81: =+S60+S70 -> 0 | T81: =+T60+T70 -> 0 | U81: =+U60+U70 -> 0 | V81: =+V60+V70 -> 0 | W81: =+W60+W70 -> 0 | X81: =+X60+X70 -> 0 | Y81: =+Y60+Y70 -> 0 | Z81: =+Z60+Z70 -> 0 | ... AG81: =+AG60+AG70 -> 0 | AI81: =+AI60+AI70 -> 0 | AJ81: =+AJ60+AJ70 -> 0
A83: INGRESOS NETOS
A85: Ingresos por Operación de Plazas: | C85: =+SUM(C86:C94) -> 17030565 | D85: =+SUM(D86:D94) -> 10366156 | E85: =+SUM(E86:E94) -> 10888271 | F85: =+SUM(F86:F94) -> 878182.57 | G85: =+SUM(G86:G94) -> 0 | H85: =+SUM(H86:H94) -> 5799095.6 | I85: =+SUM(I86:I94) -> 1107544.9 | J85: =+SUM(J86:J94) -> 0 | ... Q85: =+SUM(Q86:Q94) -> 2316478.4 | S85: =+SUM(S86:S94) -> 96097240 | T85: =+SUM(T86:T94) -> 57983340 | U85: =+SUM(U86:U94) -> 63888277 | V85: =+SUM(V86:V94) -> 5158569.2 | W85: =+SUM(W86:W94) -> 0 | X85: =+SUM(X86:X94) -> 33331550 | Y85: =+SUM(Y86:Y94) -> 6041278.8 | Z85: =+SUM(Z86:Z94) -> 0 | ... AG85: =+SUM(AG86:AG94) -> 14408583 | AI85: =+SUM(AI86:AI94) -> 82298852 | AJ85: =+SUM(AJ86:AJ94) -> 4.7496545e+08
A86: Renta Mínima | C86: =+C11-C36-C61 -> 10447173 | D86: =+D11-D36-D61 -> 6660185 | E86: =+E11-E36-E61 -> 8048538.4 | F86: =+F11-F36-F61 -> 753371.17 | G86: =+G11-G36-G61 -> 0 | H86: =+H11-H36-H61 -> 4515304.4 | I86: =+I11-I36-I61 -> 888433.2 | J86: =+J11-J36-J61 -> 0 | ... Q86: =+Q11-Q36-Q61 -> 1670117.6 | S86: =+S11-S36-S61 -> 60754716 | T86: =+T11-T36-T61 -> 38997584 | U86: =+U11-U36-U61 -> 47740380 | V86: =+V11-V36-V61 -> 4460732.8 | W86: =+W11-W36-W61 -> 0 | X86: =+X11-X36-X61 -> 25858736 | Y86: =+Y11-Y36-Y61 -> 5227015.1 | Z86: =+Z11-Z36-Z61 -> 0 | ... AG86: =+AG11-AG36-AG61 -> 9969443.3 | AI86: =+AI11-AI36-AI61 -> 55047532 | AJ86: =+AJ11-AJ36-AJ61 -> 3.2122474e+08
A87: Renta Variable | C87: =+C12-C37-C62 -> 1632424.5 | D87: =+D12-D37-D62 -> 930917.75 | E87: =+E12-E37-E62 -> 431731.42 | F87: =+F12-F37-F62 -> 36095.693 | G87: =+G12-G37-G62 -> 0 | H87: =+H12-H37-H62 -> 50275.906 | I87: =+I12-I37-I62 -> 116061.26 | J87: =+J12-J37-J62 -> 0 | ... Q87: =+Q12-Q37-Q62 -> 375410.27 | S87: =+S12-S37-S62 -> 6891213.6 | T87: =+T12-T37-T62 -> 2947253.3 | U87: =+U12-U37-U62 -> 2750351.5 | V87: =+V12-V37-V62 -> 177440.95 | W87: =+W12-W37-W62 -> 0 | X87: =+X12-X37-X62 -> 566607.55 | Y87: =+Y12-Y37-Y62 -> 216084.25 | Z87: =+Z12-Z37-Z62 -> 0 | ... AG87: =+AG12-AG37-AG62 -> 2776823.8 | AI87: =+AI12-AI37-AI62 -> 8282128.9 | AJ87: =+AJ12-AJ37-AJ62 -> 44532608
A88: Cuota de Mantenimiento | C88: =+C13-C38-C63 -> 1380058.4 | D88: =+D13-D38-D63 -> 934548.12 | E88: =+E13-E38-E63 -> 1093709.1 | F88: =+F13-F38-F63 -> 86270.547 | G88: =+G13-G38-G63 -> 0 | H88: =+H13-H38-H63 -> 602917.35 | I88: =+I13-I38-I63 -> 103050.48 | J88: =+J13-J38-J63 -> 0 | ... Q88: =+Q13-Q38-Q63 -> 270950.55 | S88: =+S13-S38-S63 -> 8033909 | T88: =+T13-T38-T63 -> 5456779.4 | U88: =+U13-U38-U63 -> 6482638.7 | V88: =+V13-V38-V63 -> 505724.45 | W88: =+W13-W38-W63 -> 0 | X88: =+X13-X38-X63 -> 3581970.9 | Y88: =+Y13-Y38-Y63 -> 598179.49 | Z88: =+Z13-Z38-Z63 -> 0 | ... AG88: =+AG13-AG38-AG63 -> 1662316.2 | AI88: =+AI13-AI38-AI63 -> 7773932.2 | AJ88: =+AJ13-AJ38-AJ63 -> 45617430
A89: Publicidad | C89: =+C14-C39-C64 -> 21434.397 | D89: =+D14-D39-D64 -> 0 | E89: =+E14-E39-E64 -> 13043.385 | F89: =+F14-F39-F64 -> 2445.1647 | G89: =+G14-G39-G64 -> 0 | H89: =+H14-H39-H64 -> 2891.423 | I89: =+I14-I39-I64 -> 0 | J89: =+J14-J39-J64 -> 0 | ... Q89: =+Q14-Q39-Q64 -> 0 | S89: =+S14-S39-S64 -> 128606.38 | T89: =+T14-T39-T64 -> 0 | U89: =+U14-U39-U64 -> 78260.307 | V89: =+V14-V39-V64 -> 14670.988 | W89: =+W14-W39-W64 -> 0 | X89: =+X14-X39-X64 -> 17348.538 | Y89: =+Y14-Y39-Y64 -> 0 | Z89: =+Z14-Z39-Z64 -> 0 | ... AG89: =+AG14-AG39-AG64 -> 0 | AI89: =+AI14-AI39-AI64 -> 40336.055 | AJ89: =+AJ14-AJ39-AJ64 -> 242016.33
A90: Estacionamiento | C90: =+C15-C40-C65 -> 3511434.6 | D90: =+D15-D40-D65 -> 1826234.9 | E90: =+E15-E40-E65 -> 1285428.9 | F90: =+F15-F40-F65 -> 0 | G90: =+G15-G40-G65 -> 0 | H90: =+H15-H40-H65 -> 624489.6 | I90: =+I15-I40-I65 -> 0 | J90: =+J15-J40-J65 -> 0 | ... Q90: =+Q15-Q40-Q65 -> 0 | S90: =+S15-S40-S65 -> 20041883 | T90: =+T15-T40-T65 -> 10496100 | U90: =+U15-U40-U65 -> 6741727.1 | V90: =+V15-V40-V65 -> 0 | W90: =+W15-W40-W65 -> 0 | X90: =+X15-X40-X65 -> 3287585.2 | Y90: =+Y15-Y40-Y65 -> 0 | Z90: =+Z15-Z40-Z65 -> 0 | ... AG90: =+AG15-AG40-AG65 -> 0 | AI90: =+AI15-AI40-AI65 -> 10588316 | AJ90: =+AJ15-AJ40-AJ65 -> 59740223
A91: Cuotas Condominales | C91: =+C16-C41-C66 -> 0 | D91: =+D16-D41-D66 -> 0 | E91: =+E16-E41-E66 -> 0 | F91: =+F16-F41-F66 -> 0 | G91: =+G16-G41-G66 -> 0 | H91: =+H16-H41-H66 -> 0 | I91: =+I16-I41-I66 -> 0 | J91: =+J16-J41-J66 -> 0 | ... Q91: =+Q16-Q41-Q66 -> 0 | S91: =+S16-S41-S66 -> 0 | T91: =+T16-T41-T66 -> 0 | U91: =+U16-U41-U66 -> 0 | V91: =+V16-V41-V66 -> 0 | W91: =+W16-W41-W66 -> 0 | X91: =+X16-X41-X66 -> 0 | Y91: =+Y16-Y41-Y66 -> 0 | Z91: =+Z16-Z41-Z66 -> 0 | ... AG91: =+AG16-AG41-AG66 -> 0 | AI91: =+AI16-AI41-AI66 -> 279491.69 | AJ91: =+AJ16-AJ41-AJ66 -> 1631478.7
A92: Guantes | C92: =+C17-C42-C67 -> 38040.223 | D92: =+D17-D42-D67 -> 14270.551 | E92: =+E17-E42-E67 -> 15819.824 | F92: =+F17-F42-F67 -> 0 | G92: =+G17-G42-G67 -> 0 | H92: =+H17-H42-H67 -> 3216.9621 | I92: =+I17-I42-I67 -> 0 | J92: =+J17-J42-J67 -> 0 | ... Q92: =+Q17-Q42-Q67 -> 0 | S92: =+S17-S42-S67 -> 246912.44 | T92: =+T17-T42-T67 -> 85623.306 | U92: =+U17-U42-U67 -> 94918.943 | V92: =+V17-V42-V67 -> 0 | W92: =+W17-W42-W67 -> 0 | X92: =+X17-X42-X67 -> 19301.773 | Y92: =+Y17-Y42-Y67 -> 0 | Z92: =+Z17-Z42-Z67 -> 0 | ... AG92: =+AG17-AG42-AG67 -> 0 | AI92: =+AI17-AI42-AI67 -> 237615.87 | AJ92: =+AJ17-AJ42-AJ67 -> 1444366.3
A93: Penalizaciones | C93: =+C18-C43-C68 -> 0 | D93: =+D18-D43-D68 -> 0 | E93: =+E18-E43-E68 -> 0 | F93: =+F18-F43-F68 -> 0 | G93: =+G18-G43-G68 -> 0 | H93: =+H18-H43-H68 -> 0 | I93: =+I18-I43-I68 -> 0 | J93: =+J18-J43-J68 -> 0 | ... Q93: =+Q18-Q43-Q68 -> 0 | S93: =+S18-S43-S68 -> 0 | T93: =+T18-T43-T68 -> 0 | U93: =+U18-U43-U68 -> 0 | V93: =+V18-V43-V68 -> 0 | W93: =+W18-W43-W68 -> 0 | X93: =+X18-X43-X68 -> 0 | Y93: =+Y18-Y43-Y68 -> 0 | Z93: =+Z18-Z43-Z68 -> 0 | ... AG93: =+AG18-AG43-AG68 -> 0 | AI93: =+AI18-AI43-AI68 -> 0 | AJ93: =+AJ18-AJ43-AJ68 -> 0
A94: Otros Ingresos Operativos de Plazas | C94: =+C19-C44-C69 -> 0 | D94: =+D19-D44-D69 -> 0 | E94: =+E19-E44-E69 -> 0 | F94: =+F19-F44-F69 -> 0 | G94: =+G19-G44-G69 -> 0 | H94: =+H19-H44-H69 -> 0 | I94: =+I19-I44-I69 -> 0 | J94: =+J19-J44-J69 -> 0 | ... Q94: =+Q19-Q44-Q69 -> 0 | S94: =+S19-S44-S69 -> 0 | T94: =+T19-T44-T69 -> 0 | U94: =+U19-U44-U69 -> 0 | V94: =+V19-V44-V69 -> 0 | W94: =+W19-W44-W69 -> 0 | X94: =+X19-X44-X69 -> 0 | Y94: =+Y19-Y44-Y69 -> 0 | Z94: =+Z19-Z44-Z69 -> 0 | ... AG94: =+AG19-AG44-AG69 -> 0 | AI94: =+AI19-AI44-AI69 -> 49500 | AJ94: =+AJ19-AJ44-AJ69 -> 532588
A95: Ingresos por Servicios: | C95: =+SUM(C96:C104) -> 0 | D95: =+SUM(D96:D104) -> 0 | E95: =+SUM(E96:E104) -> 0 | F95: =+SUM(F96:F104) -> 0 | G95: =+SUM(G96:G104) -> 0 | H95: =+SUM(H96:H104) -> 0 | I95: =+SUM(I96:I104) -> 0 | J95: =+SUM(J96:J104) -> 0 | ... Q95: =+SUM(Q96:Q104) -> 0 | S95: =+SUM(S96:S104) -> 0 | T95: =+SUM(T96:T104) -> 0 | U95: =+SUM(U96:U104) -> 0 | V95: =+SUM(V96:V104) -> 0 | W95: =+SUM(W96:W104) -> 0 | X95: =+SUM(X96:X104) -> 0 | Y95: =+SUM(Y96:Y104) -> 0 | Z95: =+SUM(Z96:Z104) -> 0 | ... AG95: =+SUM(AG96:AG104) -> 0 | AI95: =+SUM(AI96:AI104) -> 0 | AJ95: =+SUM(AJ96:AJ104) -> 0
A96: Administración de Nómina | C96: =+C21-C46-C71 -> 0 | D96: =+D21-D46-D71 -> 0 | E96: =+E21-E46-E71 -> 0 | F96: =+F21-F46-F71 -> 0 | G96: =+G21-G46-G71 -> 0 | H96: =+H21-H46-H71 -> 0 | I96: =+I21-I46-I71 -> 0 | J96: =+J21-J46-J71 -> 0 | ... Q96: =+Q21-Q46-Q71 -> 0 | S96: =+S21-S46-S71 -> 0 | T96: =+T21-T46-T71 -> 0 | U96: =+U21-U46-U71 -> 0 | V96: =+V21-V46-V71 -> 0 | W96: =+W21-W46-W71 -> 0 | X96: =+X21-X46-X71 -> 0 | Y96: =+Y21-Y46-Y71 -> 0 | Z96: =+Z21-Z46-Z71 -> 0 | ... AG96: =+AG21-AG46-AG71 -> 0 | AI96: =+AI21-AI46-AI71 -> 0 | AJ96: =+AJ21-AJ46-AJ71 -> 0
A97: Apertura/Cierre de Contratos | C97: =+C22-C47-C72 -> 0 | D97: =+D22-D47-D72 -> 0 | E97: =+E22-E47-E72 -> 0 | F97: =+F22-F47-F72 -> 0 | G97: =+G22-G47-G72 -> 0 | H97: =+H22-H47-H72 -> 0 | I97: =+I22-I47-I72 -> 0 | J97: =+J22-J47-J72 -> 0 | ... Q97: =+Q22-Q47-Q72 -> 0 | S97: =+S22-S47-S72 -> 0 | T97: =+T22-T47-T72 -> 0 | U97: =+U22-U47-U72 -> 0 | V97: =+V22-V47-V72 -> 0 | W97: =+W22-W47-W72 -> 0 | X97: =+X22-X47-X72 -> 0 | Y97: =+Y22-Y47-Y72 -> 0 | Z97: =+Z22-Z47-Z72 -> 0 | ... AG97: =+AG22-AG47-AG72 -> 0 | AI97: =+AI22-AI47-AI72 -> 0 | AJ97: =+AJ22-AJ47-AJ72 -> 0
A98: Renovación de Contratos | C98: =+C23-C48-C73 -> 0 | D98: =+D23-D48-D73 -> 0 | E98: =+E23-E48-E73 -> 0 | F98: =+F23-F48-F73 -> 0 | G98: =+G23-G48-G73 -> 0 | H98: =+H23-H48-H73 -> 0 | I98: =+I23-I48-I73 -> 0 | J98: =+J23-J48-J73 -> 0 | ... Q98: =+Q23-Q48-Q73 -> 0 | S98: =+S23-S48-S73 -> 0 | T98: =+T23-T48-T73 -> 0 | U98: =+U23-U48-U73 -> 0 | V98: =+V23-V48-V73 -> 0 | W98: =+W23-W48-W73 -> 0 | X98: =+X23-X48-X73 -> 0 | Y98: =+Y23-Y48-Y73 -> 0 | Z98: =+Z23-Z48-Z73 -> 0 | ... AG98: =+AG23-AG48-AG73 -> 0 | AI98: =+AI23-AI48-AI73 -> 0 | AJ98: =+AJ23-AJ48-AJ73 -> 0
A99: Administración de Obra | C99: =+C24-C49-C74 -> 0 | D99: =+D24-D49-D74 -> 0 | E99: =+E24-E49-E74 -> 0 | F99: =+F24-F49-F74 -> 0 | G99: =+G24-G49-G74 -> 0 | H99: =+H24-H49-H74 -> 0 | I99: =+I24-I49-I74 -> 0 | J99: =+J24-J49-J74 -> 0 | ... Q99: =+Q24-Q49-Q74 -> 0 | S99: =+S24-S49-S74 -> 0 | T99: =+T24-T49-T74 -> 0 | U99: =+U24-U49-U74 -> 0 | V99: =+V24-V49-V74 -> 0 | W99: =+W24-W49-W74 -> 0 | X99: =+X24-X49-X74 -> 0 | Y99: =+Y24-Y49-Y74 -> 0 | Z99: =+Z24-Z49-Z74 -> 0 | ... AG99: =+AG24-AG49-AG74 -> 0 | AI99: =+AI24-AI49-AI74 -> 0 | AJ99: =+AJ24-AJ49-AJ74 -> 0
A100: Administración de Plaza | C100: =+C25-C50-C75 -> 0 | D100: =+D25-D50-D75 -> 0 | E100: =+E25-E50-E75 -> 0 | F100: =+F25-F50-F75 -> 0 | G100: =+G25-G50-G75 -> 0 | H100: =+H25-H50-H75 -> 0 | I100: =+I25-I50-I75 -> 0 | J100: =+J25-J50-J75 -> 0 | ... Q100: =+Q25-Q50-Q75 -> 0 | S100: =+S25-S50-S75 -> 0 | T100: =+T25-T50-T75 -> 0 | U100: =+U25-U50-U75 -> 0 | V100: =+V25-V50-V75 -> 0 | W100: =+W25-W50-W75 -> 0 | X100: =+X25-X50-X75 -> 0 | Y100: =+Y25-Y50-Y75 -> 0 | Z100: =+Z25-Z50-Z75 -> 0 | ... AG100: =+AG25-AG50-AG75 -> 0 | AI100: =+AI25-AI50-AI75 -> 0 | AJ100: =+AJ25-AJ50-AJ75 -> 0
A101: Consultoría | C101: =+C26-C51-C76 -> 0 | D101: =+D26-D51-D76 -> 0 | E101: =+E26-E51-E76 -> 0 | F101: =+F26-F51-F76 -> 0 | G101: =+G26-G51-G76 -> 0 | H101: =+H26-H51-H76 -> 0 | I101: =+I26-I51-I76 -> 0 | J101: =+J26-J51-J76 -> 0 | ... Q101: =+Q26-Q51-Q76 -> 0 | S101: =+S26-S51-S76 -> 0 | T101: =+T26-T51-T76 -> 0 | U101: =+U26-U51-U76 -> 0 | V101: =+V26-V51-V76 -> 0 | W101: =+W26-W51-W76 -> 0 | X101: =+X26-X51-X76 -> 0 | Y101: =+Y26-Y51-Y76 -> 0 | Z101: =+Z26-Z51-Z76 -> 0 | ... AG101: =+AG26-AG51-AG76 -> 0 | AI101: =+AI26-AI51-AI76 -> 0 | AJ101: =+AJ26-AJ51-AJ76 -> 0
A102: Renta de Terrenos | C102: =+C27-C52-C77 -> 0 | D102: =+D27-D52-D77 -> 0 | E102: =+E27-E52-E77 -> 0 | F102: =+F27-F52-F77 -> 0 | G102: =+G27-G52-G77 -> 0 | H102: =+H27-H52-H77 -> 0 | I102: =+I27-I52-I77 -> 0 | J102: =+J27-J52-J77 -> 0 | ... Q102: =+Q27-Q52-Q77 -> 0 | S102: =+S27-S52-S77 -> 0 | T102: =+T27-T52-T77 -> 0 | U102: =+U27-U52-U77 -> 0 | V102: =+V27-V52-V77 -> 0 | W102: =+W27-W52-W77 -> 0 | X102: =+X27-X52-X77 -> 0 | Y102: =+Y27-Y52-Y77 -> 0 | Z102: =+Z27-Z52-Z77 -> 0 | ... AG102: =+AG27-AG52-AG77 -> 0 | AI102: =+AI27-AI52-AI77 -> 0 | AJ102: =+AJ27-AJ52-AJ77 -> 0
A103: Operación de Hotel | C103: =+C28-C53-C78 -> 0 | D103: =+D28-D53-D78 -> 0 | E103: =+E28-E53-E78 -> 0 | F103: =+F28-F53-F78 -> 0 | G103: =+G28-G53-G78 -> 0 | H103: =+H28-H53-H78 -> 0 | I103: =+I28-I53-I78 -> 0 | J103: =+J28-J53-J78 -> 0 | ... Q103: =+Q28-Q53-Q78 -> 0 | S103: =+S28-S53-S78 -> 0 | T103: =+T28-T53-T78 -> 0 | U103: =+U28-U53-U78 -> 0 | V103: =+V28-V53-V78 -> 0 | W103: =+W28-W53-W78 -> 0 | X103: =+X28-X53-X78 -> 0 | Y103: =+Y28-Y53-Y78 -> 0 | Z103: =+Z28-Z53-Z78 -> 0 | ... AG103: =+AG28-AG53-AG78 -> 0 | AI103: =+AI28-AI53-AI78 -> 0 | AJ103: =+AJ28-AJ53-AJ78 -> 0
A104: Otros Servicios | C104: =+C29-C54-C79 -> 0 | D104: =+D29-D54-D79 -> 0 | E104: =+E29-E54-E79 -> 0 | F104: =+F29-F54-F79 -> 0 | G104: =+G29-G54-G79 -> 0 | H104: =+H29-H54-H79 -> 0 | I104: =+I29-I54-I79 -> 0 | J104: =+J29-J54-J79 -> 0 | ... Q104: =+Q29-Q54-Q79 -> 0 | S104: =+S29-S54-S79 -> 0 | T104: =+T29-T54-T79 -> 0 | U104: =+U29-U54-U79 -> 0 | V104: =+V29-V54-V79 -> 0 | W104: =+W29-W54-W79 -> 0 | X104: =+X29-X54-X79 -> 0 | Y104: =+Y29-Y54-Y79 -> 0 | Z104: =+Z29-Z54-Z79 -> 0 | ... AG104: =+AG29-AG54-AG79 -> 0 | AI104: =+AI29-AI54-AI79 -> 0 | AJ104: =+AJ29-AJ54-AJ79 -> 0
A106: Total Ingresos Netos | C106: =+C85+C95 -> 17030565 | D106: =+D85+D95 -> 10366156 | E106: =+E85+E95 -> 10888271 | F106: =+F85+F95 -> 878182.57 | G106: =+G85+G95 -> 0 | H106: =+H85+H95 -> 5799095.6 | I106: =+I85+I95 -> 1107544.9 | J106: =+J85+J95 -> 0 | ... Q106: =+Q85+Q95 -> 2316478.4 | S106: =+S85+S95 -> 96097240 | T106: =+T85+T95 -> 57983340 | U106: =+U85+U95 -> 63888277 | V106: =+V85+V95 -> 5158569.2 | W106: =+W85+W95 -> 0 | X106: =+X85+X95 -> 33331550 | Y106: =+Y85+Y95 -> 6041278.8 | Z106: =+Z85+Z95 -> 0 | ... AG106: =+AG85+AG95 -> 14408583 | AI106: =+AI85+AI95 -> 82298852 | AJ106: =+AJ85+AJ95 -> 4.7496545e+08
A108: COSTO DE INGRESOS
A110: Ingresos por Operación de Plazas: | C110: =+SUM(C111:C119) -> 0 | D110: =+SUM(D111:D119) -> 0 | E110: =+SUM(E111:E119) -> 0 | F110: =+SUM(F111:F119) -> 0 | G110: =+SUM(G111:G119) -> 0 | H110: =+SUM(H111:H119) -> 0 | I110: =+SUM(I111:I119) -> 0 | J110: =+SUM(J111:J119) -> 0 | ... Q110: =+SUM(Q111:Q119) -> 0 | S110: =+SUM(S111:S119) -> 0 | T110: =+SUM(T111:T119) -> 0 | U110: =+SUM(U111:U119) -> 0 | V110: =+SUM(V111:V119) -> 0 | W110: =+SUM(W111:W119) -> 0 | X110: =+SUM(X111:X119) -> 0 | Y110: =+SUM(Y111:Y119) -> 0 | Z110: =+SUM(Z111:Z119) -> 0 | ... AG110: =+SUM(AG111:AG119) -> 0 | AI110: =+SUM(AI111:AI119) -> 0 | AJ110: =+SUM(AJ111:AJ119) -> 0
A111: Renta Mínima | C111: 0 | D111: 0 | E111: 0 | F111: 0 | G111: 0 | H111: 0 | I111: 0 | J111: 0 | K111: 0 | L111: 0 | M111: 0 | N111: 0 | O111: 0 | P111: 0 | Q111: 0 | S111: 0 | T111: 0 | U111: 0 | V111: 0 | W111: 0 | X111: 0 | Y111: 0 | Z111: 0 | AA111: 0 | AB111: 0 | AC111: 0 | AD111: 0 | AE111: 0 | AF111: 0 | AG111: 0 | AI111: =+SUM(R111:AF111) -> 0 | AJ111: =+SUM(S111:AG111) -> 0
A112: Renta Variable | C112: 0 | D112: 0 | E112: 0 | F112: 0 | G112: 0 | H112: 0 | I112: 0 | J112: 0 | K112: 0 | L112: 0 | M112: 0 | N112: 0 | O112: 0 | P112: 0 | Q112: 0 | S112: 0 | T112: 0 | U112: 0 | V112: 0 | W112: 0 | X112: 0 | Y112: 0 | Z112: 0 | AA112: 0 | AB112: 0 | AC112: 0 | AD112: 0 | AE112: 0 | AF112: 0 | AG112: 0 | AI112: =+SUM(R112:AF112) -> 0 | AJ112: =+SUM(S112:AG112) -> 0
A113: Cuota de Mantenimiento | C113: 0 | D113: 0 | E113: 0 | F113: 0 | G113: 0 | H113: 0 | I113: 0 | J113: 0 | K113: 0 | L113: 0 | M113: 0 | N113: 0 | O113: 0 | P113: 0 | Q113: 0 | S113: 0 | T113: 0 | U113: 0 | V113: 0 | W113: 0 | X113: 0 | Y113: 0 | Z113: 0 | AA113: 0 | AB113: 0 | AC113: 0 | AD113: 0 | AE113: 0 | AF113: 0 | AG113: 0 | AI113: =+SUM(R113:AF113) -> 0 | AJ113: =+SUM(S113:AG113) -> 0
A114: Publicidad | C114: 0 | D114: 0 | E114: 0 | F114: 0 | G114: 0 | H114: 0 | I114: 0 | J114: 0 | K114: 0 | L114: 0 | M114: 0 | N114: 0 | O114: 0 | P114: 0 | Q114: 0 | S114: 0 | T114: 0 | U114: 0 | V114: 0 | W114: 0 | X114: 0 | Y114: 0 | Z114: 0 | AA114: 0 | AB114: 0 | AC114: 0 | AD114: 0 | AE114: 0 | AF114: 0 | AG114: 0 | AI114: =+SUM(R114:AF114) -> 0 | AJ114: =+SUM(S114:AG114) -> 0
A115: Estacionamiento | C115: 0 | D115: 0 | E115: 0 | F115: 0 | G115: 0 | H115: 0 | I115: 0 | J115: 0 | K115: 0 | L115: 0 | M115: 0 | N115: 0 | O115: 0 | P115: 0 | Q115: 0 | S115: 0 | T115: 0 | U115: 0 | V115: 0 | W115: 0 | X115: 0 | Y115: 0 | Z115: 0 | AA115: 0 | AB115: 0 | AC115: 0 | AD115: 0 | AE115: 0 | AF115: 0 | AG115: 0 | AI115: =+SUM(R115:AF115) -> 0 | AJ115: =+SUM(S115:AG115) -> 0
A116: Cuotas Condominales | C116: 0 | D116: 0 | E116: 0 | F116: 0 | G116: 0 | H116: 0 | I116: 0 | J116: 0 | K116: 0 | L116: 0 | M116: 0 | N116: 0 | O116: 0 | P116: 0 | Q116: 0 | S116: 0 | T116: 0 | U116: 0 | V116: 0 | W116: 0 | X116: 0 | Y116: 0 | Z116: 0 | AA116: 0 | AB116: 0 | AC116: 0 | AD116: 0 | AE116: 0 | AF116: 0 | AG116: 0 | AI116: =+SUM(R116:AF116) -> 0 | AJ116: =+SUM(S116:AG116) -> 0
A117: Guantes | C117: 0 | D117: 0 | E117: 0 | F117: 0 | G117: 0 | H117: 0 | I117: 0 | J117: 0 | K117: 0 | L117: 0 | M117: 0 | N117: 0 | O117: 0 | P117: 0 | Q117: 0 | S117: 0 | T117: 0 | U117: 0 | V117: 0 | W117: 0 | X117: 0 | Y117: 0 | Z117: 0 | AA117: 0 | AB117: 0 | AC117: 0 | AD117: 0 | AE117: 0 | AF117: 0 | AG117: 0 | AI117: =+SUM(R117:AF117) -> 0 | AJ117: =+SUM(S117:AG117) -> 0
...

Sheet 2025R
C2: MENSUAL | S2: ACUMULADO
A5: ESTADO DE RESULTADOS | C5: P2K | D5: PSP | E5: PRG | F5: PC | G5: PLA | H5: PSI | I5: PPA | J5: PPB | K5: CBA | L5: TORR | M5: HOT | N5: PV | O5: DEPTOS | P5: PLP | Q5: PE | S5: P2K | T5: PSP | U5: PRG | V5: PC | W5: PLA | X5: PSI | Y5: PPA | Z5: PPB | AA5: CBA | AB5: TORR | AC5: HOT | AD5: PV | AE5: DEPTOS | AF5: PLP | AG5: PE | AI5: TOTAL | AJ5: TOTAL
A6: 2025R | AI6: MENSUAL | AJ6: ACUMULADO
A8: INGRESOS BRUTOS
A10: Ingresos por Operación de Plazas: | C10: =+SUM(C11:C19) -> 15568235 | D10: =+SUM(D11:D19) -> 9232008.4 | E10: =+SUM(E11:E19) -> 11497740 | F10: =+SUM(F11:F19) -> 620657.56 | G10: =+SUM(G11:G19) -> 0 | H10: =+SUM(H11:H19) -> 5217715.4 | I10: =+SUM(I11:I19) -> 1041623.9 | J10: =+SUM(J11:J19) -> 0 | ... Q10: =+SUM(Q11:Q19) -> 2204930.6 | S10: =+SUM(S11:S19) -> 88848494 | T10: =+SUM(T11:T19) -> 51757584 | U10: =+SUM(U11:U19) -> 59889617 | V10: =+SUM(V11:V19) -> 3718216.2 | W10: =+SUM(W11:W19) -> 0 | X10: =+SUM(X11:X19) -> 32212173 | Y10: =+SUM(Y11:Y19) -> 5764997 | Z10: =+SUM(Z11:Z19) -> 0 | ... AG10: =+SUM(AG11:AG19) -> 13896058 | AI10: =+SUM(AI11:AI19) -> 75483465 | AJ10: =+SUM(AJ11:AJ19) -> 4.3424599e+08
A11: Renta Mínima | C11: 9725317.1 | D11: 5911252.9 | E11: 7855681.9 | F11: 521439.74 | G11: 0 | H11: 4090217 | I11: 831282.44 | J11: 0 | K11: 6387130.4 | L11: 7288212.9 | M11: 160883.06 | N11: 4340171.7 | O11: 0 | P11: 1821883.2 | Q11: 1587811.5 | S11: 58153921 | T11: 35786889 | U11: 45371649 | V11: 3142151.2 | W11: 0 | X11: 25258114 | Y11: 4971937.6 | Z11: 0 | AA11: 38646159 | AB11: 42138125 | AC11: 1238248.1 | AD11: 24335917 | AE11: 0 | AF11: 11093882 | AG11: 9574587.7 | AI11: =+SUM(C11:Q11) -> 50521284 | AJ11: =+SUM(S11:AG11) -> 2.9971158e+08
A12: Renta Variable | C12: 1497090.6 | D12: 785783.61 | E12: 225941.85 | F12: 34541.33 | G12: 0 | H12: 68483.09 | I12: 112136.49 | J12: 0 | K12: 2864185 | L12: 374917.34 | M12: 54262.92 | N12: 737392.9 | O12: 0 | P12: 57152.45 | Q12: 359244.28 | S12: 5990094.1 | T12: 1987270.5 | U12: 1426671.6 | V12: 191960.92 | W12: 0 | X12: 587355.83 | Y12: 208587.44 | Z12: 0 | AA12: 17908373 | AB12: 2649869.8 | AC12: 188999.53 | AD12: 2626132.7 | AE12: 0 | AF12: 344350.87 | AG12: 2696910.5 | AI12: =+SUM(C12:Q12) -> 7171131.8 | AJ12: =+SUM(S12:AG12) -> 36806576
A13: Cuota de Mantenimiento | C13: 1246904 | D13: 824215.18 | E13: 1033159.7 | F13: 62313.99 | G13: 0 | H13: 575845.34 | I13: 98204.97 | J13: 0 | K13: 1114697 | L13: 930648.92 | M13: 16088.31 | N13: 604328.36 | O13: 0 | P13: 280690.05 | Q13: 257874.91 | S13: 7414026.9 | T13: 5028347 | U13: 6121172.9 | V13: 369929.06 | W13: 0 | X13: 3401540.3 | Y13: 584471.97 | Z13: 0 | AA13: 6884582.4 | AB13: 5553240.8 | AC13: 95879.55 | AD13: 3423240.8 | AE13: 0 | AF13: 1543730.7 | AG13: 1624559.9 | AI13: =+SUM(C13:Q13) -> 7044970.8 | AJ13: =+SUM(S13:AG13) -> 42044722
A14: Publicidad | C14: 23218.53 | D14: 0 | E14: 13378.17 | F14: 2362.5 | G14: 0 | H14: 2793.65 | I14: 0 | J14: 0 | K14: 0 | L14: 0 | M14: 0 | N14: 0 | O14: 0 | P14: 504.04 | Q14: 0 | S14: 164131.64 | T14: 0 | U14: 85484.65 | V14: 14175 | W14: 0 | X14: 16761.9 | Y14: 0 | Z14: 0 | AA14: 0 | AB14: 0 | AC14: 0 | AD14: 0 | AE14: 0 | AF14: 3024.24 | AG14: 0 | AI14: =+SUM(C14:Q14) -> 42256.89 | AJ14: =+SUM(S14:AG14) -> 283577.43
A15: Estacionamiento | C15: 3026483.3 | D15: 1705706.5 | E15: 992616.66 | F15: 0 | G15: 0 | H15: 466585.35 | I15: 0 | J15: 0 | K15: 1656562.9 | L15: 117739 | M15: 0 | N15: 762183.6 | O15: 0 | P15: 0 | Q15: 0 | S15: 16789224 | T15: 8930380.1 | U15: 5485503.9 | V15: 0 | W15: 0 | X15: 2788016.4 | Y15: 0 | Z15: 0 | AA15: 8864477.5 | AB15: 715329.1 | AC15: 0 | AD15: 4330746.1 | AE15: 0 | AF15: 0 | AG15: 0 | AI15: =+SUM(C15:Q15) -> 8727877.3 | AJ15: =+SUM(S15:AG15) -> 47903677
A16: Cuotas Condominales | C16: 0 | D16: 0 | E16: 0 | F16: 0 | G16: 0 | H16: 0 | I16: 0 | J16: 0 | K16: 0 | L16: 0 | M16: 0 | N16: 66382.47 | O16: 75450 | P16: 117880.13 | Q16: 0 | S16: 0 | T16: 0 | U16: 0 | V16: 0 | W16: 0 | X16: 0 | Y16: 0 | Z16: 0 | AA16: 0 | AB16: 0 | AC16: 0 | AD16: 1294975.2 | AE16: 511515 | AF16: 2159507.2 | AG16: 0 | AI16: =+SUM(C16:Q16) -> 259712.6 | AJ16: =+SUM(S16:AG16) -> 3965997.4
A17: Guantes | C17: 49221.13 | D17: 5050.29 | E17: 19386.77 | F17: 0 | G17: 0 | H17: 621.93 | I17: 0 | J17: 0 | K17: 173476.41 | L17: 0 | M17: 0 | N17: 2740.71 | O17: 0 | P17: 520 | Q17: 0 | S17: 337096.19 | T17: 24697.56 | U17: 41560.2 | V17: 0 | W17: 0 | X17: 1202.45 | Y17: 0 | Z17: 0 | AA17: 1025614.8 | AB17: 0 | AC17: 0 | AD17: 8619.14 | AE17: 0 | AF17: 3120 | AG17: 0 | AI17: =+SUM(C17:Q17) -> 251017.24 | AJ17: =+SUM(S17:AG17) -> 1441910.4
A18: Penalizaciones | C18: 0 | D18: 0 | E18: 1357574.8 | F18: 0 | G18: 0 | H18: 0 | I18: 0 | J18: 0 | K18: 0 | L18: 0 | M18: 0 | N18: 0 | O18: 0 | P18: 12991.18 | Q18: 0 | S18: 0 | T18: 0 | U18: 1357574.8 | V18: 0 | W18: 0 | X18: 0 | Y18: 0 | Z18: 0 | AA18: 0 | AB18: 0 | AC18: 0 | AD18: 90459.29 | AE18: 0 | AF18: 12991.18 | AG18: 0 | AI18: =+SUM(C18:Q18) -> 1370566 | AJ18: =+SUM(S18:AG18) -> 1461025.3
A19: Otros Ingresos Operativos de Plazas | C19: 0 | D19: 0 | E19: 0 | F19: 0 | G19: 0 | H19: 13168.98 | I19: 0 | J19: 0 | K19: 81479.25 | L19: 0 | M19: 0 | N19: 0 | O19: 0 | P19: 0 | Q19: 0 | S19: 0 | T19: 0 | U19: 0 | V19: 0 | W19: 0 | X19: 159181.97 | Y19: 0 | Z19: 0 | AA19: 467739.6 | AB19: 0 | AC19: 0 | AD19: 0 | AE19: 0 | AF19: 0 | AG19: 0 | AI19: =+SUM(C19:Q19) -> 94648.23 | AJ19: =+SUM(S19:AG19) -> 626921.57
A20: Ingresos por Servicios: | C20: =+SUM(C21:C29) -> 0 | D20: =+SUM(D21:D29) -> 0 | E20: =+SUM(E21:E29) -> 0 | F20: =+SUM(F21:F29) -> 0 | G20: =+SUM(G21:G29) -> 0 | H20: =+SUM(H21:H29) -> 0 | I20: =+SUM(I21:I29) -> 0 | J20: =+SUM(J21:J29) -> 0 | ... Q20: =+SUM(Q21:Q29) -> 0 | S20: =+SUM(S21:S29) -> 0 | T20: =+SUM(T21:T29) -> 0 | U20: =+SUM(U21:U29) -> 0 | V20: =+SUM(V21:V29) -> 0 | W20: =+SUM(W21:W29) -> 0 | X20: =+SUM(X21:X29) -> 0 | Y20: =+SUM(Y21:Y29) -> 0 | Z20: =+SUM(Z21:Z29) -> 0 | ... AG20: =+SUM(AG21:AG29) -> 0 | AI20: =+SUM(AI21:AI29) -> 0 | AJ20: =+SUM(AJ21:AJ29) -> 0
A21: Administración de Nómina | C21: 0 | D21: 0 | E21: 0 | F21: 0 | G21: 0 | H21: 0 | I21: 0 | J21: 0 | K21: 0 | L21: 0 | M21: 0 | N21: 0 | O21: 0 | P21: 0 | Q21: 0 | S21: 0 | T21: 0 | U21: 0 | V21: 0 | W21: 0 | X21: 0 | Y21: 0 | Z21: 0 | AA21: 0 | AB21: 0 | AC21: 0 | AD21: 0 | AE21: 0 | AF21: 0 | AG21: 0 | AI21: =+SUM(R21:AF21) -> 0 | AJ21: =+SUM(S21:AG21) -> 0
A22: Apertura/Cierre de Contratos | C22: 0 | D22: 0 | E22: 0 | F22: 0 | G22: 0 | H22: 0 | I22: 0 | J22: 0 | K22: 0 | L22: 0 | M22: 0 | N22: 0 | O22: 0 | P22: 0 | Q22: 0 | S22: 0 | T22: 0 | U22: 0 | V22: 0 | W22: 0 | X22: 0 | Y22: 0 | Z22: 0 | AA22: 0 | AB22: 0 | AC22: 0 | AD22: 0 | AE22: 0 | AF22: 0 | AG22: 0 | AI22: =+SUM(R22:AF22) -> 0 | AJ22: =+SUM(S22:AG22) -> 0
A23: Renovación de Contratos | C23: 0 | D23: 0 | E23: 0 | F23: 0 | G23: 0 | H23: 0 | I23: 0 | J23: 0 | K23: 0 | L23: 0 | M23: 0 | N23: 0 | O23: 0 | P23: 0 | Q23: 0 | S23: 0 | T23: 0 | U23: 0 | V23: 0 | W23: 0 | X23: 0 | Y23: 0 | Z23: 0 | AA23: 0 | AB23: 0 | AC23: 0 | AD23: 0 | AE23: 0 | AF23: 0 | AG23: 0 | AI23: =+SUM(R23:AF23) -> 0 | AJ23: =+SUM(S23:AG23) -> 0
A24: Administración de Obra | C24: 0 | D24: 0 | E24: 0 | F24: 0 | G24: 0 | H24: 0 | I24: 0 | J24: 0 | K24: 0 | L24: 0 | M24: 0 | N24: 0 | O24: 0 | P24: 0 | Q24: 0 | S24: 0 | T24: 0 | U24: 0 | V24: 0 | W24: 0 | X24: 0 | Y24: 0 | Z24: 0 | AA24: 0 | AB24: 0 | AC24: 0 | AD24: 0 | AE24: 0 | AF24: 0 | AG24: 0 | AI24: =+SUM(R24:AF24) -> 0 | AJ24: =+SUM(S24:AG24) -> 0
A25: Administración de Plaza | C25: 0 | D25: 0 | E25: 0 | F25: 0 | G25: 0 | H25: 0 | I25: 0 | J25: 0 | K25: 0 | L25: 0 | M25: 0 | N25: 0 | O25: 0 | P25: 0 | Q25: 0 | S25: 0 | T25: 0 | U25: 0 | V25: 0 | W25: 0 | X25: 0 | Y25: 0 | Z25: 0 | AA25: 0 | AB25: 0 | AC25: 0 | AD25: 0 | AE25: 0 | AF25: 0 | AG25: 0 | AI25: =+SUM(R25:AF25) -> 0 | AJ25: =+SUM(S25:AG25) -> 0
A26: Consultoría | C26: 0 | D26: 0 | E26: 0 | F26: 0 | G26: 0 | H26: 0 | I26: 0 | J26: 0 | K26: 0 | L26: 0 | M26: 0 | N26: 0 | O26: 0 | P26: 0 | Q26: 0 | S26: 0 | T26: 0 | U26: 0 | V26: 0 | W26: 0 | X26: 0 | Y26: 0 | Z26: 0 | AA26: 0 | AB26: 0 | AC26: 0 | AD26: 0 | AE26: 0 | AF26: 0 | AG26: 0 | AI26: =+SUM(R26:AF26) -> 0 | AJ26: =+SUM(S26:AG26) -> 0
A27: Renta de Terrenos | C27: 0 | D27: 0 | E27: 0 | F27: 0 | G27: 0 | H27: 0 | I27: 0 | J27: 0 | K27: 0 | L27: 0 | M27: 0 | N27: 0 | O27: 0 | P27: 0 | Q27: 0 | S27: 0 | T27: 0 | U27: 0 | V27: 0 | W27: 0 | X27: 0 | Y27: 0 | Z27: 0 | AA27: 0 | AB27: 0 | AC27: 0 | AD27: 0 | AE27: 0 | AF27: 0 | AG27: 0 | AI27: =+SUM(R27:AF27) -> 0 | AJ27: =+SUM(S27:AG27) -> 0
A28: Operación de Hotel | C28: 0 | D28: 0 | E28: 0 | F28: 0 | G28: 0 | H28: 0 | I28: 0 | J28: 0 | K28: 0 | L28: 0 | M28: 0 | N28: 0 | O28: 0 | P28: 0 | Q28: 0 | S28: 0 | T28: 0 | U28: 0 | V28: 0 | W28: 0 | X28: 0 | Y28: 0 | Z28: 0 | AA28: 0 | AB28: 0 | AC28: 0 | AD28: 0 | AE28: 0 | AF28: 0 | AG28: 0 | AI28: =+SUM(R28:AF28) -> 0 | AJ28: =+SUM(S28:AG28) -> 0
A29: Otros Servicios | C29: 0 | D29: 0 | E29: 0 | F29: 0 | G29: 0 | H29: 0 | I29: 0 | J29: 0 | K29: 0 | L29: 0 | M29: 0 | N29: 0 | O29: 0 | P29: 0 | Q29: 0 | S29: 0 | T29: 0 | U29: 0 | V29: 0 | W29: 0 | X29: 0 | Y29: 0 | Z29: 0 | AA29: 0 | AB29: 0 | AC29: 0 | AD29: 0 | AE29: 0 | AF29: 0 | AG29: 0 | AI29: =+SUM(R29:AF29) -> 0 | AJ29: =+SUM(S29:AG29) -> 0
A31: Total Ingresos Brutos | C31: =+C10+C20 -> 15568235 | D31: =+D10+D20 -> 9232008.4 | E31: =+E10+E20 -> 11497740 | F31: =+F10+F20 -> 620657.56 | G31: =+G10+G20 -> 0 | H31: =+H10+H20 -> 5217715.4 | I31: =+I10+I20 -> 1041623.9 | J31: =+J10+J20 -> 0 | ... Q31: =+Q10+Q20 -> 2204930.6 | S31: =+S10+S20 -> 88848494 | T31: =+T10+T20 -> 51757584 | U31: =+U10+U20 -> 59889617 | V31: =+V10+V20 -> 3718216.2 | W31: =+W10+W20 -> 0 | X31: =+X10+X20 -> 32212173 | Y31: =+Y10+Y20 -> 5764997 | Z31: =+Z10+Z20 -> 0 | ... AG31: =+AG10+AG20 -> 13896058 | AI31: =+AI10+AI20 -> 75483465 | AJ31: =+AJ10+AJ20 -> 4.3424599e+08
A33: BONIFICACIONES SOBRE INGRESOS
A35: Ingresos por Operación de Plazas: | C35: =+SUM(C36:C44) -> 108072.19 | D35: =+SUM(D36:D44) -> 0 | E35: =+SUM(E36:E44) -> 0 | F35: =+SUM(F36:F44) -> 0 | G35: =+SUM(G36:G44) -> 0 | H35: =+SUM(H36:H44) -> 51340.88 | I35: =+SUM(I36:I44) -> 4707.86 | J35: =+SUM(J36:J44) -> 0 | ... Q35: =+SUM(Q36:Q44) -> 0 | S35: =+SUM(S36:S44) -> 155441.65 | T35: =+SUM(T36:T44) -> 320148.71 | U35: =+SUM(U36:U44) -> 5273.44 | V35: =+SUM(V36:V44) -> 32921.52 | W35: =+SUM(W36:W44) -> 0 | X35: =+SUM(X36:X44) -> 544272.07 | Y35: =+SUM(Y36:Y44) -> 4707.86 | Z35: =+SUM(Z36:Z44) -> 0 | ... AG35: =+SUM(AG36:AG44) -> 44051.05 | AI35: =+SUM(AI36:AI44) -> 1224405.9 | AJ35: =+SUM(AJ36:AJ44) -> 5792750.1
A36: Renta Mínima | C36: 108072.19 | D36: 0 | E36: 0 | F36: 0 | G36: 0 | H36: 46147.48 | I36: 4707.86 | J36: 0 | K36: 246244.68 | L36: 0 | M36: 0 | N36: 662590.54 | O36: 0 | P36: 0 | Q36: 0 | S36: 148777.44 | T36: 294901.81 | U36: 4394.53 | V36: 12662.12 | W36: 0 | X36: 512346.63 | Y36: 4707.86 | Z36: 0 | AA36: 913332.09 | AB36: 0 | AC36: 0 | AD36: 3478067.3 | AE36: 0 | AF36: 78442.39 | AG36: 44051.05 | AI36: =+SUM(C36:Q36) -> 1067762.8 | AJ36: =+SUM(S36:AG36) -> 5491683.2
A37: Renta Variable | C37: 0 | D37: 0 | E37: 0 | F37: 0 | G37: 0 | H37: 0 | I37: 0 | J37: 0 | K37: 0 | L37: 0 | M37: 0 | N37: 0 | O37: 0 | P37: 0 | Q37: 0 | S37: 0 | T37: 0 | U37: 0 | V37: 0 | W37: 0 | X37: 0 | Y37: 0 | Z37: 0 | AA37: 0 | AB37: 0 | AC37: 0 | AD37: 0 | AE37: 0 | AF37: 33362.85 | AG37: 0 | AI37: =+SUM(C37:Q37) -> 0 | AJ37: =+SUM(S37:AG37) -> 33362.85
A38: Cuota de Mantenimiento | C38: 0 | D38: 0 | E38: 0 | F38: 0 | G38: 0 | H38: 5193.4 | I38: 0 | J38: 0 | K38: 0 | L38: 0 | M38: 0 | N38: 151449.7 | O38: 0 | P38: 0 | Q38: 0 | S38: 6664.21 | T38: 25246.9 | U38: 878.91 | V38: 3798.64 | W38: 0 | X38: 31925.44 | Y38: 0 | Z38: 0 | AA38: 19149.53 | AB38: 0 | AC38: 0 | AD38: 155735.38 | AE38: 0 | AF38: 7844.24 | AG38: 0 | AI38: =+SUM(C38:Q38) -> 156643.1 | AJ38: =+SUM(S38:AG38) -> 251243.25
A39: Publicidad | C39: 0 | D39: 0 | E39: 0 | F39: 0 | G39: 0 | H39: 0 | I39: 0 | J39: 0 | K39: 0 | L39: 0 | M39: 0 | N39: 0 | O39: 0 | P39: 0 | Q39: 0 | S39: 0 | T39: 0 | U39: 0 | V39: 0 | W39: 0 | X39: 0 | Y39: 0 | Z39: 0 | AA39: 0 | AB39: 0 | AC39: 0 | AD39: 0 | AE39: 0 | AF39: 0 | AG39: 0 | AI39: =+SUM(C39:Q39) -> 0 | AJ39: =+SUM(S39:AG39) -> 0
A40: Estacionamiento | C40: 0 | D40: 0 | E40: 0 | F40: 0 | G40: 0 | H40: 0 | I40: 0 | J40: 0 | K40: 0 | L40: 0 | M40: 0 | N40: 0 | O40: 0 | P40: 0 | Q40: 0 | S40: 0 | T40: 0 | U40: 0 | V40: 0 | W40: 0 | X40: 0 | Y40: 0 | Z40: 0 | AA40: 0 | AB40: 0 | AC40: 0 | AD40: 0 | AE40: 0 | AF40: 0 | AG40: 0 | AI40: =+SUM(C40:Q40) -> 0 | AJ40: =+SUM(S40:AG40) -> 0
A41: Cuotas Condominales | C41: 0 | D41: 0 | E41: 0 | F41: 0 | G41: 0 | H41: 0 | I41: 0 | J41: 0 | K41: 0 | L41: 0 | M41: 0 | N41: 0 | O41: 0 | P41: 0 | Q41: 0 | S41: 0 | T41: 0 | U41: 0 | V41: 0 | W41: 0 | X41: 0 | Y41: 0 | Z41: 0 | AA41: 0 | AB41: 0 | AC41: 0 | AD41: 0 | AE41: 0 | AF41: 0 | AG41: 0 | AI41: =+SUM(C41:Q41) -> 0 | AJ41: =+SUM(S41:AG41) -> 0
A42: Guantes | C42: 0 | D42: 0 | E42: 0 | F42: 0 | G42: 0 | H42: 0 | I42: 0 | J42: 0 | K42: 0 | L42: 0 | M42: 0 | N42: 0 | O42: 0 | P42: 0 | Q42: 0 | S42: 0 | T42: 0 | U42: 0 | V42: 0 | W42: 0 | X42: 0 | Y42: 0 | Z42: 0 | AA42: 0 | AB42: 0 | AC42: 0 | AD42: 0 | AE42: 0 | AF42: 0 | AG42: 0 | AI42: =+SUM(C42:Q42) -> 0 | AJ42: =+SUM(S42:AG42) -> 0
A43: Penalizaciones | C43: 0 | D43: 0 | E43: 0 | F43: 0 | G43: 0 | H43: 0 | I43: 0 | J43: 0 | K43: 0 | L43: 0 | M43: 0 | N43: 0 | O43: 0 | P43: 0 | Q43: 0 | S43: 0 | T43: 0 | U43: 0 | V43: 16460.76 | W43: 0 | X43: 0 | Y43: 0 | Z43: 0 | AA43: 0 | AB43: 0 | AC43: 0 | AD43: 0 | AE43: 0 | AF43: 0 | AG43: 0 | AI43: =+SUM(C43:Q43) -> 0 | AJ43: =+SUM(S43:AG43) -> 16460.76
A44: Otros Ingresos Operativos de Plazas | C44: 0 | D44: 0 | E44: 0 | F44: 0 | G44: 0 | H44: 0 | I44: 0 | J44: 0 | K44: 0 | L44: 0 | M44: 0 | N44: 0 | O44: 0 | P44: 0 | Q44: 0 | S44: 0 | T44: 0 | U44: 0 | V44: 0 | W44: 0 | X44: 0 | Y44: 0 | Z44: 0 | AA44: 0 | AB44: 0 | AC44: 0 | AD44: 0 | AE44: 0 | AF44: 0 | AG44: 0 | AI44: =+SUM(C44:Q44) -> 0 | AJ44: =+SUM(S44:AG44) -> 0
A45: Ingresos por Servicios: | C45: =+SUM(C46:C54) -> 0 | D45: =+SUM(D46:D54) -> 0 | E45: =+SUM(E46:E54) -> 0 | F45: =+SUM(F46:F54) -> 0 | G45: =+SUM(G46:G54) -> 0 | H45: =+SUM(H46:H54) -> 0 | I45: =+SUM(I46:I54) -> 0 | J45: =+SUM(J46:J54) -> 0 | ... Q45: =+SUM(Q46:Q54) -> 0 | S45: =+SUM(S46:S54) -> 0 | T45: =+SUM(T46:T54) -> 0 | U45: =+SUM(U46:U54) -> 0 | V45: =+SUM(V46:V54) -> 0 | W45: =+SUM(W46:W54) -> 0 | X45: =+SUM(X46:X54) -> 0 | Y45: =+SUM(Y46:Y54) -> 0 | Z45: =+SUM(Z46:Z54) -> 0 | ... AG45: =+SUM(AG46:AG54) -> 0 | AI45: =+SUM(AI46:AI54) -> 0 | AJ45: =+SUM(AJ46:AJ54) -> 0
A46: Administración de Nómina | C46: 0 | D46: 0 | E46: 0 | F46: 0 | G46: 0 | H46: 0 | I46: 0 | J46: 0 | K46: 0 | L46: 0 | M46: 0 | N46: 0 | O46: 0 | P46: 0 | Q46: 0 | S46: 0 | T46: 0 | U46: 0 | V46: 0 | W46: 0 | X46: 0 | Y46: 0 | Z46: 0 | AA46: 0 | AB46: 0 | AC46: 0 | AD46: 0 | AE46: 0 | AF46: 0 | AG46: 0 | AI46: =+SUM(R46:AF46) -> 0 | AJ46: =+SUM(S46:AG46) -> 0
A47: Apertura/Cierre de Contratos | C47: 0 | D47: 0 | E47: 0 | F47: 0 | G47: 0 | H47: 0 | I47: 0 | J47: 0 | K47: 0 | L47: 0 | M47: 0 | N47: 0 | O47: 0 | P47: 0 | Q47: 0 | S47: 0 | T47: 0 | U47: 0 | V47: 0 | W47: 0 | X47: 0 | Y47: 0 | Z47: 0 | AA47: 0 | AB47: 0 | AC47: 0 | AD47: 0 | AE47: 0 | AF47: 0 | AG47: 0 | AI47: =+SUM(R47:AF47) -> 0 | AJ47: =+SUM(S47:AG47) -> 0
A48: Renovación de Contratos | C48: 0 | D48: 0 | E48: 0 | F48: 0 | G48: 0 | H48: 0 | I48: 0 | J48: 0 | K48: 0 | L48: 0 | M48: 0 | N48: 0 | O48: 0 | P48: 0 | Q48: 0 | S48: 0 | T48: 0 | U48: 0 | V48: 0 | W48: 0 | X48: 0 | Y48: 0 | Z48: 0 | AA48: 0 | AB48: 0 | AC48: 0 | AD48: 0 | AE48: 0 | AF48: 0 | AG48: 0 | AI48: =+SUM(R48:AF48) -> 0 | AJ48: =+SUM(S48:AG48) -> 0
A49: Administración de Obra | C49: 0 | D49: 0 | E49: 0 | F49: 0 | G49: 0 | H49: 0 | I49: 0 | J49: 0 | K49: 0 | L49: 0 | M49: 0 | N49: 0 | O49: 0 | P49: 0 | Q49: 0 | S49: 0 | T49: 0 | U49: 0 | V49: 0 | W49: 0 | X49: 0 | Y49: 0 | Z49: 0 | AA49: 0 | AB49: 0 | AC49: 0 | AD49: 0 | AE49: 0 | AF49: 0 | AG49: 0 | AI49: =+SUM(R49:AF49) -> 0 | AJ49: =+SUM(S49:AG49) -> 0
A50: Administración de Plaza | C50: 0 | D50: 0 | E50: 0 | F50: 0 | G50: 0 | H50: 0 | I50: 0 | J50: 0 | K50: 0 | L50: 0 | M50: 0 | N50: 0 | O50: 0 | P50: 0 | Q50: 0 | S50: 0 | T50: 0 | U50: 0 | V50: 0 | W50: 0 | X50: 0 | Y50: 0 | Z50: 0 | AA50: 0 | AB50: 0 | AC50: 0 | AD50: 0 | AE50: 0 | AF50: 0 | AG50: 0 | AI50: =+SUM(R50:AF50) -> 0 | AJ50: =+SUM(S50:AG50) -> 0
A51: Consultoría | C51: 0 | D51: 0 | E51: 0 | F51: 0 | G51: 0 | H51: 0 | I51: 0 | J51: 0 | K51: 0 | L51: 0 | M51: 0 | N51: 0 | O51: 0 | P51: 0 | Q51: 0 | S51: 0 | T51: 0 | U51: 0 | V51: 0 | W51: 0 | X51: 0 | Y51: 0 | Z51: 0 | AA51: 0 | AB51: 0 | AC51: 0 | AD51: 0 | AE51: 0 | AF51: 0 | AG51: 0 | AI51: =+SUM(R51:AF51) -> 0 | AJ51: =+SUM(S51:AG51) -> 0
A52: Renta de Terrenos | C52: 0 | D52: 0 | E52: 0 | F52: 0 | G52: 0 | H52: 0 | I52: 0 | J52: 0 | K52: 0 | L52: 0 | M52: 0 | N52: 0 | O52: 0 | P52: 0 | Q52: 0 | S52: 0 | T52: 0 | U52: 0 | V52: 0 | W52: 0 | X52: 0 | Y52: 0 | Z52: 0 | AA52: 0 | AB52: 0 | AC52: 0 | AD52: 0 | AE52: 0 | AF52: 0 | AG52: 0 | AI52: =+SUM(R52:AF52) -> 0 | AJ52: =+SUM(S52:AG52) -> 0
A53: Operación de Hotel | C53: 0 | D53: 0 | E53: 0 | F53: 0 | G53: 0 | H53: 0 | I53: 0 | J53: 0 | K53: 0 | L53: 0 | M53: 0 | N53: 0 | O53: 0 | P53: 0 | Q53: 0 | S53: 0 | T53: 0 | U53: 0 | V53: 0 | W53: 0 | X53: 0 | Y53: 0 | Z53: 0 | AA53: 0 | AB53: 0 | AC53: 0 | AD53: 0 | AE53: 0 | AF53: 0 | AG53: 0 | AI53: =+SUM(R53:AF53) -> 0 | AJ53: =+SUM(S53:AG53) -> 0
A54: Otros Servicios | C54: 0 | D54: 0 | E54: 0 | F54: 0 | G54: 0 | H54: 0 | I54: 0 | J54: 0 | K54: 0 | L54: 0 | M54: 0 | N54: 0 | O54: 0 | P54: 0 | Q54: 0 | S54: 0 | T54: 0 | U54: 0 | V54: 0 | W54: 0 | X54: 0 | Y54: 0 | Z54: 0 | AA54: 0 | AB54: 0 | AC54: 0 | AD54: 0 | AE54: 0 | AF54: 0 | AG54: 0 | AI54: =+SUM(R54:AF54) -> 0 | AJ54: =+SUM(S54:AG54) -> 0
A56: Total Bonificaciones sobre Ingresos | C56: =+C35+C45 -> 108072.19 | D56: =+D35+D45 -> 0 | E56: =+E35+E45 -> 0 | F56: =+F35+F45 -> 0 | G56: =+G35+G45 -> 0 | H56: =+H35+H45 -> 51340.88 | I56: =+I35+I45 -> 4707.86 | J56: =+J35+J45 -> 0 | ... Q56: =+Q35+Q45 -> 0 | S56: =+S35+S45 -> 155441.65 | T56: =+T35+T45 -> 320148.71 | U56: =+U35+U45 -> 5273.44 | V56: =+V35+V45 -> 32921.52 | W56: =+W35+W45 -> 0 | X56: =+X35+X45 -> 544272.07 | Y56: =+Y35+Y45 -> 4707.86 | Z56: =+Z35+Z45 -> 0 | ... AG56: =+AG35+AG45 -> 44051.05 | AI56: =+AI35+AI45 -> 1224405.9 | AJ56: =+AJ35+AJ45 -> 5792750.1
A58: DEVOLUCIONES SOBRE INGRESOS
A60: Ingresos por Operación de Plazas: | C60: =+SUM(C61:C69) -> 0 | D60: =+SUM(D61:D69) -> 0 | E60: =+SUM(E61:E69) -> 0 | F60: =+SUM(F61:F69) -> 0 | G60: =+SUM(G61:G69) -> 0 | H60: =+SUM(H61:H69) -> 0 | I60: =+SUM(I61:I69) -> 0 | J60: =+SUM(J61:J69) -> 0 | ... Q60: =+SUM(Q61:Q69) -> 0 | S60: =+SUM(S61:S69) -> 0 | T60: =+SUM(T61:T69) -> 0 | U60: =+SUM(U61:U69) -> 0 | V60: =+SUM(V61:V69) -> 0 | W60: =+SUM(W61:W69) -> 0 | X60: =+SUM(X61:X69) -> 23827.52 | Y60: =+SUM(Y61:Y69) -> 0 | Z60: =+SUM(Z61:Z69) -> 0 | ... AG60: =+SUM(AG61:AG69) -> 0 | AI60: =+SUM(AI61:AI69) -> 0 | AJ60: =+SUM(AJ61:AJ69) -> 348059.55
A61: Renta Mínima | C61: 0 | D61: 0 | E61: 0 | F61: 0 | G61: 0 | H61: 0 | I61: 0 | J61: 0 | K61: 0 | L61: 0 | M61: 0 | N61: 0 | O61: 0 | P61: 0 | Q61: 0 | S61: 0 | T61: 0 | U61: 0 | V61: 0 | W61: 0 | X61: 19215.74 | Y61: 0 | Z61: 0 | AA61: 0 | AB61: 0 | AC61: 0 | AD61: 0 | AE61: 0 | AF61: 0 | AG61: 0 | AI61: =+SUM(C61:Q61) -> 0 | AJ61: =+SUM(S61:AG61) -> 19215.74
A62: Renta Variable | C62: 0 | D62: 0 | E62: 0 | F62: 0 | G62: 0 | H62: 0 | I62: 0 | J62: 0 | K62: 0 | L62: 0 | M62: 0 | N62: 0 | O62: 0 | P62: 0 | Q62: 0 | S62: 0 | T62: 0 | U62: 0 | V62: 0 | W62: 0 | X62: 0 | Y62: 0 | Z62: 0 | AA62: 0 | AB62: 0 | AC62: 0 | AD62: 0 | AE62: 0 | AF62: 0 | AG62: 0 | AI62: =+SUM(C62:Q62) -> 0 | AJ62: =+SUM(S62:AG62) -> 0
A63: Cuota de Mantenimiento | C63: 0 | D63: 0 | E63: 0 | F63: 0 | G63: 0 | H63: 0 | I63: 0 | J63: 0 | K63: 0 | L63: 0 | M63: 0 | N63: 0 | O63: 0 | P63: 0 | Q63: 0 | S63: 0 | T63: 0 | U63: 0 | V63: 0 | W63: 0 | X63: 4611.78 | Y63: 0 | Z63: 0 | AA63: 0 | AB63: 7000 | AC63: 0 | AD63: 0 | AE63: 0 | AF63: 0 | AG63: 0 | AI63: =+SUM(C63:Q63) -> 0 | AJ63: =+SUM(S63:AG63) -> 11611.78
A64: Publicidad | C64: 0 | D64: 0 | E64: 0 | F64: 0 | G64: 0 | H64: 0 | I64: 0 | J64: 0 | K64: 0 | L64: 0 | M64: 0 | N64: 0 | O64: 0 | P64: 0 | Q64: 0 | S64: 0 | T64: 0 | U64: 0 | V64: 0 | W64: 0 | X64: 0 | Y64: 0 | Z64: 0 | AA64: 0 | AB64: 0 | AC64: 0 | AD64: 0 | AE64: 0 | AF64: 0 | AG64: 0 | AI64: =+SUM(C64:Q64) -> 0 | AJ64: =+SUM(S64:AG64) -> 0
A65: Estacionamiento | C65: 0 | D65: 0 | E65: 0 | F65: 0 | G65: 0 | H65: 0 | I65: 0 | J65: 0 | K65: 0 | L65: 0 | M65: 0 | N65: 0 | O65: 0 | P65: 0 | Q65: 0 | S65: 0 | T65: 0 | U65: 0 | V65: 0 | W65: 0 | X65: 0 | Y65: 0 | Z65: 0 | AA65: 0 | AB65: 0 | AC65: 0 | AD65: 0 | AE65: 0 | AF65: 0 | AG65: 0 | AI65: =+SUM(C65:Q65) -> 0 | AJ65: =+SUM(S65:AG65) -> 0
A66: Cuotas Condominales | C66: 0 | D66: 0 | E66: 0 | F66: 0 | G66: 0 | H66: 0 | I66: 0 | J66: 0 | K66: 0 | L66: 0 | M66: 0 | N66: 0 | O66: 0 | P66: 0 | Q66: 0 | S66: 0 | T66: 0 | U66: 0 | V66: 0 | W66: 0 | X66: 0 | Y66: 0 | Z66: 0 | AA66: 0 | AB66: 0 | AC66: 0 | AD66: 0 | AE66: 0 | AF66: 317232.03 | AG66: 0 | AI66: =+SUM(C66:Q66) -> 0 | AJ66: =+SUM(S66:AG66) -> 317232.03
A67: Guantes | C67: 0 | D67: 0 | E67: 0 | F67: 0 | G67: 0 | H67: 0 | I67: 0 | J67: 0 | K67: 0 | L67: 0 | M67: 0 | N67: 0 | O67: 0 | P67: 0 | Q67: 0 | S67: 0 | T67: 0 | U67: 0 | V67: 0 | W67: 0 | X67: 0 | Y67: 0 | Z67: 0 | AA67: 0 | AB67: 0 | AC67: 0 | AD67: 0 | AE67: 0 | AF67: 0 | AG67: 0 | AI67: =+SUM(C67:Q67) -> 0 | AJ67: =+SUM(S67:AG67) -> 0
A68: Penalizaciones | C68: 0 | D68: 0 | E68: 0 | F68: 0 | G68: 0 | H68: 0 | I68: 0 | J68: 0 | K68: 0 | L68: 0 | M68: 0 | N68: 0 | O68: 0 | P68: 0 | Q68: 0 | S68: 0 | T68: 0 | U68: 0 | V68: 0 | W68: 0 | X68: 0 | Y68: 0 | Z68: 0 | AA68: 0 | AB68: 0 | AC68: 0 | AD68: 0 | AE68: 0 | AF68: 0 | AG68: 0 | AI68: =+SUM(C68:Q68) -> 0 | AJ68: =+SUM(S68:AG68) -> 0
A69: Otros Ingresos Operativos de Plazas | C69: 0 | D69: 0 | E69: 0 | F69: 0 | G69: 0 | H69: 0 | I69: 0 | J69: 0 | K69: 0 | L69: 0 | M69: 0 | N69: 0 | O69: 0 | P69: 0 | Q69: 0 | S69: 0 | T69: 0 | U69: 0 | V69: 0 | W69: 0 | X69: 0 | Y69: 0 | Z69: 0 | AA69: 0 | AB69: 0 | AC69: 0 | AD69: 0 | AE69: 0 | AF69: 0 | AG69: 0 | AI69: =+SUM(C69:Q69) -> 0 | AJ69: =+SUM(S69:AG69) -> 0
A70: Ingresos por Servicios: | C70: =+SUM(C71:C79) -> 0 | D70: =+SUM(D71:D79) -> 0 | E70: =+SUM(E71:E79) -> 0 | F70: =+SUM(F71:F79) -> 0 | G70: =+SUM(G71:G79) -> 0 | H70: =+SUM(H71:H79) -> 0 | I70: =+SUM(I71:I79) -> 0 | J70: =+SUM(J71:J79) -> 0 | ... Q70: =+SUM(Q71:Q79) -> 0 | S70: =+SUM(S71:S79) -> 0 | T70: =+SUM(T71:T79) -> 0 | U70: =+SUM(U71:U79) -> 0 | V70: =+SUM(V71:V79) -> 0 | W70: =+SUM(W71:W79) -> 0 | X70: =+SUM(X71:X79) -> 0 | Y70: =+SUM(Y71:Y79) -> 0 | Z70: =+SUM(Z71:Z79) -> 0 | ... AG70: =+SUM(AG71:AG79) -> 0 | AI70: =+SUM(AI71:AI79) -> 0 | AJ70: =+SUM(AJ71:AJ79) -> 0
A71: Administración de Nómina | C71: 0 | D71: 0 | E71: 0 | F71: 0 | G71: 0 | H71: 0 | I71: 0 | J71: 0 | K71: 0 | L71: 0 | M71: 0 | N71: 0 | O71: 0 | P71: 0 | Q71: 0 | S71: 0 | T71: 0 | U71: 0 | V71: 0 | W71: 0 | X71: 0 | Y71: 0 | Z71: 0 | AA71: 0 | AB71: 0 | AC71: 0 | AD71: 0 | AE71: 0 | AF71: 0 | AG71: 0 | AI71: =+SUM(R71:AF71) -> 0 | AJ71: =+SUM(S71:AG71) -> 0
A72: Apertura/Cierre de Contratos | C72: 0 | D72: 0 | E72: 0 | F72: 0 | G72: 0 | H72: 0 | I72: 0 | J72: 0 | K72: 0 | L72: 0 | M72: 0 | N72: 0 | O72: 0 | P72: 0 | Q72: 0 | S72: 0 | T72: 0 | U72: 0 | V72: 0 | W72: 0 | X72: 0 | Y72: 0 | Z72: 0 | AA72: 0 | AB72: 0 | AC72: 0 | AD72: 0 | AE72: 0 | AF72: 0 | AG72: 0 | AI72: =+SUM(R72:AF72) -> 0 | AJ72: =+SUM(S72:AG72) -> 0
A73: Renovación de Contratos | C73: 0 | D73: 0 | E73: 0 | F73: 0 | G73: 0 | H73: 0 | I73: 0 | J73: 0 | K73: 0 | L73: 0 | M73: 0 | N73: 0 | O73: 0 | P73: 0 | Q73: 0 | S73: 0 | T73: 0 | U73: 0 | V73: 0 | W73: 0 | X73: 0 | Y73: 0 | Z73: 0 | AA73: 0 | AB73: 0 | AC73: 0 | AD73: 0 | AE73: 0 | AF73: 0 | AG73: 0 | AI73: =+SUM(R73:AF73) -> 0 | AJ73: =+SUM(S73:AG73) -> 0
A74: Administración de Obra | C74: 0 | D74: 0 | E74: 0 | F74: 0 | G74: 0 | H74: 0 | I74: 0 | J74: 0 | K74: 0 | L74: 0 | M74: 0 | N74: 0 | O74: 0 | P74: 0 | Q74: 0 | S74: 0 | T74: 0 | U74: 0 | V74: 0 | W74: 0 | X74: 0 | Y74: 0 | Z74: 0 | AA74: 0 | AB74: 0 | AC74: 0 | AD74: 0 | AE74: 0 | AF74: 0 | AG74: 0 | AI74: =+SUM(R74:AF74) -> 0 | AJ74: =+SUM(S74:AG74) -> 0
A75: Administración de Plaza | C75: 0 | D75: 0 | E75: 0 | F75: 0 | G75: 0 | H75: 0 | I75: 0 | J75: 0 | K75: 0 | L75: 0 | M75: 0 | N75: 0 | O75: 0 | P75: 0 | Q75: 0 | S75: 0 | T75: 0 | U75: 0 | V75: 0 | W75: 0 | X75: 0 | Y75: 0 | Z75: 0 | AA75: 0 | AB75: 0 | AC75: 0 | AD75: 0 | AE75: 0 | AF75: 0 | AG75: 0 | AI75: =+SUM(R75:AF75) -> 0 | AJ75: =+SUM(S75:AG75) -> 0
A76: Consultoría | C76: 0 | D76: 0 | E76: 0 | F76: 0 | G76: 0 | H76: 0 | I76: 0 | J76: 0 | K76: 0 | L76: 0 | M76: 0 | N76: 0 | O76: 0 | P76: 0 | Q76: 0 | S76: 0 | T76: 0 | U76: 0 | V76: 0 | W76: 0 | X76: 0 | Y76: 0 | Z76: 0 | AA76: 0 | AB76: 0 | AC76: 0 | AD76: 0 | AE76: 0 | AF76: 0 | AG76: 0 | AI76: =+SUM(R76:AF76) -> 0 | AJ76: =+SUM(S76:AG76) -> 0
A77: Renta de Terrenos | C77: 0 | D77: 0 | E77: 0 | F77: 0 | G77: 0 | H77: 0 | I77: 0 | J77: 0 | K77: 0 | L77: 0 | M77: 0 | N77: 0 | O77: 0 | P77: 0 | Q77: 0 | S77: 0 | T77: 0 | U77: 0 | V77: 0 | W77: 0 | X77: 0 | Y77: 0 | Z77: 0 | AA77: 0 | AB77: 0 | AC77: 0 | AD77: 0 | AE77: 0 | AF77: 0 | AG77: 0 | AI77: =+SUM(R77:AF77) -> 0 | AJ77: =+SUM(S77:AG77) -> 0
A78: Operación de Hotel | C78: 0 | D78: 0 | E78: 0 | F78: 0 | G78: 0 | H78: 0 | I78: 0 | J78: 0 | K78: 0 | L78: 0 | M78: 0 | N78: 0 | O78: 0 | P78: 0 | Q78: 0 | S78: 0 | T78: 0 | U78: 0 | V78: 0 | W78: 0 | X78: 0 | Y78: 0 | Z78: 0 | AA78: 0 | AB78: 0 | AC78: 0 | AD78: 0 | AE78: 0 | AF78: 0 | AG78: 0 | AI78: =+SUM(R78:AF78) -> 0 | AJ78: =+SUM(S78:AG78) -> 0
A79: Otros Servicios | C79: 0 | D79: 0 | E79: 0 | F79: 0 | G79: 0 | H79: 0 | I79: 0 | J79: 0 | K79: 0 | L79: 0 | M79: 0 | N79: 0 | O79: 0 | P79: 0 | Q79: 0 | S79: 0 | T79: 0 | U79: 0 | V79: 0 | W79: 0 | X79: 0 | Y79: 0 | Z79: 0 | AA79: 0 | AB79: 0 | AC79: 0 | AD79: 0 | AE79: 0 | AF79: 0 | AG79: 0 | AI79: =+SUM(R79:AF79) -> 0 | AJ79: =+SUM(S79:AG79) -> 0
A81: Total Devoluciones sobre Ventas | C81: =+C60+C70 -> 0 | D81: =+D60+D70 -> 0 | E81: =+E60+E70 -> 0 | F81: =+F60+F70 -> 0 | G81: =+G60+G70 -> 0 | H81: =+H60+H70 -> 0 | I81: =+I60+I70 -> 0 | J81: =+J60+J70 -> 0 | ... Q81: =+Q60+Q70 -> 0 | S81: =+S60+S70 -> 0 | T81: =+T60+T70 -> 0 | U81: =+U60+U70 -> 0 | V81: =+V60+V70 -> 0 | W81: =+W60+W70 -> 0 | X81: =+X60+X70 -> 23827.52 | Y81: =+Y60+Y70 -> 0 | Z81: =+Z60+Z70 -> 0 | ... AG81: =+AG60+AG70 -> 0 | AI81: =+AI60+AI70 -> 0 | AJ81: =+AJ60+AJ70 -> 348059.55
A83: INGRESOS NETOS
A85: Ingresos por Operación de Plazas: | C85: =+SUM(C86:C94) -> 15460162 | D85: =+SUM(D86:D94) -> 9232008.4 | E85: =+SUM(E86:E94) -> 11497740 | F85: =+SUM(F86:F94) -> 620657.56 | G85: =+SUM(G86:G94) -> 0 | H85: =+SUM(H86:H94) -> 5166374.5 | I85: =+SUM(I86:I94) -> 1036916 | J85: =+SUM(J86:J94) -> 0 | ... Q85: =+SUM(Q86:Q94) -> 2204930.6 | S85: =+SUM(S86:S94) -> 88693052 | T85: =+SUM(T86:T94) -> 51437436 | U85: =+SUM(U86:U94) -> 59884344 | V85: =+SUM(V86:V94) -> 3685294.7 | W85: =+SUM(W86:W94) -> 0 | X85: =+SUM(X86:X94) -> 31644074 | Y85: =+SUM(Y86:Y94) -> 5760289.2 | Z85: =+SUM(Z86:Z94) -> 0 | ... AG85: =+SUM(AG86:AG94) -> 13852007 | AI85: =+SUM(AI86:AI94) -> 74259059 | AJ85: =+SUM(AJ86:AJ94) -> 4.2810518e+08
A86: Renta Mínima | C86: =+C11-C36-C61 -> 9617244.9 | D86: =+D11-D36-D61 -> 5911252.9 | E86: =+E11-E36-E61 -> 7855681.9 | F86: =+F11-F36-F61 -> 521439.74 | G86: =+G11-G36-G61 -> 0 | H86: =+H11-H36-H61 -> 4044069.6 | I86: =+I11-I36-I61 -> 826574.58 | J86: =+J11-J36-J61 -> 0 | ... Q86: =+Q11-Q36-Q61 -> 1587811.5 | S86: =+S11-S36-S61 -> 58005143 | T86: =+T11-T36-T61 -> 35491987 | U86: =+U11-U36-U61 -> 45367255 | V86: =+V11-V36-V61 -> 3129489.1 | W86: =+W11-W36-W61 -> 0 | X86: =+X11-X36-X61 -> 24726552 | Y86: =+Y11-Y36-Y61 -> 4967229.7 | Z86: =+Z11-Z36-Z61 -> 0 | ... AG86: =+AG11-AG36-AG61 -> 9530536.6 | AI86: =+AI11-AI36-AI61 -> 49453521 | AJ86: =+AJ11-AJ36-AJ61 -> 2.9420068e+08
A87: Renta Variable | C87: =+C12-C37-C62 -> 1497090.6 | D87: =+D12-D37-D62 -> 785783.61 | E87: =+E12-E37-E62 -> 225941.85 | F87: =+F12-F37-F62 -> 34541.33 | G87: =+G12-G37-G62 -> 0 | H87: =+H12-H37-H62 -> 68483.09 | I87: =+I12-I37-I62 -> 112136.49 | J87: =+J12-J37-J62 -> 0 | ... Q87: =+Q12-Q37-Q62 -> 359244.28 | S87: =+S12-S37-S62 -> 5990094.1 | T87: =+T12-T37-T62 -> 1987270.5 | U87: =+U12-U37-U62 -> 1426671.6 | V87: =+V12-V37-V62 -> 191960.92 | W87: =+W12-W37-W62 -> 0 | X87: =+X12-X37-X62 -> 587355.83 | Y87: =+Y12-Y37-Y62 -> 208587.44 | Z87: =+Z12-Z37-Z62 -> 0 | ... AG87: =+AG12-AG37-AG62 -> 2696910.5 | AI87: =+AI12-AI37-AI62 -> 7171131.8 | AJ87: =+AJ12-AJ37-AJ62 -> 36773213
A88: Cuota de Mantenimiento | C88: =+C13-C38-C63 -> 1246904 | D88: =+D13-D38-D63 -> 824215.18 | E88: =+E13-E38-E63 -> 1033159.7 | F88: =+F13-F38-F63 -> 62313.99 | G88: =+G13-G38-G63 -> 0 | H88: =+H13-H38-H63 -> 570651.94 | I88: =+I13-I38-I63 -> 98204.97 | J88: =+J13-J38-J63 -> 0 | ... Q88: =+Q13-Q38-Q63 -> 257874.91 | S88: =+S13-S38-S63 -> 7407362.7 | T88: =+T13-T38-T63 -> 5003100.1 | U88: =+U13-U38-U63 -> 6120293.9 | V88: =+V13-V38-V63 -> 366130.42 | W88: =+W13-W38-W63 -> 0 | X88: =+X13-X38-X63 -> 3365003.1 | Y88: =+Y13-Y38-Y63 -> 584471.97 | Z88: =+Z13-Z38-Z63 -> 0 | ... AG88: =+AG13-AG38-AG63 -> 1624559.9 | AI88: =+AI13-AI38-AI63 -> 6888327.7 | AJ88: =+AJ13-AJ38-AJ63 -> 41781867
A89: Publicidad | C89: =+C14-C39-C64 -> 23218.53 | D89: =+D14-D39-D64 -> 0 | E89: =+E14-E39-E64 -> 13378.17 | F89: =+F14-F39-F64 -> 2362.5 | G89: =+G14-G39-G64 -> 0 | H89: =+H14-H39-H64 -> 2793.65 | I89: =+I14-I39-I64 -> 0 | J89: =+J14-J39-J64 -> 0 | ... Q89: =+Q14-Q39-Q64 -> 0 | S89: =+S14-S39-S64 -> 164131.64 | T89: =+T14-T39-T64 -> 0 | U89: =+U14-U39-U64 -> 85484.65 | V89: =+V14-V39-V64 -> 14175 | W89: =+W14-W39-W64 -> 0 | X89: =+X14-X39-X64 -> 16761.9 | Y89: =+Y14-Y39-Y64 -> 0 | Z89: =+Z14-Z39-Z64 -> 0 | ... AG89: =+AG14-AG39-AG64 -> 0 | AI89: =+AI14-AI39-AI64 -> 42256.89 | AJ89: =+AJ14-AJ39-AJ64 -> 283577.43
A90: Estacionamiento | C90: =+C15-C40-C65 -> 3026483.3 | D90: =+D15-D40-D65 -> 1705706.5 | E90: =+E15-E40-E65 -> 992616.66 | F90: =+F15-F40-F65 -> 0 | G90: =+G15-G40-G65 -> 0 | H90: =+H15-H40-H65 -> 466585.35 | I90: =+I15-I40-I65 -> 0 | J90: =+J15-J40-J65 -> 0 | ... Q90: =+Q15-Q40-Q65 -> 0 | S90: =+S15-S40-S65 -> 16789224 | T90: =+T15-T40-T65 -> 8930380.1 | U90: =+U15-U40-U65 -> 5485503.9 | V90: =+V15-V40-V65 -> 0 | W90: =+W15-W40-W65 -> 0 | X90: =+X15-X40-X65 -> 2788016.4 | Y90: =+Y15-Y40-Y65 -> 0 | Z90: =+Z15-Z40-Z65 -> 0 | ... AG90: =+AG15-AG40-AG65 -> 0 | AI90: =+AI15-AI40-AI65 -> 8727877.3 | AJ90: =+AJ15-AJ40-AJ65 -> 47903677
A91: Cuotas Condominales | C91: =+C16-C41-C66 -> 0 | D91: =+D16-D41-D66 -> 0 | E91: =+E16-E41-E66 -> 0 | F91: =+F16-F41-F66 -> 0 | G91: =+G16-G41-G66 -> 0 | H91: =+H16-H41-H66 -> 0 | I91: =+I16-I41-I66 -> 0 | J91: =+J16-J41-J66 -> 0 | ... Q91: =+Q16-Q41-Q66 -> 0 | S91: =+S16-S41-S66 -> 0 | T91: =+T16-T41-T66 -> 0 | U91: =+U16-U41-U66 -> 0 | V91: =+V16-V41-V66 -> 0 | W91: =+W16-W41-W66 -> 0 | X91: =+X16-X41-X66 -> 0 | Y91: =+Y16-Y41-Y66 -> 0 | Z91: =+Z16-Z41-Z66 -> 0 | ... AG91: =+AG16-AG41-AG66 -> 0 | AI91: =+AI16-AI41-AI66 -> 259712.6 | AJ91: =+AJ16-AJ41-AJ66 -> 3648765.4
A92: Guantes | C92: =+C17-C42-C67 -> 49221.13 | D92: =+D17-D42-D67 -> 5050.29 | E92: =+E17-E42-E67 -> 19386.77 | F92: =+F17-F42-F67 -> 0 | G92: =+G17-G42-G67 -> 0 | H92: =+H17-H42-H67 -> 621.93 | I92: =+I17-I42-I67 -> 0 | J92: =+J17-J42-J67 -> 0 | ... Q92: =+Q17-Q42-Q67 -> 0 | S92: =+S17-S42-S67 -> 337096.19 | T92: =+T17-T42-T67 -> 24697.56 | U92: =+U17-U42-U67 -> 41560.2 | V92: =+V17-V42-V67 -> 0 | W92: =+W17-W42-W67 -> 0 | X92: =+X17-X42-X67 -> 1202.45 | Y92: =+Y17-Y42-Y67 -> 0 | Z92: =+Z17-Z42-Z67 -> 0 | ... AG92: =+AG17-AG42-AG67 -> 0 | AI92: =+AI17-AI42-AI67 -> 251017.24 | AJ92: =+AJ17-AJ42-AJ67 -> 1441910.4
A93: Penalizaciones | C93: =+C18-C43-C68 -> 0 | D93: =+D18-D43-D68 -> 0 | E93: =+E18-E43-E68 -> 1357574.8 | F93: =+F18-F43-F68 -> 0 | G93: =+G18-G43-G68 -> 0 | H93: =+H18-H43-H68 -> 0 | I93: =+I18-I43-I68 -> 0 | J93: =+J18-J43-J68 -> 0 | ... Q93: =+Q18-Q43-Q68 -> 0 | S93: =+S18-S43-S68 -> 0 | T93: =+T18-T43-T68 -> 0 | U93: =+U18-U43-U68 -> 1357574.8 | V93: =+V18-V43-V68 -> -16460.76 | W93: =+W18-W43-W68 -> 0 | X93: =+X18-X43-X68 -> 0 | Y93: =+Y18-Y43-Y68 -> 0 | Z93: =+Z18-Z43-Z68 -> 0 | ... AG93: =+AG18-AG43-AG68 -> 0 | AI93: =+AI18-AI43-AI68 -> 1370566 | AJ93: =+AJ18-AJ43-AJ68 -> 1444564.6
A94: Otros Ingresos Operativos de Plazas | C94: =+C19-C44-C69 -> 0 | D94: =+D19-D44-D69 -> 0 | E94: =+E19-E44-E69 -> 0 | F94: =+F19-F44-F69 -> 0 | G94: =+G19-G44-G69 -> 0 | H94: =+H19-H44-H69 -> 13168.98 | I94: =+I19-I44-I69 -> 0 | J94: =+J19-J44-J69 -> 0 | ... Q94: =+Q19-Q44-Q69 -> 0 | S94: =+S19-S44-S69 -> 0 | T94: =+T19-T44-T69 -> 0 | U94: =+U19-U44-U69 -> 0 | V94: =+V19-V44-V69 -> 0 | W94: =+W19-W44-W69 -> 0 | X94: =+X19-X44-X69 -> 159181.97 | Y94: =+Y19-Y44-Y69 -> 0 | Z94: =+Z19-Z44-Z69 -> 0 | ... AG94: =+AG19-AG44-AG69 -> 0 | AI94: =+AI19-AI44-AI69 -> 94648.23 | AJ94: =+AJ19-AJ44-AJ69 -> 626921.57
A95: Ingresos por Servicios: | C95: =+SUM(C96:C104) -> 0 | D95: =+SUM(D96:D104) -> 0 | E95: =+SUM(E96:E104) -> 0 | F95: =+SUM(F96:F104) -> 0 | G95: =+SUM(G96:G104) -> 0 | H95: =+SUM(H96:H104) -> 0 | I95: =+SUM(I96:I104) -> 0 | J95: =+SUM(J96:J104) -> 0 | ... Q95: =+SUM(Q96:Q104) -> 0 | S95: =+SUM(S96:S104) -> 0 | T95: =+SUM(T96:T104) -> 0 | U95: =+SUM(U96:U104) -> 0 | V95: =+SUM(V96:V104) -> 0 | W95: =+SUM(W96:W104) -> 0 | X95: =+SUM(X96:X104) -> 0 | Y95: =+SUM(Y96:Y104) -> 0 | Z95: =+SUM(Z96:Z104) -> 0 | ... AG95: =+SUM(AG96:AG104) -> 0 | AI95: =+SUM(AI96:AI104) -> 0 | AJ95: =+SUM(AJ96:AJ104) -> 0
A96: Administración de Nómina | C96: =+C21-C46-C71 -> 0 | D96: =+D21-D46-D71 -> 0 | E96: =+E21-E46-E71 -> 0 | F96: =+F21-F46-F71 -> 0 | G96: =+G21-G46-G71 -> 0 | H96: =+H21-H46-H71 -> 0 | I96: =+I21-I46-I71 -> 0 | J96: =+J21-J46-J71 -> 0 | ... Q96: =+Q21-Q46-Q71 -> 0 | S96: =+S21-S46-S71 -> 0 | T96: =+T21-T46-T71 -> 0 | U96: =+U21-U46-U71 -> 0 | V96: =+V21-V46-V71 -> 0 | W96: =+W21-W46-W71 -> 0 | X96: =+X21-X46-X71 -> 0 | Y96: =+Y21-Y46-Y71 -> 0 | Z96: =+Z21-Z46-Z71 -> 0 | ... AG96: =+AG21-AG46-AG71 -> 0 | AI96: =+AI21-AI46-AI71 -> 0 | AJ96: =+AJ21-AJ46-AJ71 -> 0
A97: Apertura/Cierre de Contratos | C97: =+C22-C47-C72 -> 0 | D97: =+D22-D47-D72 -> 0 | E97: =+E22-E47-E72 -> 0 | F97: =+F22-F47-F72 -> 0 | G97: =+G22-G47-G72 -> 0 | H97: =+H22-H47-H72 -> 0 | I97: =+I22-I47-I72 -> 0 | J97: =+J22-J47-J72 -> 0 | ... Q97: =+Q22-Q47-Q72 -> 0 | S97: =+S22-S47-S72 -> 0 | T97: =+T22-T47-T72 -> 0 | U97: =+U22-U47-U72 -> 0 | V97: =+V22-V47-V72 -> 0 | W97: =+W22-W47-W72 -> 0 | X97: =+X22-X47-X72 -> 0 | Y97: =+Y22-Y47-Y72 -> 0 | Z97: =+Z22-Z47-Z72 -> 0 | ... AG97: =+AG22-AG47-AG72 -> 0 | AI97: =+AI22-AI47-AI72 -> 0 | AJ97: =+AJ22-AJ47-AJ72 -> 0
A98: Renovación de Contratos | C98: =+C23-C48-C73 -> 0 | D98: =+D23-D48-D73 -> 0 | E98: =+E23-E48-E73 -> 0 | F98: =+F23-F48-F73 -> 0 | G98: =+G23-G48-G73 -> 0 | H98: =+H23-H48-H73 -> 0 | I98: =+I23-I48-I73 -> 0 | J98: =+J23-J48-J73 -> 0 | ... Q98: =+Q23-Q48-Q73 -> 0 | S98: =+S23-S48-S73 -> 0 | T98: =+T23-T48-T73 -> 0 | U98: =+U23-U48-U73 -> 0 | V98: =+V23-V48-V73 -> 0 | W98: =+W23-W48-W73 -> 0 | X98: =+X23-X48-X73 -> 0 | Y98: =+Y23-Y48-Y73 -> 0 | Z98: =+Z23-Z48-Z73 -> 0 | ... AG98: =+AG23-AG48-AG73 -> 0 | AI98: =+AI23-AI48-AI73 -> 0 | AJ98: =+AJ23-AJ48-AJ73 -> 0
A99: Administración de Obra | C99: =+C24-C49-C74 -> 0 | D99: =+D24-D49-D74 -> 0 | E99: =+E24-E49-E74 -> 0 | F99: =+F24-F49-F74 -> 0 | G99: =+G24-G49-G74 -> 0 | H99: =+H24-H49-H74 -> 0 | I99: =+I24-I49-I74 -> 0 | J99: =+J24-J49-J74 -> 0 | ... Q99: =+Q24-Q49-Q74 -> 0 | S99: =+S24-S49-S74 -> 0 | T99: =+T24-T49-T74 -> 0 | U99: =+U24-U49-U74 -> 0 | V99: =+V24-V49-V74 -> 0 | W99: =+W24-W49-W74 -> 0 | X99: =+X24-X49-X74 -> 0 | Y99: =+Y24-Y49-Y74 -> 0 | Z99: =+Z24-Z49-Z74 -> 0 | ... AG99: =+AG24-AG49-AG74 -> 0 | AI99: =+AI24-AI49-AI74 -> 0 | AJ99: =+AJ24-AJ49-AJ74 -> 0
A100: Administración de Plaza | C100: =+C25-C50-C75 -> 0 | D100: =+D25-D50-D75 -> 0 | E100: =+E25-E50-E75 -> 0 | F100: =+F25-F50-F75 -> 0 | G100: =+G25-G50-G75 -> 0 | H100: =+H25-H50-H75 -> 0 | I100: =+I25-I50-I75 -> 0 | J100: =+J25-J50-J75 -> 0 | ... Q100: =+Q25-Q50-Q75 -> 0 | S100: =+S25-S50-S75 -> 0 | T100: =+T25-T50-T75 -> 0 | U100: =+U25-U50-U75 -> 0 | V100: =+V25-V50-V75 -> 0 | W100: =+W25-W50-W75 -> 0 | X100: =+X25-X50-X75 -> 0 | Y100: =+Y25-Y50-Y75 -> 0 | Z100: =+Z25-Z50-Z75 -> 0 | ... AG100: =+AG25-AG50-AG75 -> 0 | AI100: =+AI25-AI50-AI75 -> 0 | AJ100: =+AJ25-AJ50-AJ75 -> 0
A101: Consultoría | C101: =+C26-C51-C76 -> 0 | D101: =+D26-D51-D76 -> 0 | E101: =+E26-E51-E76 -> 0 | F101: =+F26-F51-F76 -> 0 | G101: =+G26-G51-G76 -> 0 | H101: =+H26-H51-H76 -> 0 | I101: =+I26-I51-I76 -> 0 | J101: =+J26-J51-J76 -> 0 | ... Q101: =+Q26-Q51-Q76 -> 0 | S101: =+S26-S51-S76 -> 0 | T101: =+T26-T51-T76 -> 0 | U101: =+U26-U51-U76 -> 0 | V101: =+V26-V51-V76 -> 0 | W101: =+W26-W51-W76 -> 0 | X101: =+X26-X51-X76 -> 0 | Y101: =+Y26-Y51-Y76 -> 0 | Z101: =+Z26-Z51-Z76 -> 0 | ... AG101: =+AG26-AG51-AG76 -> 0 | AI101: =+AI26-AI51-AI76 -> 0 | AJ101: =+AJ26-AJ51-AJ76 -> 0
A102: Renta de Terrenos | C102: =+C27-C52-C77 -> 0 | D102: =+D27-D52-D77 -> 0 | E102: =+E27-E52-E77 -> 0 | F102: =+F27-F52-F77 -> 0 | G102: =+G27-G52-G77 -> 0 | H102: =+H27-H52-H77 -> 0 | I102: =+I27-I52-I77 -> 0 | J102: =+J27-J52-J77 -> 0 | ... Q102: =+Q27-Q52-Q77 -> 0 | S102: =+S27-S52-S77 -> 0 | T102: =+T27-T52-T77 -> 0 | U102: =+U27-U52-U77 -> 0 | V102: =+V27-V52-V77 -> 0 | W102: =+W27-W52-W77 -> 0 | X102: =+X27-X52-X77 -> 0 | Y102: =+Y27-Y52-Y77 -> 0 | Z102: =+Z27-Z52-Z77 -> 0 | ... AG102: =+AG27-AG52-AG77 -> 0 | AI102: =+AI27-AI52-AI77 -> 0 | AJ102: =+AJ27-AJ52-AJ77 -> 0
A103: Operación de Hotel | C103: =+C28-C53-C78 -> 0 | D103: =+D28-D53-D78 -> 0 | E103: =+E28-E53-E78 -> 0 | F103: =+F28-F53-F78 -> 0 | G103: =+G28-G53-G78 -> 0 | H103: =+H28-H53-H78 -> 0 | I103: =+I28-I53-I78 -> 0 | J103: =+J28-J53-J78 -> 0 | ... Q103: =+Q28-Q53-Q78 -> 0 | S103: =+S28-S53-S78 -> 0 | T103: =+T28-T53-T78 -> 0 | U103: =+U28-U53-U78 -> 0 | V103: =+V28-V53-V78 -> 0 | W103: =+W28-W53-W78 -> 0 | X103: =+X28-X53-X78 -> 0 | Y103: =+Y28-Y53-Y78 -> 0 | Z103: =+Z28-Z53-Z78 -> 0 | ... AG103: =+AG28-AG53-AG78 -> 0 | AI103: =+AI28-AI53-AI78 -> 0 | AJ103: =+AJ28-AJ53-AJ78 -> 0 | AL103: =+AA106+AB106+AC106 -> 1.2543716e+08 | AM103: =+AD106 -> 32476288
A104: Otros Servicios | C104: =+C29-C54-C79 -> 0 | D104: =+D29-D54-D79 -> 0 | E104: =+E29-E54-E79 -> 0 | F104: =+F29-F54-F79 -> 0 | G104: =+G29-G54-G79 -> 0 | H104: =+H29-H54-H79 -> 0 | I104: =+I29-I54-I79 -> 0 | J104: =+J29-J54-J79 -> 0 | ... Q104: =+Q29-Q54-Q79 -> 0 | S104: =+S29-S54-S79 -> 0 | T104: =+T29-T54-T79 -> 0 | U104: =+U29-U54-U79 -> 0 | V104: =+V29-V54-V79 -> 0 | W104: =+W29-W54-W79 -> 0 | X104: =+X29-X54-X79 -> 0 | Y104: =+Y29-Y54-Y79 -> 0 | Z104: =+Z29-Z54-Z79 -> 0 | ... AG104: =+AG29-AG54-AG79 -> 0 | AI104: =+AI29-AI54-AI79 -> 0 | AJ104: =+AJ29-AJ54-AJ79 -> 0 | AL104: 1.0888289e+08 | AM104: 27566200
A106: Total Ingresos Netos | C106: =+C85+C95 -> 15460162 | D106: =+D85+D95 -> 9232008.4 | E106: =+E85+E95 -> 11497740 | F106: =+F85+F95 -> 620657.56 | G106: =+G85+G95 -> 0 | H106: =+H85+H95 -> 5166374.5 | I106: =+I85+I95 -> 1036916 | J106: =+J85+J95 -> 0 | ... Q106: =+Q85+Q95 -> 2204930.6 | S106: =+S85+S95 -> 88693052 | T106: =+T85+T95 -> 51437436 | U106: =+U85+U95 -> 59884344 | V106: =+V85+V95 -> 3685294.7 | W106: =+W85+W95 -> 0 | X106: =+X85+X95 -> 31644074 | Y106: =+Y85+Y95 -> 5760289.2 | Z106: =+Z85+Z95 -> 0 | ... AG106: =+AG85+AG95 -> 13852007 | AI106: =+AI85+AI95 -> 74259059 | AJ106: =+AJ85+AJ95 -> 4.2810518e+08 | AL106: =+AL103-AL104 -> 16554262 | AM106: =+AM103-AM104 -> 4910087.4
A108: COSTO DE INGRESOS
A110: Ingresos por Operación de Plazas: | C110: =+SUM(C111:C119) -> 0 | D110: =+SUM(D111:D119) -> 0 | E110: =+SUM(E111:E119) -> 0 | F110: =+SUM(F111:F119) -> 0 | G110: =+SUM(G111:G119) -> 0 | H110: =+SUM(H111:H119) -> 0 | I110: =+SUM(I111:I119) -> 0 | J110: =+SUM(J111:J119) -> 0 | ... Q110: =+SUM(Q111:Q119) -> 0 | S110: =+SUM(S111:S119) -> 0 | T110: =+SUM(T111:T119) -> 0 | U110: =+SUM(U111:U119) -> 0 | V110: =+SUM(V111:V119) -> 0 | W110: =+SUM(W111:W119) -> 0 | X110: =+SUM(X111:X119) -> 0 | Y110: =+SUM(Y111:Y119) -> 0 | Z110: =+SUM(Z111:Z119) -> 0 | ... AG110: =+SUM(AG111:AG119) -> 0 | AI110: =+SUM(AI111:AI119) -> 0 | AJ110: =+SUM(AJ111:AJ119) -> 0
A111: Renta Mínima | C111: 0 | D111: 0 | E111: 0 | F111: 0 | G111: 0 | H111: 0 | I111: 0 | J111: 0 | K111: 0 | L111: 0 | M111: 0 | N111: 0 | O111: 0 | P111: 0 | Q111: 0 | S111: 0 | T111: 0 | U111: 0 | V111: 0 | W111: 0 | X111: 0 | Y111: 0 | Z111: 0 | AA111: 0 | AB111: 0 | AC111: 0 | AD111: 0 | AE111: 0 | AF111: 0 | AG111: 0 | AI111: =+SUM(R111:AF111) -> 0 | AJ111: =+SUM(S111:AG111) -> 0
A112: Renta Variable | C112: 0 | D112: 0 | E112: 0 | F112: 0 | G112: 0 | H112: 0 | I112: 0 | J112: 0 | K112: 0 | L112: 0 | M112: 0 | N112: 0 | O112: 0 | P112: 0 | Q112: 0 | S112: 0 | T112: 0 | U112: 0 | V112: 0 | W112: 0 | X112: 0 | Y112: 0 | Z112: 0 | AA112: 0 | AB112: 0 | AC112: 0 | AD112: 0 | AE112: 0 | AF112: 0 | AG112: 0 | AI112: =+SUM(R112:AF112) -> 0 | AJ112: =+SUM(S112:AG112) -> 0
A113: Cuota de Mantenimiento | C113: 0 | D113: 0 | E113: 0 | F113: 0 | G113: 0 | H113: 0 | I113: 0 | J113: 0 | K113: 0 | L113: 0 | M113: 0 | N113: 0 | O113: 0 | P113: 0 | Q113: 0 | S113: 0 | T113: 0 | U113: 0 | V113: 0 | W113: 0 | X113: 0 | Y113: 0 | Z113: 0 | AA113: 0 | AB113: 0 | AC113: 0 | AD113: 0 | AE113: 0 | AF113: 0 | AG113: 0 | AI113: =+SUM(R113:AF113) -> 0 | AJ113: =+SUM(S113:AG113) -> 0
A114: Publicidad | C114: 0 | D114: 0 | E114: 0 | F114: 0 | G114: 0 | H114: 0 | I114: 0 | J114: 0 | K114: 0 | L114: 0 | M114: 0 | N114: 0 | O114: 0 | P114: 0 | Q114: 0 | S114: 0 | T114: 0 | U114: 0 | V114: 0 | W114: 0 | X114: 0 | Y114: 0 | Z114: 0 | AA114: 0 | AB114: 0 | AC114: 0 | AD114: 0 | AE114: 0 | AF114: 0 | AG114: 0 | AI114: =+SUM(R114:AF114) -> 0 | AJ114: =+SUM(S114:AG114) -> 0
A115: Estacionamiento | C115: 0 | D115: 0 | E115: 0 | F115: 0 | G115: 0 | H115: 0 | I115: 0 | J115: 0 | K115: 0 | L115: 0 | M115: 0 | N115: 0 | O115: 0 | P115: 0 | Q115: 0 | S115: 0 | T115: 0 | U115: 0 | V115: 0 | W115: 0 | X115: 0 | Y115: 0 | Z115: 0 | AA115: 0 | AB115: 0 | AC115: 0 | AD115: 0 | AE115: 0 | AF115: 0 | AG115: 0 | AI115: =+SUM(R115:AF115) -> 0 | AJ115: =+SUM(S115:AG115) -> 0
A116: Cuotas Condominales | C116: 0 | D116: 0 | E116: 0 | F116: 0 | G116: 0 | H116: 0 | I116: 0 | J116: 0 | K116: 0 | L116: 0 | M116: 0 | N116: 0 | O116: 0 | P116: 0 | Q116: 0 | S116: 0 | T116: 0 | U116: 0 | V116: 0 | W116: 0 | X116: 0 | Y116: 0 | Z116: 0 | AA116: 0 | AB116: 0 | AC116: 0 | AD116: 0 | AE116: 0 | AF116: 0 | AG116: 0 | AI116: =+SUM(R116:AF116) -> 0 | AJ116: =+SUM(S116:AG116) -> 0
A117: Guantes | C117: 0 | D117: 0 | E117: 0 | F117: 0 | G117: 0 | H117: 0 | I117: 0 | J117: 0 | K117: 0 | L117: 0 | M117: 0 | N117: 0 | O117: 0 | P117: 0 | Q117: 0 | S117: 0 | T117: 0 | U117: 0 | V117: 0 | W117: 0 | X117: 0 | Y117: 0 | Z117: 0 | AA117: 0 | AB117: 0 | AC117: 0 | AD117: 0 | AE117: 0 | AF117: 0 | AG117: 0 | AI117: =+SUM(R117:AF117) -> 0 | AJ117: =+SUM(S117:AG117) -> 0
...

Sheet RESUMEN JUN26
B1: COMPARATIVO GENERAL | Q1: ESTADO DE RESULTADOS - PLAZAS 2026
B2: JUNIO DE 2026
B4: PLAZA | D4: INGRESOS NETOS | H4: GASTOS NETOS | L4: NOI AJUSTADO | P4: NOI AJUSTADO
D5: 46174 | E5: % CREC | F5: 45809 | H5: 46174 | I5: % CREC | J5: 45809 | L5: 46174 | M5: % CREC | N5: 45809 | P5: 46174 | Q5: 45809
B7: P2K | D7: =P2K!C106 -> 16254512 | E7: =(D7-F7)/F7 -> 0.051380394 | F7: =P2K!K106 -> 15460162 | H7: =P2K!C135 -> 2420105.8 | I7: =(H7-J7)/J7 -> -0.0076118831 | J7: =P2K!K135 -> 2438668.7 | L7: =D7-H7 -> 13834406 | M7: =L7/N7-1 -> 0.062428483 | N7: =F7-J7 -> 13021494 | P7: =L7/D7 -> 0.85111175 | Q7: =N7/F7 -> 0.84226112
B8: PSP | D8: =PSP!C106 -> 9448412.4 | E8: =(D8-F8)/F8 -> 0.02344062 | F8: =PSP!K106 -> 9232008.4 | H8: =PSP!C135 -> 2415620.8 | I8: =(H8-J8)/J8 -> 0.1028867 | J8: =PSP!K135 -> 2190271 | L8: =D8-H8 -> 7032791.6 | M8: =L8/N8-1 -> -0.0012703902 | N8: =F8-J8 -> 7041737.4 | P8: =L8/D8 -> 0.7443358 | Q8: =N8/F8 -> 0.76275249
B9: PRG | D9: =PRG!C106 -> 10766404 | E9: =(D9-F9)/F9 -> -0.063606945 | F9: =PRG!K106 -> 11497740 | H9: =PRG!C135 -> 1743304.4 | I9: =(H9-J9)/J9 -> 0.13862961 | J9: =PRG!K135 -> 1531054.9 | L9: =D9-H9 -> 9023099.4 | M9: =L9/N9-1 -> -0.094673971 | N9: =F9-J9 -> 9966685 | P9: =L9/D9 -> 0.83807923 | Q9: =N9/F9 -> 0.86683862
B10: PC | D10: =PC!C106 -> 857264.25 | E10: =(D10-F10)/F10 -> 0.38121938 | F10: =PC!K106 -> 620657.56 | H10: =PC!C135 -> 478836.49 | I10: =(H10-J10)/J10 -> 0.33241263 | J10: =PC!K135 -> 359375.52 | L10: =D10-H10 -> 378427.76 | M10: =L10/N10-1 -> 0.44834971 | N10: =F10-J10 -> 261282.04 | P10: =L10/D10 -> 0.44143654 | Q10: =N10/F10 -> 0.42097616
